Workbook

Sheet 0. Investment Committee
B2: ClaimPulse · Investment Committee Summary
B3: Team Finsighters · NMIMS Mumbai · PS_BFDL Motor Insurance Claims TAT. One page. Every figure on it is live from the model behind it; the tab reference tells you where.
B4: All figures at the Base plan: 60 per cent rollout of the addressable Motor OD book, filed FY2026 net-earned-premium basis.
B6: 1. THE ASK
B7: Ref | C7: Item | D7: Value | G7: Basis
B8: IC-01 | C8: Capital requested, build (one-off) | D8: ='3. Workings'!$D$55 -> 9.8904698 | G8: Fifteen costed components, Sheet 3 Part D
B9: IC-02 | C9: Capital requested, fully loaded | D9: ='5. Investor Metrics'!$E$36 -> 11.37404 | G9: Build plus a 15 per cent contingency, Sheet 5 RE-04
B10: IC-03 | C10: Annual run cost at steady state | D10: ='3. Workings'!$E$65 -> 3.9006065 | G10: Six lines, Sheet 3 Part E
B11: IC-04 | C11: Three-year total cost of ownership | D11: ='5. Investor Metrics'!$C$51 -> 22.639871 | G11: Build plus three years of run cost, Sheet 5 Part D
B12: All rupee figures in crore unless stated. The build sits with BFDL; the underwriting benefit lands in Bajaj General. Sheet 3 Part I splits every rupee by the entity that books it.
B14: 2. THE RETURN
B15: Ref | C15: Measure | D15: Conservative | E15: Base | F15: Aggressive | G15: What it means
B16: IC-05 | C16: Rollout of the addressable book | D16: ='3. Workings'!$D$12 -> 0.2 | E16: ='3. Workings'!$E$12 -> 0.6 | F16: ='3. Workings'!$F$12 -> 1 | G16: The only lever that separates the three plans.
B17: IC-06 | C17: Net annual benefit, steady state | D17: ='3. Workings'!$D$71 -> 12.85009 | E17: ='3. Workings'!$E$71 -> 43.310005 | F17: ='3. Workings'!$F$71 -> 75.277514 | G17: Gross benefit less full annual run cost.
B18: IC-07 | C18: Payback from project kickoff | D18: ='4. Forecast'!$D$50 -> 27.21363 | E18: ='4. Forecast'!$E$50 -> 16.842971 | F18: ='4. Forecast'!$F$50 -> 13.83294 | G18: Includes the ten-month build window with no benefit. The figure the deck quotes.
B19: IC-08 | C19: Five-year NPV at 12 per cent | D19: ='5. Investor Metrics'!$D$28 -> 35.585967 | E19: ='5. Investor Metrics'!$E$28 -> 145.93821 | F19: ='5. Investor Metrics'!$F$28 -> 261.79085 | G19: Project DCF, Sheet 5 Part B.
B20: IC-09 | C20: Combined ratio impact, Motor OD basis | D20: ='3. Workings'!$D$82 -> 0.76499125 | E20: ='3. Workings'!$E$82 -> 2.5826285 | F20: ='3. Workings'!$F$82 -> 4.4913773 | G20: Loss ratio plus expense ratio, against Motor OD earned premium.
B21: IC-10 | C21: Claim TAT, whole Motor OD book | D21: ='3. Workings'!$D$24 -> 8.382 | E21: ='3. Workings'!$E$24 -> 5.546 | F21: ='3. Workings'!$F$24 -> 2.71 | G21: Against 9.8 days today. Platform TAT on the rolled-out share.
B22: IC-11 | C22: Cost to serve per claim, after | D22: ='5. Investor Metrics'!$D$9 -> 369 | E22: ='5. Investor Metrics'!$E$9 -> 307.5 | F22: ='5. Investor Metrics'!$F$9 -> 246 | G22: Against Rs 1,750 today, identical across plans.
B23: IC-12 | C23: FTE capacity released | D23: ='3. Workings'!$D$113 -> 58.620505 | E23: ='3. Workings'!$E$113 -> 175.86152 | F23: ='3. Workings'!$F$113 -> 293.10253 | G23: Redeployed to complex claims, not removed.
B26: 3. THE DOWNSIDE · what has to go wrong, and what is left when it does
B27: Ref | C27: Case | D27: Net annual | E27: 5-yr NPV | F27: Payback, mo | G27: What is assumed
B28: IC-13 | C28: As modelled | D28: ='3. Workings'!$D$183 -> 43.310005 | E28: ='3. Workings'!$D$190 -> 145.93821 | F28: ='3. Workings'!$D$191 -> 16.842971 | G28: Base plan on published assumptions.
B29: IC-14 | C29: Operating reality misses | D29: ='3. Workings'!$E$183 -> 25.114505 | E29: ='3. Workings'!$E$190 -> 79.552766 | F29: ='3. Workings'!$E$191 -> 22.355635 | G29: In-house handling at Rs 83 a touch and five baseline touches.
B30: IC-15 | C30: Fraud disappoints | D30: ='3. Workings'!$F$183 -> 27.245157 | E30: ='3. Workings'!$F$190 -> 87.326352 | F30: ='3. Workings'!$F$191 -> 21.733642 | G30: Detection lands at 82 per cent, leakage halves, synthetic incidence quarters.
B31: IC-16 | C31: Adoption drags | D31: ='3. Workings'!$G$183 -> 23.557645 | E31: ='3. Workings'!$G$190 -> 74.35973 | F31: ='3. Workings'!$G$191 -> 22.49288 | G31: Rollout 35 per cent, green lane 50 per cent, live-capture friction doubled.
B32: IC-17 | C32: ALL THREE AT ONCE | D32: ='3. Workings'!$H$183 -> 4.2073585 | E32: ='3. Workings'!$H$190 -> 3.7610998 | F32: ='3. Workings'!$H$191 -> 47.66379 | G32: Every one of the above, applied together. Sheet 3 Part L.
B33: IC-18 | C33: Labour only, zero fraud benefit | D33: ='3. Workings'!$E$94 -> 3.7847953 | F33: ='3. Workings'!$E$97 -> 31.358536 | G33: No fraud, gate, synthetic or renewal value at all. Sheet 3 Part H.
B34: IC-19 | C34: INVESTOR GATE — five-year NPV positive in every case above? | D34: =IF(MIN('3. Workings'!$D$190,'3. Workings'!$E$190,'3. Workings'!$F$190,'3. Workings'!$G$190,'3. Workings'!$H$190)>0,"PASS","REVIEW") -> PASS | G34: Tested on the correlated case, not on the headline.
B35: No single assumption carries this case. Three separate things have to disappoint at the same time before the return compresses materially, and the build still repays even then.
B37: 4. EVIDENCE POSITION
B38: Ref | C38: Check | D38: Result | G38: Where it is done
B39: IC-20 | C39: Claim frequency implied by the model | D39: ='3. Workings'!$D$153 -> 0.057882969 | G39: Sheet 3 Part K. Industry norm is 5 to 15 per cent.
B40: IC-21 | C40: Frequency reconciliation | D40: ='3. Workings'!$D$155 -> PASS - inside the 5 to 15 per cent band | G40: B-01 and B-21 cross-check to an in-band frequency.
B41: IC-22 | C41: Stakeholder split ties to the P&L | D41: =IF(ABS('3. Workings'!$E$105)<0.0001,"TIE","REVIEW") -> TIE | G41: Sheet 3 W-60. Every rupee is attributed to an entity.
B42: IC-23 | C42: Scenario engine ties to the model | D42: ='8. Scenario Simulation'!$D$14 -> ALL SIX ANCHORS TIE - Part B is live against the current engine | G42: Sheet 8 Part A, six anchors.
B43: IC-24 | C43: Net earned premium basis | D43: ='1. Assumptions and Sources'!$D$8 -> 0.4988 | G43: Filed FY2026. Sheet 1 Table P carries three bases; Sheet 3 Part M restates the case on each.
B44: IC-25 | C44: Case on the Motor OD retention basis | D44: ='3. Workings'!$G$203 -> 60.471437 | G44: Sheet 3 Part M. The headline basis is the conservative one.
B46: 5. WHAT WE NEED FROM BAJAJ, AND WHAT WE COMMIT TO PROVE
B47: Ref | C47: Item | D47: Owner | G47: Why it matters
B48: IC-26 | C48: Manual touches per claim, and whether handling is in house or BPO | D48: Claims operations | G48: The two largest levers in the model. Sheet 3 Part L shows the case at the adverse end of both.
B49: IC-27 | C49: Motor OD claim count by ticket band | D49: Claims operations | G49: Replaces the Tier 4 average claim size and fixes the claim count directly.
B50: IC-28 | C50: Motor-specific fraud leakage | D50: Fraud unit | G50: Replaces the health-sector proxy at H-01 with an own-book figure.
B51: IC-29 | C51: Retained claim-media volume, and DPDP reuse position | D51: Claims operations and Legal | G51: The model values the existing image archive at zero. If it is usable, the build cost falls and the models start from a base no competitor can buy.
B52: IC-30 | C52: Exception-handling capacity today | D52: Claims operations | G52: Breakpoint H* on Sheet 10, the constraint most likely to bind first.
B54: Ref | C54: 90-day pilot gate | D54: Target | G54: Kill criterion
B55: IC-31 | C55: Measured GPU-seconds per claim, in-scope workload | D55: Below Sheet 13 breakeven | G55: Above it, the GenAI layer is bought rather than self-hosted. Decision rule is already in the model.
B56: IC-32 | C56: Shadow-mode fraud detection against held-out claims | D56: 82 per cent or better | G56: Below 82 per cent, the fraud lines are rebuilt at the achieved rate before any further capital is released.
B57: IC-33 | C57: Green-lane share achieved on live claims | D57: 50 per cent or better | G57: Below 50 per cent, rollout pauses and lane thresholds are recalibrated before Phase 3.
B58: IC-34 | C58: Exception-queue depth and P90 TAT | D58: Within claims-operations capacity | G58: If P90 TAT deteriorates, rollout holds at the pilot cohort until capacity is added.
B60: The pilot converts every Tier 4 input in this model into a measured one, and each gate carries a stated kill criterion. Capital beyond the pilot is released against these gates, not against this page.

Sheet Navigation
B2: ClaimPulse · Navigation
B3: Team Finsighters · NMIMS Mumbai · PS_BFDL Motor Insurance Claims TAT Reduction. Fifteen tabs. Click any tab name below to jump to it. Start at Sheet 0.
B4: THE ONE-LINE VERSION. A Rs 9.89 Cr build returns Rs 43.31 Cr a year at the Base plan, repays from project kickoff in 16.8 months, moves the Motor OD combined ratio by 2.58 pp, and stays NPV positive even when the operating, fraud and adoption assumptions all miss at the same time.
B5: HOW IT IS BUILT. Sheet 1 holds every input with a source and an evidence tier. Sheets 2 to 6 are pure formula and contain no typed numbers. Sheets 7 to 13 carry the evidence base, the stress testing and the architecture decisions. Sheet 0 is the one page an investment committee reads.
B7: THE MODEL · the numbers, and how they are produced
B8: Tab | C8: What it is | D8: What you will find here | E8: Go here first for
B9: Dashboard | C9: The one-page investor view | D9: Headline KPIs, the stakeholder scorecard, five-year cumulative value, and LIVE CHALLENGE LEVERS where you can type a value and watch the model move | E9: A five-minute read of the whole case
B10: 1. Assumptions and Sources | C10: Every input, every source | D10: Every input with a source and an evidence tier. Table G sets out how each line is constructed. Table H and Table N are the sensitivity register: which inputs move the answer and how each is validated. Table P carries three net-earned-premium bases; Table Q carries the rates that change inside the window. | E10: Checking whether a number is defensible
B11: 2. Summary | C11: The headline figures | D11: 19 headline metrics across Conservative, Base and Aggressive. Where the benefit comes from, line by line. The 24 self-audit integrity checks | E11: The investment case on one screen
B12: 3. Workings | C12: The engine | D12: The full chain from filed premium to net benefit. Part G is the insurance P&L bridge, Part H the downside tests, Part J the break-even analysis, Part K the claim-frequency reconciliation, Part L the correlated stress test, Part M the same case on three net-earned-premium bases. | E12: Understanding how a number was derived
B13: 4. Forecast | C13: Three-year view | D13: Year by year benefit, cost and cumulative position on the ramp convention | E13: The multi-year picture
B14: 5. Investor Metrics | C14: Return metrics | D14: NPV, IRR, ROIC, EVA and the unit economics block | E14: Anything an investment committee asks
B15: 6. Stakeholder Analysis | C15: Who gets what | D15: Quantified value split by stakeholder, every row a formula reading the P&L | E15: Who benefits, and who carries a cost
B16: 0. Investment Committee | C16: The one page that decides | D16: The ask, the return across all three plans, the correlated downside, the evidence position, the five data requests and the four pilot gates with their kill criteria. Every figure is live from the model behind it. | E16: Reading the case in two minutes
B17: THE RESEARCH · what could change, and what we would do about it
B18: Tab | C18: What it is | D18: What you will find here | E18: Go here first for
B19: 7. Trend Analysis | C19: The evidence base | D19: Twenty-one trends, each with a named publisher, a date and an evidence class. The four-domain trend vector map. The evidence gaps, carried openly with the handling for each. A full evidence-class summary. | E19: Where a fact came from, and whether it holds
B20: 8. Scenario Simulation | C20: Stress testing | D20: A live engine check that must tie before anything below it counts. Five scenarios at three intensities, all computed live from the engine. The correlated stress test sits at Sheet 3 Part L. Cross-domain synthesis and the scenario library. | E20: What breaks the case, and what does not
B21: 9. Landscape Impact | C21: The wider consequence | D21: All 17 scenarios across eight landscape dimensions, grouped into eight themes: market structure, ecosystem, regulation, business model, capital, talent, moat and demand | E21: What each scenario does beyond the P&L
B22: 10. Resilience and Breakpoints | C22: Where it stops working | D22: Nine named breakpoints, five computable today. Three resilience dimensions reported separately, never averaged. Component dependency matrix. What each severity grade means, and how the platform repurposes at the worst one | E22: The honest limits of the case
B23: 11. Strategy and Early Warning | C23: The response | D23: Strategic response per scenario, quarterly indicators to monitor, the management question for each, ten driver-interaction mechanisms, and a 31-metric KPI framework across seven layers | E23: What management should do, and watch
B25: SUGGESTED READING PATH
B26: 1. | C26: Sheet 0 Investment Committee. That is the case. Sheet 2 Summary if you want the same thing with more lines.
B27: 2. | C27: Sheet 8 Part A. Confirm the six engine anchors tie before trusting any scenario number below them.
B28: 3. | C28: Sheet 3 Part L. The correlated downside: what is left when the operating, fraud and adoption assumptions all miss together.
B29: 4. | C29: Sheet 1 Table H. The sensitivity register: which assumptions move the answer, and how each is validated.
B30: 5. | C30: Sheet 10 Part A. The nine breakpoints, including the one the pilot is designed to measure first.
B31: 6. | C31: Sheets 7, 9, 10 and 11 as reference, when a specific trend, consequence, breakpoint or response is queried.
B33: THREE THINGS TO KNOW BEFORE QUOTING A NUMBER
B34: 1. | C34: Combined ratio is reported on two bases and they are not interchangeable. 2.58 pp on a Motor OD basis is 0.42 pp on the group book. Never subtract the Motor OD figure from a group combined ratio.
B35: 2. | C35: Payback from project kickoff, Sheet 4 FS-05, is the figure the deck quotes. It includes the ten-month build window. The steady-state figure on Sheet 3 Part F is shorter because it excludes that window.
B36: 3. | C36: Net earned premium runs on the filed FY2026 basis. Sheet 1 Table P and Sheet 3 Part M carry the other two bases; the case is stronger on the Motor OD retention basis, so the headline is the conservative one.
B38: Sheet numbering on this page matches the tab names exactly. Sheets 12 and 13 sit below because they were added as the cost and architecture annexures.
B40: 12. Cost Architecture | C40: Where the money goes | D40: The full build and run cost stack, the nine decisions taken to reduce it, fixed versus variable ceiling, build-versus-buy on verified vendor rates, and the unpriced value of Bajaj's historical claim-image archive | E40: Any question about cost, efficiency or AI spend
B42: 13. GenAI Build vs Buy | C42: The architecture decision | D42: Incremental five-year cost of adding generative AI via API versus self-hosting, with the baseline conventional-ML and moat layers netted out. Part G re-runs the decision on the rate card that applies from 1 September 2026. | E42: Whether to buy or build the GenAI layer

Sheet Dashboard
D2: Claims Pulse | S2: Executive Business Case Dashboard | CZ2: Section 1 helper tables | DB2: Section 2 — Financial Impact | DD2: Section 3 — Investment Case | DH2: Section 1 helper tables — STAKEHOLDER IMPACT
BH3: Scenario
BH4: Aggressive | CZ4: Table A — TAT comparison | DB4: Chart 1 — Annual Benefit Composition | DD4: Five-Year Cumulative Value Chart | DH4: Table S1 — Value split by beneficiary (Rs Cr)
D5: AI Powered Claims Transformation | S5: Transforming Motor OD Claims | Faster. Smarter. Fraud - Resilient | CZ5: Metric | DA5: Value | DB5: Benefit Component | DC5: Value | DD5: Year | DE5: Annual Net Cash Flow | DF5: Cumulative Net Position | DH5: Beneficiary | DI5: Value
BH6: All values in Rs. Cr unless stated otherwise. | CZ6: Current | DA6: =INDEX('3. Workings'!$D$22:$F$22,MATCH($BH$4,'3. Workings'!$D$6:$F$6,0)) -> 9.8 | DB6: Labour | DC6: =INDEX('3. Workings'!$D$30:$F$30,MATCH($BH$4,'3. Workings'!$D$68:$F$68,0)) -> 41.255831 | DD6: Year 0 | DE6: =INDEX('5. Investor Metrics'!$D$21:$F$21,MATCH($BH$4,'5. Investor Metrics'!$D$20:$F$20,0)) -> -9.8904698 | DF6: =DE6 -> -9.8904698 | DH6: Claims operations (expense ratio) | DI6: =INDEX('3. Workings'!$D$101:$F$101,MATCH($BH$4,'3. Workings'!$D$100:$F$100,0)) -> 40.465826
CZ7: ClaimPulse – Selected Scenario | DA7: =INDEX('3. Workings'!$D$24:$F$24,MATCH($BH$4,'3. Workings'!$D$6:$F$6,0)) -> 2.71 | DB7: Fraud Graph | DC7: =INDEX('3. Workings'!$D$31:$F$31,MATCH($BH$4,'3. Workings'!$D$68:$F$68,0)) -> 18.418297 | DD7: Year 1 | DE7: =INDEX('5. Investor Metrics'!$D$22:$F$22,MATCH($BH$4,'5. Investor Metrics'!$D$20:$F$20,0)) -> 30.964649 | DF7: =DF6+DE7 -> 21.074179 | DH7: Underwriting (loss ratio) | DI7: =INDEX('3. Workings'!$D$102:$F$102,MATCH($BH$4,'3. Workings'!$D$100:$F$100,0)) -> 39.142943
DB8: Synthetic Media | DC8: =INDEX('3. Workings'!$D$33:$F$33,MATCH($BH$4,'3. Workings'!$D$68:$F$68,0)) -> 10.492258 | DD8: Year 2 | DE8: =INDEX('5. Investor Metrics'!$D$23:$F$23,MATCH($BH$4,'5. Investor Metrics'!$D$20:$F$20,0)) -> 74.820391 | DF8: =DF7+DE8 -> 95.89457 | DH8: BFDL distribution (renewal) | DI8: =INDEX('3. Workings'!$D$103:$F$103,MATCH($BH$4,'3. Workings'!$D$100:$F$100,0)) -> 0.96007586
DB9: Capture Integrity Gate | DC9: =INDEX('3. Workings'!$D$32:$F$32,MATCH($BH$4,'3. Workings'!$D$68:$F$68,0)) -> 10.232387 | DD9: Year 3 | DE9: =INDEX('5. Investor Metrics'!$D$24:$F$24,MATCH($BH$4,'5. Investor Metrics'!$D$20:$F$20,0)) -> 88.945577 | DF9: =DF8+DE9 -> 184.84015
D10: =IF((INDEX('3. Workings'!$D$13:$F$13,MATCH($BH$4,'3. Workings'!$D$6:$F$6,0)))>=1000000000,TEXT((INDEX('3. Workings'!$D$13:$F$13,MATCH($BH$4,'3. Workings'!$D$6:$F$6,0)))/1000000000,"0.0")&"B Claims",IF((INDEX('3. Workings'!$D$13:$F$13,MATCH($BH$4,'3. Workings'!$D$6:$F$6,0)))>=1000000,TEXT((INDEX('3. Workings'!$D$13:$F$13,MATCH($BH$4,'3. Workings'!$D$6:$F$6,0)))/1000000,"0.0")&"M Claims",IF((INDEX('3. Workings'!$D$13:$F$13,MATCH($BH$4,'3. Workings'!$D$6:$F$6,0)))>=1000,TEXT((INDEX('3. Workings'!$D$13:$F$13,MATCH($BH$4,'3. Workings'!$D$6:$F$6,0)))/1000,"0.0")&"K Claims",TEXT((INDEX('3. Workings'!$D$13:$F$13,MATCH($BH$4,'3. Workings'!$D$6:$F$6,0))),"0.0")&" Claims"))) -> 274.3K Claims | S10: =TEXT(INDEX('3. Workings'!$D$22:$F$22,MATCH($BH$4,'3. Workings'!$D$6:$F$6,0)),"0.0")&" Days" -> 9.8 Days | AB10: =TEXT(INDEX('3. Workings'!$D$24:$F$24,MATCH($BH$4,'3. Workings'!$D$6:$F$6,0)),"0.0")&" Days" -> 2.7 Days | AN10: =TEXT(INDEX('3. Workings'!$D$26:$F$26,MATCH($BH$4,'3. Workings'!$D$6:$F$6,0)),"0.0%") -> 72.3% | BC10: ="₹"&TEXT(INDEX('3. Workings'!$D$71:$F$71,MATCH($BH$4,'3. Workings'!$D$68:$F$68,0)),"0.0")&" Cr" -> ₹75.3 Cr | BR10: =TEXT(INDEX('4. Forecast'!$D$50:$F$50,MATCH($BH$4,'4. Forecast'!$D$45:$F$45,0)),"0.0")&" Months" -> 13.8 Months | CG10: =TEXT(INDEX('3. Workings'!$D$82:$F$82,MATCH($BH$4,'3. Workings'!$D$77:$F$77,0)),"0.0")&" pp" -> 4.5 pp | CZ10: Table B — Manual touches | DB10: Renewal | DC10: =INDEX('3. Workings'!$D$34:$F$34,MATCH($BH$4,'3. Workings'!$D$68:$F$68,0)) -> 0.96007586 | DD10: Year 4 | DE10: =INDEX('5. Investor Metrics'!$D$25:$F$25,MATCH($BH$4,'5. Investor Metrics'!$D$20:$F$20,0)) -> 96.683842 | DF10: =DF9+DE10 -> 281.52399 | DH10: Table S2 — Claimant impact
CZ11: Metric | DA11: Value | DB11: Friction Cost | DC11: =INDEX('3. Workings'!$D$35:$F$35,MATCH($BH$4,'3. Workings'!$D$68:$F$68,0)) -> -0.79000528 | DD11: Year 5 | DE11: =INDEX('5. Investor Metrics'!$D$26:$F$26,MATCH($BH$4,'5. Investor Metrics'!$D$20:$F$20,0)) -> 105.09534 | DF11: =DF10+DE11 -> 386.61932 | DH11: Metric | DI11: Value
D12: Annual vol. at selected scenario | S12: Current | AB12: ClaimPulse | AN12: Reduction | BC12: Benefit | BR12: From Project Kickoff | CG12: Improvement vs. Current | CZ12: Current – Whole Book | DA12: =INDEX('1. Assumptions and Sources'!$D$23:$D$45,MATCH("Manual touches per claim today",'1. Assumptions and Sources'!$C$23:$C$45,0)) -> 7 | DH12: Claimant-days returned per year | DI12: =INDEX('3. Workings'!$D$107:$F$107,MATCH($BH$4,'3. Workings'!$D$100:$F$100,0)) -> 1944839.4
CZ13: ClaimPulse – Whole Book | DA13: =(INDEX('3. Workings'!$D$12:$F$12,MATCH($BH$4,'3. Workings'!$D$6:$F$6,0)))*(INDEX('3. Workings'!$D$19:$F$19,MATCH($BH$4,'3. Workings'!$D$6:$F$6,0)))+(1-(INDEX('3. Workings'!$D$12:$F$12,MATCH($BH$4,'3. Workings'!$D$6:$F$6,0))))*(INDEX('1. Assumptions and Sources'!$D$23:$D$45,MATCH("Manual touches per claim today",'1. Assumptions and Sources'!$C$23:$C$45,0))) -> 1.23 | DH13: Claims auto-settled, zero human touch | DI13: =INDEX('3. Workings'!$D$108:$F$108,MATCH($BH$4,'3. Workings'!$D$100:$F$100,0)) -> 178299.8
DB14: 2. Annual Run Cost — Helper Table | DH14: Claims still reviewed by a human | DI14: =INDEX('3. Workings'!$D$109:$F$109,MATCH($BH$4,'3. Workings'!$D$100:$F$100,0)) -> 96007.586
DH15: TAT saved per on-platform claim (days) | DI15: =INDEX('3. Workings'!$D$106:$F$106,MATCH($BH$4,'3. Workings'!$D$100:$F$100,0)) -> 7.09
CL16: ="Selected scenario: "&$BH$4 -> Selected scenario: Aggressive | CZ16: Table C — Annual manual touches avoided | DB16: Cost Component | DC16: Value | DD16: Section 4 - Investment P&L | DH16: Share of book still on 9.8-day journey | DI16: =INDEX('3. Workings'!$D$110:$F$110,MATCH($BH$4,'3. Workings'!$D$100:$F$100,0)) -> 0
CZ17: Metric | DA17: Value | DB17: GPU Compute | DC17: =INDEX('3. Workings'!$D$59:$F$59,MATCH($BH$4,'3. Workings'!$D$58:$F$58,0)) -> 3.1369715
D18: ="WHERE THE GROSS BENEFIT LANDS · ₹"&TEXT(DI6+DI7+DI8,"0.0")&" Cr" -> WHERE THE GROSS BENEFIT LANDS · ₹80.6 Cr | AG18: WHAT THE CLAIMANT GETS | BI18: CAPACITY RELEASED, NOT HEADCOUNT CUT | CZ18: Current annual touches | DA18: =(INDEX('3. Workings'!$D$11:$F$11,MATCH($BH$4,'3. Workings'!$D$6:$F$6,0)))*(INDEX('1. Assumptions and Sources'!$D$23:$D$45,MATCH("Manual touches per claim today",'1. Assumptions and Sources'!$C$23:$C$45,0))) -> 1920151.7 | DB18: Storage | DC18: =INDEX('3. Workings'!$D$60:$F$60,MATCH($BH$4,'3. Workings'!$D$58:$F$58,0)) -> 0.33983942 | DD18: Helper Table A — Motor OD P&L Bridge | DH18: Table S3 — Claims workforce
CZ19: After ClaimPulse annual touches | DA19: =(INDEX('3. Workings'!$D$11:$F$11,MATCH($BH$4,'3. Workings'!$D$6:$F$6,0)))*((INDEX('3. Workings'!$D$12:$F$12,MATCH($BH$4,'3. Workings'!$D$6:$F$6,0)))*(INDEX('3. Workings'!$D$19:$F$19,MATCH($BH$4,'3. Workings'!$D$6:$F$6,0)))+(1-(INDEX('3. Workings'!$D$12:$F$12,MATCH($BH$4,'3. Workings'!$D$6:$F$6,0))))*(INDEX('1. Assumptions and Sources'!$D$23:$D$45,MATCH("Manual touches per claim today",'1. Assumptions and Sources'!$C$23:$C$45,0)))) -> 337398.09 | DB19: MLOps | DC19: =INDEX('3. Workings'!$D$61:$F$61,MATCH($BH$4,'3. Workings'!$D$58:$F$58,0)) -> 0.80052 | DD19: Metric | DE19: Value | DH19: Metric | DI19: Value
AH20: =TEXT(DI12/100000,"0.0")&" lakh claimant-days returned" -> 19.4 lakh claimant-days returned | DB20: Operations | DC20: =INDEX('3. Workings'!$D$62:$F$62,MATCH($BH$4,'3. Workings'!$D$58:$F$58,0)) -> 0.6440004 | DD20: Loss Ratio Improvement | DE20: =INDEX('3. Workings'!$D$80:$F$80,MATCH($BH$4,'3. Workings'!$D$77:$F$77,0)) -> 2.3656053 | DH20: Manual touches avoided per year | DI20: =INDEX('3. Workings'!$D$111:$F$111,MATCH($BH$4,'3. Workings'!$D$100:$F$100,0)) -> 1582753.6
CZ21: Table D — Claim Lane Mix | DB21: Security & Compliance | DC21: =INDEX('3. Workings'!$D$63:$F$63,MATCH($BH$4,'3. Workings'!$D$58:$F$58,0)) -> 0.2499996 | DD21: Expense Ratio Improvement | DE21: =INDEX('3. Workings'!$D$81:$F$81,MATCH($BH$4,'3. Workings'!$D$77:$F$77,0)) -> 2.125772 | DH21: Claims-handling hours released | DI21: =INDEX('3. Workings'!$D$112:$F$112,MATCH($BH$4,'3. Workings'!$D$100:$F$100,0)) -> 527584.55
CZ22: Metric | DA22: Value | DB22: Legal & Regulatory | DC22: =INDEX('3. Workings'!$D$64:$F$64,MATCH($BH$4,'3. Workings'!$D$58:$F$58,0)) -> 0.12 | DD22: Motor OD Combined Ratio Improvement | DE22: =INDEX('3. Workings'!$D$82:$F$82,MATCH($BH$4,'3. Workings'!$D$77:$F$77,0)) -> 4.4913773 | DH22: FTE capacity released | DI22: =INDEX('3. Workings'!$D$113:$F$113,MATCH($BH$4,'3. Workings'!$D$100:$F$100,0)) -> 293.10253
CZ23: Straight through (Green) | DA23: =INDEX('1. Assumptions and Sources'!$D$23:$D$45,MATCH("Green lane share",'1. Assumptions and Sources'!$C$23:$C$45,0)) -> 0.65 | DB23: Total Annual Run Cost | DC23: =INDEX('3. Workings'!$D$65:$F$65,MATCH($BH$4,'3. Workings'!$D$58:$F$58,0)) -> 5.2913309 | DH23: Adjuster throughput multiple | DI23: =INDEX('3. Workings'!$D$114:$F$114,MATCH($BH$4,'3. Workings'!$D$100:$F$100,0)) -> 5.6910569
CZ24: Complex (Amber) | DA24: =INDEX('1. Assumptions and Sources'!$D$23:$D$45,MATCH("Amber lane share",'1. Assumptions and Sources'!$C$23:$C$45,0)) -> 0.25
CZ25: Investigation (Red) | DA25: =INDEX('1. Assumptions and Sources'!$D$23:$D$45,MATCH("Red lane share",'1. Assumptions and Sources'!$C$23:$C$45,0)) -> 0.1 | DB25: 3. Financial Bridge | DH25: Table S4 — Surveyor deployment
DB26: Metric | DC26: Value | DH26: Metric | DI26: Value
CZ27: Table E - Cost per claim | DB27: Gross Annual Benefit | DC27: =INDEX('3. Workings'!$D$69:$F$69,MATCH($BH$4,'3. Workings'!$D$68:$F$68,0)) -> 80.568845 | DH27: Physical surveys — today | DI27: =INDEX('3. Workings'!$D$115:$F$115,MATCH($BH$4,'3. Workings'!$D$100:$F$100,0)) -> 150869.06
CZ28: Metric | DA28: Value | DB28: Annual Run Cost | DC28: =-INDEX('3. Workings'!$D$70:$F$70,MATCH($BH$4,'3. Workings'!$D$68:$F$68,0)) -> -5.2913309 | DH28: Physical surveys — ClaimPulse | DI28: =INDEX('3. Workings'!$D$116:$F$116,MATCH($BH$4,'3. Workings'!$D$100:$F$100,0)) -> 27430.739
DB29: Net Annual Benefit | DC29: =INDEX('3. Workings'!$D$71:$F$71,MATCH($BH$4,'3. Workings'!$D$68:$F$68,0)) -> 75.277514 | DH29: Surveyor visits avoided | DI29: =INDEX('3. Workings'!$D$117:$F$117,MATCH($BH$4,'3. Workings'!$D$100:$F$100,0)) -> 123438.33
DH31: Table S5 — Governance and moat spend (Rs Cr)
CZ32: Current Cost / Claim | DA32: =INDEX('5. Investor Metrics'!$D$7:$F$7,MATCH($BH$4,'5. Investor Metrics'!$D$6:$F$6,0)) -> 1750 | DH32: Component | DI32: Value
CZ33: ClaimPulse Cost / Claim | DA33: =INDEX('5. Investor Metrics'!$D$9:$F$9,MATCH($BH$4,'5. Investor Metrics'!$D$6:$F$6,0)) -> 246 | DH33: Capture Integrity Gate build | DI33: =INDEX('3. Workings'!$D$120:$F$120,MATCH($BH$4,'3. Workings'!$D$100:$F$100,0)) -> 1.9148541
E34: Both sides of the combined ratio move. Neither side carries the case alone. | BJ34: ="At the "&$BH$4&" rollout, ClaimPulse releases "&TEXT(DI22,"0")&" FTE of claims-handling capacity and lets the same team clear "&TEXT(DI23,"0.0")&"x the claims it handles today." -> At the Aggressive rollout, ClaimPulse releases 293 FTE of claims-handling capacity and lets the same team clear 5.7x the claims it handles today. | DB34: Gross Annual Benefit | DC34: =INDEX('3. Workings'!$D$69:$F$69,MATCH($BH$4,'3. Workings'!$D$68:$F$68,0)) -> 80.568845 | DH34: Governance, audit and explainability build | DI34: =INDEX('3. Workings'!$D$119:$F$119,MATCH($BH$4,'3. Workings'!$D$100:$F$100,0)) -> 1.0013452
DB35: Annual Run Cost | DC35: =-INDEX('3. Workings'!$D$70:$F$70,MATCH($BH$4,'3. Workings'!$D$68:$F$68,0)) -> -5.2913309 | DH35: Rest of the build | DI35: ='3. Workings'!$D$55-DI33-DI34 -> 6.9742705
DB36: Net Annual Benefit | DC36: =INDEX('3. Workings'!$D$71:$F$71,MATCH($BH$4,'3. Workings'!$D$68:$F$68,0)) -> 75.277514 | DH36: Annual compliance and legal run cost | DI36: =INDEX('3. Workings'!$D$121:$F$121,MATCH($BH$4,'3. Workings'!$D$100:$F$100,0)) -> 0.3699996
F37: THE STAKEHOLDER SCORECARD | AQ37: SURVEYORS: REDEPLOYED, NOT DISPLACED | BL37: ="WHAT THE BUILD BUYS THE REGULATOR · "&TEXT(DI37,"0.0%")&" OF THE BUILD" -> WHAT THE BUILD BUYS THE REGULATOR · 29.5% OF THE BUILD | DH37: Gate + governance as share of build | DI37: =INDEX('3. Workings'!$D$122:$F$122,MATCH($BH$4,'3. Workings'!$D$100:$F$100,0)) -> 0.29484942
F39: Stakeholder | Q39: Outcome | AB39: Value | DH39: Table S6 — Who funds vs who books (Rs Cr)
DH40: Entity | DI40: Value
F41: Policyholder | Q41: Claimant-days returned per year | AB41: =DI12 -> 1944839.4 | DH41: BFDL — capital deployed (one-off) | DI41: =INDEX('3. Workings'!$D$126:$F$126,MATCH($BH$4,'3. Workings'!$D$100:$F$100,0)) -> 9.8904698
DH42: Bajaj General — annual underwriting value | DI42: =INDEX('3. Workings'!$D$127:$F$127,MATCH($BH$4,'3. Workings'!$D$100:$F$100,0)) -> 74.317438
F43: Claims operations | Q43: FTE capacity released | AB43: =DI22 -> 293.10253 | DH43: BFDL — annual distribution value | DI43: =INDEX('3. Workings'!$D$128:$F$128,MATCH($BH$4,'3. Workings'!$D$100:$F$100,0)) -> 0.96007586
DH44: Group consolidated net annual benefit | DI44: =INDEX('3. Workings'!$D$129:$F$129,MATCH($BH$4,'3. Workings'!$D$100:$F$100,0)) -> 75.277514
F45: Underwriting / CFO | Q45: Combined ratio improvement, Motor OD | AB45: =DE22 -> 4.4913773
DH46: Table S7 — What the design costs the people it touches
F47: BFDL / Bajaj Markets | Q47: Distribution income retained | AB47: =DI8 -> 0.96007586 | DH47: Metric | DI47: Value
DH48: Honest claimants downgraded to amber | DI48: =INDEX('3. Workings'!$D$123:$F$123,MATCH($BH$4,'3. Workings'!$D$100:$F$100,0)) -> 21944.591
F49: Group leadership | Q49: Group consolidated net annual benefit | AB49: =DI44 -> 75.277514 | DH49: Cost we carry (Rs Cr) | DI49: =INDEX('3. Workings'!$D$124:$F$124,MATCH($BH$4,'3. Workings'!$D$100:$F$100,0)) -> 0.79000528
DH50: Friction as share of gross benefit | DI50: =INDEX('3. Workings'!$D$125:$F$125,MATCH($BH$4,'3. Workings'!$D$100:$F$100,0)) -> 0.0098053446
F51: Surveyors | Q51: Physical survey visits avoided | AB51: =DI29 -> 123438.33
DH52: Table S8 — Strategic context (flat, filed)
F53: Garages | Q53: Estimate-to-approval days saved | AB53: =INDEX('3. Workings'!$D$118:$F$118,MATCH($BH$4,'3. Workings'!$D$100:$F$100,0)) -> 3 | DH53: Metric | DI53: Value
DH54: Motor OD premium at risk per 1 pp of share | DI54: =INDEX('3. Workings'!$D$130:$F$130,MATCH($BH$4,'3. Workings'!$D$100:$F$100,0)) -> 427.48711
F55: IRDAI / regulator | Q55: Governance & explainability build spend | AB55: =DI34 -> 1.0013452 | DH55: Annualised Q1 FY27 underwriting loss | DI55: =INDEX('3. Workings'!$D$131:$F$131,MATCH($BH$4,'3. Workings'!$D$100:$F$100,0)) -> 520
DH56: Share of that loss offset by ClaimPulse | DI56: =INDEX('3. Workings'!$D$132:$F$132,MATCH($BH$4,'3. Workings'!$D$100:$F$100,0)) -> 0.14476445
DH58: Table S9 — Claims-handling hours (Panel 3 source)
DH59: Metric | DI59: Value
DH60: Hours today | DI60: =INDEX('3. Workings'!$D$133:$F$133,MATCH($BH$4,'3. Workings'!$D$100:$F$100,0)) -> 640050.58
AU61: ="Selected scenario: "&$BH$4 -> Selected scenario: Aggressive | CL61: ="Selected scenario: "&$BH$4 -> Selected scenario: Aggressive | DH61: Hours after ClaimPulse | DI61: =INDEX('3. Workings'!$D$134:$F$134,MATCH($BH$4,'3. Workings'!$D$100:$F$100,0)) -> 112466.03
D63: COST TO SERVE PER CLAIM (₹) | U63: ANNUAL MANUAL TOUCHES (WHOLE BOOK) | AL63: CLAIM LINE MIX (BY VOLUME) | BE63: ANNUAL BENEFIT COMPOSITION (₹ Cr) | DH63: Table S10 — Payback ladder (Section 5 chart source)
DH64: Basis | DI64: Months
DH65: ="As modelled" -> As modelled | DI65: =IF(ISNUMBER(INDEX('3. Workings'!$D$95:$F$95,MATCH($BH$4,'3. Workings'!$D$89:$F$89,0))),MIN(INDEX('3. Workings'!$D$95:$F$95,MATCH($BH$4,'3. Workings'!$D$89:$F$89,0)),60),60) -> 1.5766413
DH66: ="Realistic downside" -> Realistic downside | DI66: =IF(ISNUMBER(INDEX('3. Workings'!$D$96:$F$96,MATCH($BH$4,'3. Workings'!$D$89:$F$89,0))),MIN(INDEX('3. Workings'!$D$96:$F$96,MATCH($BH$4,'3. Workings'!$D$89:$F$89,0)),60),60) -> 4.2414317
DH67: ="Absolute floor"&IF(ISNUMBER(INDEX('3. Workings'!$D$97:$F$97,MATCH($BH$4,'3. Workings'!$D$89:$F$89,0))),IF(INDEX('3. Workings'!$D$97:$F$97,MATCH($BH$4,'3. Workings'!$D$89:$F$89,0))>60," — capped at 60",""), " — does not pay back") -> Absolute floor | DI67: =IF(ISNUMBER(INDEX('3. Workings'!$D$97:$F$97,MATCH($BH$4,'3. Workings'!$D$89:$F$89,0))),MIN(INDEX('3. Workings'!$D$97:$F$97,MATCH($BH$4,'3. Workings'!$D$89:$F$89,0)),60),60) -> 15.787552
DH69: From project kickoff (reference, not a bar) | DI69: =INDEX('4. Forecast'!$D$50:$F$50,MATCH($BH$4,'4. Forecast'!$D$45:$F$45,0)) -> 13.83294
DH70: Cap applied? | DI70: =IF(ISNUMBER(INDEX('3. Workings'!$D$97:$F$97,MATCH($BH$4,'3. Workings'!$D$89:$F$89,0))),IF(INDEX('3. Workings'!$D$97:$F$97,MATCH($BH$4,'3. Workings'!$D$89:$F$89,0))>60,"YES — floor bar capped at 60","no"),"YES — floor does not pay back, plotted at 60") -> no
D75: ="At the "&$BH$4&" rollout, ClaimPulse reduces cost to serve by "&TEXT((1-((INDEX('5. Investor Metrics'!$D$9:$F$9,MATCH($BH$4,'5. Investor Metrics'!$D$6:$F$6,0)))/(INDEX('5. Investor Metrics'!$D$7:$F$7,MATCH($BH$4,'5. Investor Metrics'!$D$6:$F$6,0))))),"0.0%")&" and eliminates "&TEXT((((INDEX('3. Workings'!$D$11:$F$11,MATCH($BH$4,'3. Workings'!$D$6:$F$6,0)))*(INDEX('1. Assumptions and Sources'!$D$23:$D$45,MATCH("Manual touches per claim today",'1. Assumptions and Sources'!$C$23:$C$45,0))))-((INDEX('3. Workings'!$D$11:$F$11,MATCH($BH$4,'3. Workings'!$D$6:$F$6,0)))*((INDEX('3. Workings'!$D$12:$F$12,MATCH($BH$4,'3. Workings'!$D$6:$F$6,0)))*(INDEX('3. Workings'!$D$19:$F$19,MATCH($BH$4,'3. Workings'!$D$6:$F$6,0)))+(1-(INDEX('3. Workings'!$D$12:$F$12,MATCH($BH$4,'3. Workings'!$D$6:$F$6,0))))*(INDEX('1. Assumptions and Sources'!$D$23:$D$45,MATCH("Manual touches per claim today",'1. Assumptions and Sources'!$C$23:$C$45,0))))))/1000000,"0.00")&"M manual touches annually, with "&TEXT(INDEX('1. Assumptions and Sources'!$D$23:$D$45,MATCH("Green lane share",'1. Assumptions and Sources'!$C$23:$C$45,0)),"0%")&" of claims flowing through the straight-through lane." -> At the Aggressive rollout, ClaimPulse reduces cost to serve by 85.9% and eliminates 1.58M manual touches annually, with 65% of claims flowing through the straight-through lane.
AU79: ="Selected scenario: "&$BH$4 -> Selected scenario: Aggressive
D81: INVESTMENT PROFILE | R81: Five-Year Cumulative Value | BE81: ANNUAL VALUE BRIDGE
D83: Build Cost | J83: =TEXT(INDEX('5. Investor Metrics'!$D$35:$F$35,MATCH($BH$4,'5. Investor Metrics'!$D$32:$F$32,0)),"0.00") -> 9.89
D86: Net Annual Benefit | J86: =TEXT(INDEX('5. Investor Metrics'!$D$33:$F$33,MATCH($BH$4,'5. Investor Metrics'!$D$32:$F$32,0)),"0.00") -> 75.28
D89: Payback from Project Kickoff | J89: =TEXT(IF(((INDEX('5. Investor Metrics'!$D$22:$F$22,MATCH(($BH$4),'5. Investor Metrics'!$D$32:$F$32,0)))-(INDEX('5. Investor Metrics'!$D$35:$F$35,MATCH(($BH$4),'5. Investor Metrics'!$D$32:$F$32,0))))>=0,10+(INDEX('5. Investor Metrics'!$D$35:$F$35,MATCH(($BH$4),'5. Investor Metrics'!$D$32:$F$32,0)))/(INDEX('5. Investor Metrics'!$D$22:$F$22,MATCH(($BH$4),'5. Investor Metrics'!$D$32:$F$32,0)))*12,IF((((INDEX('5. Investor Metrics'!$D$22:$F$22,MATCH(($BH$4),'5. Investor Metrics'!$D$32:$F$32,0)))-(INDEX('5. Investor Metrics'!$D$35:$F$35,MATCH(($BH$4),'5. Investor Metrics'!$D$32:$F$32,0))))+(INDEX('5. Investor Metrics'!$D$23:$F$23,MATCH(($BH$4),'5. Investor Metrics'!$D$32:$F$32,0))))>=0,22+(-((INDEX('5. Investor Metrics'!$D$22:$F$22,MATCH(($BH$4),'5. Investor Metrics'!$D$32:$F$32,0)))-(INDEX('5. Investor Metrics'!$D$35:$F$35,MATCH(($BH$4),'5. Investor Metrics'!$D$32:$F$32,0)))))/(INDEX('5. Investor Metrics'!$D$23:$F$23,MATCH(($BH$4),'5. Investor Metrics'!$D$32:$F$32,0)))*12,34+(-(((INDEX('5. Investor Metrics'!$D$22:$F$22,MATCH(($BH$4),'5. Investor Metrics'!$D$32:$F$32,0)))-(INDEX('5. Investor Metrics'!$D$35:$F$35,MATCH(($BH$4),'5. Investor Metrics'!$D$32:$F$32,0))))+(INDEX('5. Investor Metrics'!$D$23:$F$23,MATCH(($BH$4),'5. Investor Metrics'!$D$32:$F$32,0)))))/(INDEX('5. Investor Metrics'!$D$24:$F$24,MATCH(($BH$4),'5. Investor Metrics'!$D$32:$F$32,0)))*12)),"0.00") -> 13.83
D92: 3-Year NPV | J92: =TEXT(INDEX('4. Forecast'!$D$49:$F$49,MATCH($BH$4,'4. Forecast'!$D$45:$F$45,0)),"0.00") -> 140.71
D95: 5-Year NPV | J95: =TEXT(INDEX('5. Investor Metrics'!$D$28:$F$28,MATCH($BH$4,'5. Investor Metrics'!$D$20:$F$20,0)),"0.00") -> 261.79
BE97: ="At the "&$BH$4&" rollout, every ₹1 of annual run cost generates ₹"&TEXT(INDEX('3. Workings'!$D$69:$F$69,MATCH($BH$4,'3. Workings'!$D$68:$F$68,0))/INDEX('3. Workings'!$D$70:$F$70,MATCH($BH$4,'3. Workings'!$D$68:$F$68,0)),"0.0")&" of gross benefit, delivering ₹"&TEXT(INDEX('3. Workings'!$D$71:$F$71,MATCH($BH$4,'3. Workings'!$D$68:$F$68,0)),"0.0")&" Cr in net annual value." -> At the Aggressive rollout, every ₹1 of annual run cost generates ₹15.2 of gross benefit, delivering ₹75.3 Cr in net annual value.
D98: ="At the "&$BH$4&" rollout, the ₹"&TEXT(J83,"0.0")&" Cr build investment reaches payback in "&TEXT(J89,"0.0")&" months and generates ₹"&TEXT(J95,"0.0")&" Cr of 5-year NPV." -> At the Aggressive rollout, the ₹9.9 Cr build investment reaches payback in 13.8 months and generates ₹261.8 Cr of 5-year NPV.
CL101: ="Selected scenario: "&$BH$4 -> Selected scenario: Aggressive
D103: LIVE CHALLENGE LEVERS · type a value, clear the cell to reset | AL103: THE CASE, RIGHT NOW | BK103: WHAT WOULD HAVE TO BE TRUE FOR THIS TO FAIL
D105: Manual touches per claim today | X105: Published 7 · B-02, Tier 4, sensitivity register H-04 | AL105: Net annual benefit | AY105: ="₹"&TEXT(INDEX('3. Workings'!$D$71:$F$71,MATCH($BH$4,'3. Workings'!$D$68:$F$68,0)),"0.0")&" Cr" -> ₹75.3 Cr | BK105: ="Manual touches per claim · we assume "&TEXT('1. Assumptions and Sources'!$F$147,"0.0") -> Manual touches per claim · we assume 7.0 | BW105: ="Breaks at "&TEXT(INDEX('3. Workings'!$D$138:$F$138,MATCH($BH$4,'3. Workings'!$D$137:$F$137,0)),"0.0")&" · "&IF(INDEX('3. Workings'!$D$139:$F$139,MATCH($BH$4,'3. Workings'!$D$137:$F$137,0))>0,TEXT(INDEX('3. Workings'!$D$139:$F$139,MATCH($BH$4,'3. Workings'!$D$137:$F$137,0)),"0%")&" cushion","NO cushion at this plan") -> Breaks at 1.8 · 75% cushion
D108: Cost per manual touch (₹) | X108: Published 300 / 250 / 200 by plan · C-02, sensitivity register H-03 | AL108: Payback from project kickoff | AY108: =TEXT(INDEX('4. Forecast'!$D$50:$F$50,MATCH($BH$4,'4. Forecast'!$D$45:$F$45,0)),"0.0")&" months" -> 13.8 months
BK109: ="Cost per manual touch · we assume ₹"&TEXT(INDEX('1. Assumptions and Sources'!$D$55:$F$55,MATCH($BH$4,'1. Assumptions and Sources'!$D$53:$F$53,0)),"0") -> Cost per manual touch · we assume ₹200 | BW109: ="Breaks at "&TEXT(INDEX('3. Workings'!$D$140:$F$140,MATCH($BH$4,'3. Workings'!$D$137:$F$137,0)),"0")&" · "&IF(INDEX('3. Workings'!$D$141:$F$141,MATCH($BH$4,'3. Workings'!$D$137:$F$137,0))>0,TEXT(INDEX('3. Workings'!$D$141:$F$141,MATCH($BH$4,'3. Workings'!$D$137:$F$137,0)),"0%")&" cushion","NO cushion at this plan") -> Breaks at 63 · 75% cushion
D111: Fraud precision target | X111: Published 90% · B-14, a TARGET not a capability | AL111: Payback, realistic downside | AY111: =TEXT(INDEX('3. Workings'!$D$96:$F$96,MATCH($BH$4,'3. Workings'!$D$89:$F$89,0)),"0.0")&" months" -> 4.2 months
BK113: ="Rollout of the book · we plan "&TEXT(INDEX('3. Workings'!$D$12:$F$12,MATCH($BH$4,'3. Workings'!$D$6:$F$6,0)),"0%") -> Rollout of the book · we plan 100% | BW113: ="Breaks at "&TEXT(INDEX('3. Workings'!$D$142:$F$142,MATCH($BH$4,'3. Workings'!$D$137:$F$137,0)),"0%")&" · "&IF(INDEX('3. Workings'!$D$143:$F$143,MATCH($BH$4,'3. Workings'!$D$137:$F$137,0))>0,TEXT(INDEX('3. Workings'!$D$143:$F$143,MATCH($BH$4,'3. Workings'!$D$137:$F$137,0)),"0%")&" cushion","NO cushion at this plan") -> Breaks at 31% · 69% cushion
D114: Average claim size (₹) | X114: Published 45,000 · B-01, Tier 4, sensitivity register H-08 | AL114: Motor OD combined ratio | AY114: =TEXT(INDEX('3. Workings'!$D$82:$F$82,MATCH($BH$4,'3. Workings'!$D$77:$F$77,0)),"0.00")&" pp" -> 4.49 pp
D117: ="At the "&$BH$4&" rollout, the case does not rest on the fraud benefit. Labour alone covers the annual run cost down to "&TEXT(INDEX('3. Workings'!$D$138:$F$138,MATCH($BH$4,'3. Workings'!$D$137:$F$137,0)),"0.0")&" touches per claim and ₹"&TEXT(INDEX('3. Workings'!$D$140:$F$140,MATCH($BH$4,'3. Workings'!$D$137:$F$137,0)),"0")&" per touch, which is "&TEXT(INDEX('3. Workings'!$D$139:$F$139,MATCH($BH$4,'3. Workings'!$D$137:$F$137,0)),"0%")&" and "&TEXT(INDEX('3. Workings'!$D$141:$F$141,MATCH($BH$4,'3. Workings'!$D$137:$F$137,0)),"0%")&" below what we assume. Payback moves from "&TEXT(INDEX('3. Workings'!$D$95:$F$95,MATCH($BH$4,'3. Workings'!$D$89:$F$89,0)),"0.0")&" months as modelled to "&TEXT(INDEX('3. Workings'!$D$96:$F$96,MATCH($BH$4,'3. Workings'!$D$89:$F$89,0)),"0.0")&" months if both our weakest assumptions break, and "&'2. Summary'!$D$74&"." -> At the Aggressive rollout, the case does not rest on the fraud benefit. Labour alone covers the annual run cost down to 1.8 touches per claim and ₹63 per touch, which is 75% and 75% below what we assume. Payback moves from 1.6 months as modelled to 4.2 months if both our weakest assumptions break, and ALL 24 CHECKS PASS.
I120: =IF(SUMPRODUCT(--('1. Assumptions and Sources'!$E$147:$E$150<>""))=0,"No overrides. The model is running on its published assumptions.","LIVE OVERRIDE ACTIVE · "&SUMPRODUCT(--('1. Assumptions and Sources'!$E$147:$E$150<>""))&" of 4 levers overridden. Clear the yellow cells to return to published assumptions.") -> No overrides. The model is running on its published assumptions.

Sheet 1. Assumptions and Sources
B2: ClaimPulse · Assumptions and Sources
B3: Team Finsighters · NMIMS Mumbai · PS_BFDL Motor Insurance Claims TAT Reduction. Every input lives here. Sheets 1 to 3 contain no typed numbers, only formulas that read this sheet.
B5: TABLE A — FILED AND EXTERNAL DATA
B6: Ref | C6: Item | D6: Value | E6: Unit | F6: Tier | G6: Source
B7: A-01 | C7: Motor OD GDPI, FY2025-26 | D7: 3317.3 | E7: Rs Cr | F7: TIER 1 FILED | G7: GI Council segment-wise GDPI filings, Jun'25-Jun'26
B8: A-02 | C8: Net earned premium / GDPI | D8: 0.4988 | E8: ratio | F8: TIER 1 FILED | G8: Bajaj General FY2026: net earned premium Rs 9,519 Cr on gross direct premium Rs 19,082 Cr. Cross-checks to Q1 FY2027 filed: NEP Rs 2,669 Cr on GWP Rs 5,789 Cr, 46.1%. Motor OD retention runs above the whole-book blend, so this basis is conservative for Motor OD. Three bases are carried at Table P.
B9: A-03 | C9: Net incurred claims ratio | D9: 0.746 | E9: ratio | F9: TIER 1 FILED | G9: IRDAI Financial Highlights FY24-25, up 0.8 pp
B10: A-04 | C10: Group combined ratio, FY2024-25 | D10: 1.023 | E10: ratio | F10: TIER 1 FILED | G10: Crossed 100%, was 99.85% a year earlier
B11: A-05 | C11: Bajaj total GDPI, FY2025-26 | D11: 20461 | E11: Rs Cr | F11: TIER 1 FILED | G11: Motor is Rs 7,278 Cr, 35.6% of the book
B12: A-06 | C12: Motor OD market growth p.a. | D12: 0.087 | E12: ratio | F12: TIER 2 | G12: Motor sector research
B13: A-07 | C13: Salary inflation p.a. | D13: 0.069 | E13: ratio | F13: TIER 1 | G13: India talent outlook 2026
B14: A-08 | C14: FX rate | D14: 95.3 | E14: Rs / USD | F14: Market | G14: Spot, August 2026
B15: A-09 | C15: Discount rate (WACC) | D15: 0.12 | E15: ratio | F15: Standard | G15: Indian corporate project hurdle rate
B16: A-10 | C16: India regulated-sector cost uplift | D16: 1.314 | E16: x | F16: TIER 2 | G16: Compliance overhead applied to USD build benchmarks
B17: A-11 | C17: IRDAI surveyor exemption threshold | D17: 50000 | E17: Rs | F17: TIER 1 | G17: Master Circular on Protection of Policyholders' Interests, 2024
B18: A-12 | C18: API / inference price deflation p.a. | D18: -0.3 | E18: ratio | F18: TIER 2 | G18: Conservative end of a 30-50% observed range
B19: A-13 | C19: GPU price deflation p.a. | D19: -0.1 | E19: ratio | F19: TIER 2 | G19: Deflation slowing after a steep fall from peak
B21: TABLE B — OPERATING ASSUMPTIONS
B22: Ref | C22: Assumption | D22: Value | E22: Unit | F22: Tier | G22: Basis
B23: B-01 | C23: Average claim size | D23: =F150 -> 45000 | E23: Rs | F23: TIER 4 | G23: Conservative, and sits inside the Rs 50,000 surveyor corridor. A lower figure would mean more claims and more benefit.
B24: B-02 | C24: Manual touches per claim today | D24: =F147 -> 7 | E24: touches | F24: TIER 4 | G24: Workflow mapping. The largest single driver of the labour line, and confirmed by data request 1.
B25: B-03 | C25: Green lane share | D25: 0.65 | E25: ratio | F25: TIER 2 | G25: Auto-settle. Clean docs, intact EXIF, no synthetic flags.
B26: B-04 | C26: Amber lane share | D26: 0.25 | E26: ratio | F26: TIER 4 | G26: Signals inconclusive, not contradictory. One reviewer.
B27: B-05 | C27: Red lane share | D27: 0.1 | E27: ratio | F27: TIER 4 | G27: Hard contradiction at the capture gate. Investigate.
B28: B-06 | C28: Touches, green lane | D28: 0.2 | E28: touches | F28: TIER 4 | G28: Zero human touch in practice
B29: B-07 | C29: Touches, amber lane | D29: 2 | E29: touches | F29: TIER 4 | G29: One reviewer on an AI-prepared file
B30: B-08 | C30: Touches, red lane | D30: 6 | E30: touches | F30: TIER 4 | G30: Investigation with evidence pack pre-attached
B31: B-09 | C31: Claim TAT today | D31: 9.8 | E31: days | F31: TIER 2 | G31: Industry-typical 7-10+ days for non-complex motor claims
B32: B-10 | C32: TAT, green lane | D32: 1.5 | E32: days | F32: TIER 4 | G32: Auto-settlement
B33: B-11 | C33: TAT, amber lane | D33: 3.5 | E33: days | F33: TIER 4 | G33: Single assisted review
B34: B-12 | C34: TAT, red lane | D34: 7 | E34: days | F34: TIER 4 | G34: Full investigation, still faster than today
B35: B-13 | C35: Fraud detection rate (recall), today | D35: 0.62 | E35: ratio | F35: TIER 4 | G35: Share of fraudulent claims the existing rule-based engine currently catches.
B36: B-14 | C36: Fraud detection rate (recall), TARGET | D36: =F149 -> 0.9 | E36: ratio | F36: TARGET | G36: A target for the share of fraudulent claims caught. Published graph-AI lift runs +10 to 20 pp against the +28 pp modelled here, which is why F-02 tests an 82% landing and Sheet 8 runs the full curve.
B37: B-15 | C37: of the uplift, from the Capture Integrity Gate | D37: 0.1 | E37: pp | F37: TIER 4 | G37: EXIF and metadata contradiction catches crude attempts at intake, before any model runs.
B38: B-16 | C38: of the uplift, from the fraud and duplicate graph | D38: 0.18 | E38: pp | F38: TIER 4 | G38: Graph engine catches rings: same garage, vehicle, 3 claims in 30 days.
B39: B-17 | C39: Fraud leakage pool, % of claims value | D39: 0.0315 | E39: ratio | F39: TIER 2 PROXY | G39: Derived from the 8 to 10 per cent industry fraud and waste benchmark, applied to motor as a proxy. See H-01.
B40: B-18 | C40: Synthetic-media fraud, % of claims value | D40: 0.01 | E40: ratio | F40: TIER 4 | G40: Forward-looking. A NEW vector, so additive to B-17 rather than inside it. Sensitivity 0.5% to 2.0%.
B41: B-19 | C41: Gate detection rate on synthetic media | D41: 0.85 | E41: ratio | F41: TIER 4 | G41: Diffusion and GAN artefact screening on live-captured frames
B42: B-20 | C42: Live-capture friction: claims downgraded | D42: 0.08 | E42: ratio | F42: TIER 4 | G42: Honest claimants who cannot use live capture drop from green to amber. A real cost of the hard rule.
B43: B-21 | C43: Average Motor OD premium per policy | D43: 7000 | E43: Rs | F43: TIER 4 | G43: Used only to size the renewal line
B44: B-22 | C44: Renewal uplift on claimants | D44: 0.05 | E44: pp | F44: TIER 4 | G44: Applied to the claimant cohort ONLY, not the whole book. The whole-book NPS effect is not counted.
B45: B-23 | C45: Retained value on premium | D45: 0.1 | E45: ratio | F45: TIER 4 | G45: Distribution commission and margin retained within the group
B46: B-24 | C46: Benefit realisation, Year 1 | D46: 0.45 | E46: ratio | F46: Plan | G46: Rollout, touch reduction and fraud precision all still ramping
B47: B-25 | C47: Benefit realisation, Year 2 | D47: 0.92 | E47: ratio | F47: Plan | G47: Approaching steady state
B48: B-26 | C48: Benefit realisation, Year 3 | D48: 1 | E48: ratio | F48: Plan | G48: Steady state
... B51: B-28 | C51: Cost per manual touch, BASELINE (today) | D51: 250 | E51: Rs | F51: TIER 4 | G51: The rate the current process runs at. Held constant across all three plans, because the baseline does not change with the rollout chosen. The volume discounts at C-02 apply only to touches performed after go-live.
B52: TABLE C — THE THREE IMPLEMENTATION PLANS
B53: Ref | C53: Lever | D53: Conservative | E53: Base | F53: Aggressive | G53: Unit
B54: C-01 | C54: Rollout of the addressable Motor OD book | D54: 0.2 | E54: 0.6 | F54: 1 | G54: ratio
B55: C-02 | C55: Cost per manual touch | D55: =IF($E$148="",300,$E$148) -> 300 | E55: =IF($E$148="",250,$E$148) -> 250 | F55: =IF($E$148="",200,$E$148) -> 200 | G55: Rs
C56: C-01 and C-02 are the only differences between the plans. Cost per touch falls as volume rises (BPO volume discounts) and applies to post-implementation touches only; the baseline is fixed at B-28. Build cost is identical in all three, because the same system is built.
B58: TABLE D — BUILD COST BENCHMARKS · one-off, identical in all three plans
B59: Ref | C59: Component | D59: USD benchmark | E59: Rs direct | F59: Phase | G59: Basis
B60: D-01 | C60: Document AI, OCR and field extraction | D60: 35000 | F60: P1 | G60: Vendor NLP extraction band $20-45K
B61: D-02 | C61: Policy validation, RAG on actual wording | D61: 25000 | F61: P1 | G61: Vendor RAG build band $20-60K
B62: D-03 | C62: EXIF and metadata forensics engine | D62: 25000 | F62: P1 | G62: CAPTURE INTEGRITY GATE. Rules-based, zero model training.
B63: D-04 | C63: Synthetic and tampered image screening | D63: 50000 | F63: P2 | G63: CAPTURE INTEGRITY GATE. The moat. Diffusion and GAN artefact classifier tuned on own media.
B64: D-05 | C64: Guided live-capture SDK, gallery disabled | D64: 30000 | F64: P1 | G64: CAPTURE INTEGRITY GATE. The hard rule that makes the other two checks reliable.
B65: D-06 | C65: CV damage assessment, 360 video and depth | D65: 80000 | F65: P2 | G65: Two independent sources, $80-180K band
B66: D-07 | C66: Repair cost estimation engine | D66: 40000 | F66: P2 | G66: Settled claims plus live parts feeds. Garage APIs.
B67: D-08 | C67: Fraud and duplicate graph engine | D67: 80000 | F67: P3 | G67: Two sources, $80-100K real-time financial fraud
B68: D-09 | C68: Trust Score orchestration core | D68: 150000 | F68: P4 | G68: Multi-model parallel orchestration, $150-300K band
B69: D-10 | C69: Production hardening | D69: 60000 | F69: P4 | G69: 40% of orchestration. Audit trail, human override, rollback, explainability.
B70: D-11 | C70: Claimant, surveyor and garage consoles | D70: 35000 | F70: P4 | G70: Submission, tracking, proactive status push
B71: D-12 | C71: Systems integration | D71: 80000 | F71: Cross | G71: VAHAN, garage, policy DB, payment, CRM, surveyor, WhatsApp, mobile. No published benchmark exists; an SI quote is a pre-build gate.
B72: D-13 | C72: Training data: labelled damage and synthetic set | E72: 6000000 | F72: P2 | G72: CAPTURE INTEGRITY GATE. Real Indian damage media plus generated fakes to train the classifier.
B73: D-14 | C73: Model QC and UAT window | E73: 4000000 | F73: Cross | G73: Shadow to canary to gradual, plus model-output quality assurance
B74: D-15 | C74: Security, DPDP and SOC2 setup | E74: 2500000 | F74: Cross | G74: India pentest, SOC2 tooling, compliance engineering. One-off, separate from ongoing monitoring.
B76: TABLE E — RUN COST INPUTS
B77: Ref | C77: Item | D77: Value | E77: Unit | F77: Tier | G77: Basis
B78: E-01 | C78: GPU hours per claim | D78: 0.133333 | E78: hours | F78: TIER 4 | G78: 2 min per 10 sec of 1080p x 40 sec of claim video
B79: E-02 | C79: GPU peak-to-average multiplier | D79: 2.5 | E79: x | F79: TIER 4 | G79: 1.5x sourced floor, uplifted because claims cluster
B80: E-03 | C80: GPU safety margin | D80: 1.2 | E80: x | F80: Standard | G80: Capacity headroom
B81: E-04 | C81: GPU rate | D81: 3 | E81: USD / hour | F81: Market | G81: Commodity inference GPU
B82: E-05 | C82: Storage per claim | D82: 0.05 | E82: USD | F82: TIER 4 | G82: Image and video retention
B83: E-06 | C83: Storage replication multiplier | D83: 2.6 | E83: x | F83: TIER 4 | G83: Replication and backup
B84: E-07 | C84: MLOps tooling | D84: 7000 | E84: USD / month | F84: TIER 2 | G84: Midpoint of a $4,200-10,000 published range
B85: E-08 | C85: Operations team | D85: 536667 | E85: Rs / month | F85: TIER 1 | G85: Senior 100% + mid 50% + model QC 30% + PM 20%, India domestic bands
B86: E-09 | C86: Security and compliance monitoring | D86: 208333 | E86: Rs / month | F86: TIER 2 | G86: Rs 25L p.a. ongoing. Distinct from the D-15 one-off setup.
B87: E-10 | C87: Legal and regulatory counsel | D87: 100000 | E87: Rs / month | F87: TIER 4 | G87: DPDP and IRDAI scope, priced at India counsel rates.
B90: TABLE F — DOWNSIDE TEST INPUTS · used only in the sensitivity block on Sheet 3
B91: Ref | C91: Item | D91: Value | E91: Unit | F91: Tier | G91: Why this row exists
B92: F-01 | C92: In-house cost per manual touch | D92: 83 | E92: Rs | F92: TIER 4 | G92: Rs 250 is BPO per-transaction pricing. If claims handling sits with salaried in-house staff the marginal cost is far lower. This tests the case at that rate.
B93: F-02 | C93: Fraud detection rate, downside landing | D93: 0.82 | E93: ratio | F93: TIER 4 | G93: Tests the case with the 90% detection target landing at 82%.
B95: TABLE G — BASIS OF PREPARATION · how each cost and benefit line is constructed
B96: Item | C96: Convention applied | D96: Where it lands | E96: Why it is built this way
B97: FX rate | C97: Spot, Rs 95.3 / USD | D97: Every USD-benchmarked build line | E97: Spot as at August 2026, inside the 94.89 to 95.45 range traded in the week to 11 August. Marginally conservative.
B98: Build cost | C98: Bottom-up, fifteen costed components | D98: Sheet 3 Part D | E98: Every layer carries its own line, including the Capture Integrity Gate, repair estimation, the consoles, training data, systems integration and security setup. The gate is the single largest block, which is right, because it is the moat.
B99: Run cost | C99: Bottom-up, six lines | D99: Sheet 3 Part E | E99: GPU, storage, MLOps tooling, operations team, security monitoring and legal counsel. Two lines scale with volume; four are fixed.
B100: Fraud benefit | C100: Leakage pool x reduction in the UNDETECTED share | D100: Sheet 3 Part C | E100: Detection lift applies to the undetected share. Moving detection from 62% to 90% cuts the undetected share from 38% to 10%, a 73.7% reduction in residual leakage.
B101: Surveyor exemption threshold | C101: Rs 50,000 | D101: Lane design and Sheet 3 Part I | E101: Master Circular on Protection of Policyholders’ Interests, 2024, confirmed to Parliament in December 2025.
B102: Capture Integrity Gate | C102: Costed in build lines D-03 to D-05 and D-13, valued in benefit lines W-20 and W-21 | D102: Sheets 1, 3 and 5 | E102: The moat carries both its cost and its value inside the model rather than sitting on a slide.
B103: TAT | C103: Lane-weighted, and restated after live-capture friction | D103: Sheet 3 Part B | E103: The problem statement is TAT reduction, so TAT is a modelled output on every sheet.
B105: TABLE H — ASSUMPTION SENSITIVITY REGISTER · which inputs move the answer, and how each is validated
B106: Ref | C106: Assumption | D106: Direction of bias | E106: Validation route
B107: W-01 | C107: The fraud leakage pool derives from a life and health benchmark, applied to motor as a proxy | D107: Ambiguous. The 8 to 10 per cent benchmark is already net of existing controls, so a literal reading gives a LARGER benefit, not smaller. | E107: Motor-specific leakage from Bajaj’s own fraud unit. Data request 2.
B108: W-02 | C108: 90 per cent fraud detection is a target rather than a demonstrated capability | D108: Optimistic. F-02 lands it at 82 per cent and Sheet 8 runs the full curve to 62 per cent. | E108: Shadow-mode results against held-out historical claims at the UAT gate. Pilot gate 3.
B109: W-03 | C109: Rs 250 per touch is BPO transaction pricing, applied to a process that may be handled in house | D109: Optimistic if handling is in house. F-01 tests the case at Rs 83 and it still clears. | E109: Confirmation of the claims-operations delivery model plus a time-and-motion study. Data request 3.
B110: W-04 | C110: Seven manual touches per claim is a workflow-mapped estimate | D110: The largest single driver of the labour line. Part J shows the case survives down to 2.2 touches. | E110: One session with Bajaj claims operations. Data request 1.
B111: W-05 | C111: Synthetic-media incidence at 1 per cent of claims value is forward looking | D111: No published incidence exists, because the vector is new. Sensitivity 0.5 to 2.0 per cent. | E111: Pilot instrumentation. ClaimPulse would be the first system to measure it.
...

Sheet 2. Summary
B2: ClaimPulse · Investment Summary
B3: Team Finsighters · NMIMS Mumbai · PS_BFDL Motor Insurance Claims TAT Reduction. Three implementation plans. Every figure is a formula reading Sheets 2 to 4 — nothing on this sheet is typed.
B5: PART 1 — HEADLINE FIGURES
B6: Ref | C6: Metric | D6: Conservative | E6: Base | F6: Aggressive | G6: Unit
B7: H-01 | C7: Rollout of the addressable Motor OD book | D7: ='3. Workings'!D12 -> 0.2 | E7: ='3. Workings'!E12 -> 0.6 | F7: ='3. Workings'!F12 -> 1 | G7: ratio
B8: H-02 | C8: Claims on the platform, per month | D8: ='3. Workings'!D14 -> 4571.7898 | E8: ='3. Workings'!E14 -> 13715.369 | F8: ='3. Workings'!F14 -> 22858.949 | G8: claims
B9: H-03 | C9: Claim TAT on ClaimPulse (9.8 days today) | D9: ='3. Workings'!D23 -> 2.71 | E9: ='3. Workings'!E23 -> 2.71 | F9: ='3. Workings'!F23 -> 2.71 | G9: days
B10: H-04 | C10: Blended TAT across the whole Motor OD book | D10: ='3. Workings'!D24 -> 8.382 | E10: ='3. Workings'!E24 -> 5.546 | F10: ='3. Workings'!F24 -> 2.71 | G10: days
B11: H-05 | C11: TAT reduction vs today | D11: ='3. Workings'!D26 -> 0.14469388 | E11: ='3. Workings'!E26 -> 0.43408163 | F11: ='3. Workings'!F26 -> 0.72346939 | G11: %
B12: H-06 | C12: Manual touches per claim (7 today) | D12: ='3. Workings'!D19 -> 1.23 | E12: ='3. Workings'!E19 -> 1.23 | F12: ='3. Workings'!F19 -> 1.23 | G12: touches
B13: H-07 | C13: Gross annual benefit | D13: ='3. Workings'!D36 -> 15.359972 | E13: ='3. Workings'!E36 -> 47.210612 | F13: ='3. Workings'!F36 -> 80.568845 | G13: Rs Cr
B14: H-08 | C14: Annual run cost | D14: ='3. Workings'!D65 -> 2.5098822 | E14: ='3. Workings'!E65 -> 3.9006065 | F14: ='3. Workings'!F65 -> 5.2913309 | G14: Rs Cr
B15: H-09 | C15: NET ANNUAL BENEFIT | D15: ='3. Workings'!D71 -> 12.85009 | E15: ='3. Workings'!E71 -> 43.310005 | F15: ='3. Workings'!F71 -> 75.277514 | G15: Rs Cr
B16: H-10 | C16: Net monthly benefit | D16: ='3. Workings'!D72 -> 1.0708408 | E16: ='3. Workings'!E72 -> 3.6091671 | F16: ='3. Workings'!F72 -> 6.2731261 | G16: Rs Cr
B17: H-11 | C17: Build cost, one-off (same in all three plans) | D17: ='3. Workings'!D73 -> 9.8904698 | E17: ='3. Workings'!E73 -> 9.8904698 | F17: ='3. Workings'!F73 -> 9.8904698 | G17: Rs Cr
B18: H-12 | C18: Payback on steady-state economics | D18: ='3. Workings'!D74 -> 9.2361717 | E18: ='3. Workings'!E74 -> 2.7403746 | F18: ='3. Workings'!F74 -> 1.5766413 | G18: months
B19: H-13 | C19: Payback — REALISTIC DOWNSIDE | D19: ='3. Workings'!D96 -> 28.634321 | E19: ='3. Workings'!E96 -> 7.3884554 | F19: ='3. Workings'!F96 -> 4.2414317 | G19: months
B20: H-14 | C20: Payback — absolute floor, labour only | D20: ='3. Workings'!D97 -> 2286.0024 | E20: ='3. Workings'!E97 -> 31.358536 | F20: ='3. Workings'!F97 -> 15.787552 | G20: months
B21: H-15 | C21: Combined ratio impact — Motor OD basis | D21: ='3. Workings'!D82 -> 0.76499125 | E21: ='3. Workings'!E82 -> 2.5826285 | F21: ='3. Workings'!F82 -> 4.4913773 | G21: pp
B22: H-16 | C22: Combined ratio impact — group basis | D22: ='3. Workings'!D85 -> 0.12402646 | E22: ='3. Workings'!E85 -> 0.41871627 | F22: ='3. Workings'!F85 -> 0.72817779 | G22: pp
B23: H-17 | C23: 3-year net benefit | D23: ='4. Forecast'!D47 -> 32.217718 | E23: ='4. Forecast'!E47 -> 111.49047 | F23: ='4. Forecast'!F47 -> 194.73062 | G23: Rs Cr
B24: H-18 | C24: 3-year NPV at 12% | D24: ='4. Forecast'!D49 -> 14.91756 | E24: ='4. Forecast'!E49 -> 76.277313 | F24: ='4. Forecast'!F49 -> 140.7126 | G24: Rs Cr
B25: H-19 | C25: Payback from project kickoff (includes the 10-month build) | D25: ='4. Forecast'!D50 -> 27.21363 | E25: ='4. Forecast'!E50 -> 16.842971 | F25: ='4. Forecast'!F50 -> 13.83294 | G25: months
B27: PART 1B — WHERE THE BENEFIT COMES FROM (Rs Cr per year, steady state)
B28: Ref | C28: Benefit line | D28: Conservative | E28: Base | F28: Aggressive | G28: Drives which ratio
B29: H-20 | C29: Labour: manual touches removed | D29: ='3. Workings'!D30 -> 7.5763701 | E29: ='3. Workings'!E30 -> 23.741305 | F29: ='3. Workings'!F30 -> 41.255831 | G29: Expense ratio
B30: H-21 | C30: Fraud avoided: fraud and duplicate graph | D30: ='3. Workings'!D31 -> 3.6836595 | E30: ='3. Workings'!E31 -> 11.050978 | F30: ='3. Workings'!F31 -> 18.418297 | G30: Loss ratio
B31: H-22 | C31: Fraud avoided: CAPTURE INTEGRITY GATE | D31: ='3. Workings'!D32 -> 2.0464775 | E31: ='3. Workings'!E32 -> 6.1394325 | F31: ='3. Workings'!F32 -> 10.232387 | G31: Loss ratio
B32: H-23 | C32: Synthetic-media exposure avoided: THE GATE | D32: ='3. Workings'!D33 -> 2.0984515 | E32: ='3. Workings'!E33 -> 6.2953546 | F32: ='3. Workings'!F33 -> 10.492258 | G32: Loss ratio
B33: H-24 | C33: Renewal retention on claimants | D33: ='3. Workings'!D34 -> 0.19201517 | E33: ='3. Workings'!E34 -> 0.57604552 | F33: ='3. Workings'!F34 -> 0.96007586 | G33: Outside both ratios
B34: H-25 | C34: less: live-capture friction cost | D34: ='3. Workings'!D35 -> -0.23700158 | E34: ='3. Workings'!E35 -> -0.59250396 | F34: ='3. Workings'!F35 -> -0.79000528 | G34: Expense ratio
B35: H-26 | C35: GROSS ANNUAL BENEFIT | D35: ='3. Workings'!D36 -> 15.359972 | E35: ='3. Workings'!E36 -> 47.210612 | F35: ='3. Workings'!F36 -> 80.568845
C36: Rows H-22, H-23 and part of the TAT gain are the Capture Integrity Gate. It carries its own build cost and its own benefit lines rather than sitting on a slide as a claim.
B38: PART 2 — KEY ASSUMPTIONS AND DATA SOURCES · full register on Sheet 1
B39: Ref | C39: Assumption | D39: Value | E39: Tier | F39: Source / basis | G39: Why it matters
B40: A-01 | C40: ='1. Assumptions and Sources'!$C$7 -> Motor OD GDPI, FY2025-26 | D40: ='1. Assumptions and Sources'!$D$7 -> 3317.3 | E40: ='1. Assumptions and Sources'!$F$7 -> TIER 1 FILED | F40: ='1. Assumptions and Sources'!$G$7 -> GI Council segment-wise GDPI filings, Jun'25-Jun'26 | G40: Top of the benefit chain. Everything scales from this.
B41: A-02 | C41: ='1. Assumptions and Sources'!$C$8 -> Net earned premium / GDPI | D41: ='1. Assumptions and Sources'!$D$8 -> 0.4988 | E41: ='1. Assumptions and Sources'!$F$8 -> TIER 1 FILED | F41: ='1. Assumptions and Sources'!$G$8 -> Bajaj General FY2026: net earned premium Rs 9,519 Cr on gross direct premium Rs 19,082 Cr. Cross-checks to Q1 FY2027 filed: NEP Rs 2,669 Cr on GWP Rs 5,789 Cr, 46.1%. Motor OD retention runs above the whole-book blend, so this basis is conservative for Motor OD. Three bases are carried at Table P. | G41: Converts gross direct premium to net earned premium. Filed FY2026 basis; three bases are carried at Table P.
B42: A-03 | C42: ='1. Assumptions and Sources'!$C$9 -> Net incurred claims ratio | D42: ='1. Assumptions and Sources'!$D$9 -> 0.746 | E42: ='1. Assumptions and Sources'!$F$9 -> TIER 1 FILED | F42: ='1. Assumptions and Sources'!$G$9 -> IRDAI Financial Highlights FY24-25, up 0.8 pp | G42: Converts earned premium into the claims pool ClaimPulse acts on.
B43: A-11 | C43: ='1. Assumptions and Sources'!$C$17 -> IRDAI surveyor exemption threshold | D43: ='1. Assumptions and Sources'!$D$17 -> 50000 | E43: ='1. Assumptions and Sources'!$F$17 -> TIER 1 | F43: ='1. Assumptions and Sources'!$G$17 -> Master Circular on Protection of Policyholders' Interests, 2024 | G43: The regulatory corridor the green lane is scoped to sit inside.
B44: A-08 | C44: ='1. Assumptions and Sources'!$C$14 -> FX rate | D44: ='1. Assumptions and Sources'!$D$14 -> 95.3 | E44: ='1. Assumptions and Sources'!$F$14 -> Market | F44: ='1. Assumptions and Sources'!$G$14 -> Spot, August 2026 | G44: Every USD build benchmark converts at this rate.
B45: B-01 | C45: ='1. Assumptions and Sources'!$C$23 -> Average claim size | D45: ='1. Assumptions and Sources'!$D$23 -> 45000 | E45: ='1. Assumptions and Sources'!$F$23 -> TIER 4 | F45: ='1. Assumptions and Sources'!$G$23 -> Conservative, and sits inside the Rs 50,000 surveyor corridor. A lower figure would mean more claims and more benefit. | G45: Sets claim count. A lower figure means MORE claims and MORE benefit, so this is conservative.
B46: B-02 | C46: ='1. Assumptions and Sources'!$C$24 -> Manual touches per claim today | D46: ='1. Assumptions and Sources'!$D$24 -> 7 | E46: ='1. Assumptions and Sources'!$F$24 -> TIER 4 | F46: ='1. Assumptions and Sources'!$G$24 -> Workflow mapping. The largest single driver of the labour line, and confirmed by data request 1. | G46: Largest single driver of the labour line, and a team estimate. Validate with claims ops.
B47: B-03 | C47: ='1. Assumptions and Sources'!$C$25 -> Green lane share | D47: ='1. Assumptions and Sources'!$D$25 -> 0.65 | E47: ='1. Assumptions and Sources'!$F$25 -> TIER 2 | F47: ='1. Assumptions and Sources'!$G$25 -> Auto-settle. Clean docs, intact EXIF, no synthetic flags. | G47: Green-lane share sets both the touch reduction and the TAT gain.
B48: B-13 | C48: ='1. Assumptions and Sources'!$C$35 -> Fraud detection rate (recall), today | D48: ='1. Assumptions and Sources'!$D$35 -> 0.62 | E48: ='1. Assumptions and Sources'!$F$35 -> TIER 4 | F48: ='1. Assumptions and Sources'!$G$35 -> Share of fraudulent claims the existing rule-based engine currently catches. | G48: Denominator of the fraud formula.
B49: B-14 | C49: ='1. Assumptions and Sources'!$C$36 -> Fraud detection rate (recall), TARGET | D49: ='1. Assumptions and Sources'!$D$36 -> 0.9 | E49: ='1. Assumptions and Sources'!$F$36 -> TARGET | F49: ='1. Assumptions and Sources'!$G$36 -> A target for the share of fraudulent claims caught. Published graph-AI lift runs +10 to 20 pp against the +28 pp modelled here, which is why F-02 tests an 82% landing and Sheet 8 runs the full curve. | G49: A TARGET, not a demonstrated capability. Tested at 82% in the downside.
B50: B-17 | C50: ='1. Assumptions and Sources'!$C$39 -> Fraud leakage pool, % of claims value | D50: ='1. Assumptions and Sources'!$D$39 -> 0.0315 | E50: ='1. Assumptions and Sources'!$F$39 -> TIER 2 PROXY | F50: ='1. Assumptions and Sources'!$G$39 -> Derived from the 8 to 10 per cent industry fraud and waste benchmark, applied to motor as a proxy. See H-01. | G50: Fraud leakage pool. Derived from a life and health benchmark used as a motor proxy.
B51: B-18 | C51: ='1. Assumptions and Sources'!$C$40 -> Synthetic-media fraud, % of claims value | D51: ='1. Assumptions and Sources'!$D$40 -> 0.01 | E51: ='1. Assumptions and Sources'!$F$40 -> TIER 4 | F51: ='1. Assumptions and Sources'!$G$40 -> Forward-looking. A NEW vector, so additive to B-17 rather than inside it. Sensitivity 0.5% to 2.0%. | G51: Synthetic-media incidence. Forward-looking, and the vector nobody else defends against.
B52: C-02 | C52: ='1. Assumptions and Sources'!$C$55 -> Cost per manual touch | D52: ='1. Assumptions and Sources'!$E$55 -> 250 | E52: TIER 2 | F52: BPO per-transaction pricing benchmark | G52: Rs 300 / 250 / 200 across the three plans. BPO transaction pricing; the downside test uses Rs 83.
B55: HOW TO REPRODUCE THIS WORKBOOK
B56: 1. Every input lives on Sheet 1. Sheets 2, 3 and 4 contain no typed numbers, only formulas.
B57: 2. Change any yellow cell on Sheet 1 and the whole workbook recalculates, including all three plans.
B58: 3. The three plans differ by exactly two levers: rollout (C-01) and cost per touch (C-02). Build cost is identical in all three.
B59: 4. Sheet 3 Part H tests the case when the two weakest assumptions break. Quote H-13, not H-12.
B60: 5. Combined ratio is shown on two bases. Always state which one you are using.
B61: 6. Sheet 1 Table G sets out how every line is constructed. Table H is the sensitivity register: which inputs move the answer, and how each one is validated.
B63: PART 3 — MODEL INTEGRITY · the workbook audits itself before anyone else does
B64: Ref | C64: Check | D64: Conservative | E64: Base | F64: Aggressive | G64: What it proves
B65: IC-01 | C65: Stakeholder split reconciles to net annual benefit | D65: =IF(ROUND('3. Workings'!D105,6)=0,"PASS","FAIL") -> PASS | E65: =IF(ROUND('3. Workings'!E105,6)=0,"PASS","FAIL") -> PASS | F65: =IF(ROUND('3. Workings'!F105,6)=0,"PASS","FAIL") -> PASS | G65: The Sheet 3 Part I split does not drift from the P&L.
B66: IC-02 | C66: Benefit lines sum to gross annual benefit | D66: =IF(ROUND(SUM('3. Workings'!D30:D35)-'3. Workings'!D36,6)=0,"PASS","FAIL") -> PASS | E66: =IF(ROUND(SUM('3. Workings'!E30:E35)-'3. Workings'!E36,6)=0,"PASS","FAIL") -> PASS | F66: =IF(ROUND(SUM('3. Workings'!F30:F35)-'3. Workings'!F36,6)=0,"PASS","FAIL") -> PASS | G66: No benefit line is double counted or dropped.
B67: IC-03 | C67: Group consolidated benefit equals net annual benefit | D67: =IF(ROUND('3. Workings'!D129-'3. Workings'!D71,6)=0,"PASS","FAIL") -> PASS | E67: =IF(ROUND('3. Workings'!E129-'3. Workings'!E71,6)=0,"PASS","FAIL") -> PASS | F67: =IF(ROUND('3. Workings'!F129-'3. Workings'!F71,6)=0,"PASS","FAIL") -> PASS | G67: Who-books-what adds back to the same total.
B68: IC-04 | C68: Summary headline equals the Workings result | D68: =IF(ROUND(D15-'3. Workings'!D71,6)=0,"PASS","FAIL") -> PASS | E68: =IF(ROUND(E15-'3. Workings'!E71,6)=0,"PASS","FAIL") -> PASS | F68: =IF(ROUND(F15-'3. Workings'!F71,6)=0,"PASS","FAIL") -> PASS | G68: Sheet 2 is a formula on Sheet 3, not a retyped number.
B69: IC-05 | C69: Investor Metrics net benefit equals the Workings result | D69: =IF(ROUND('5. Investor Metrics'!D33-'3. Workings'!D71,6)=0,"PASS","FAIL") -> PASS | E69: =IF(ROUND('5. Investor Metrics'!E33-'3. Workings'!E71,6)=0,"PASS","FAIL") -> PASS | F69: =IF(ROUND('5. Investor Metrics'!F33-'3. Workings'!F71,6)=0,"PASS","FAIL") -> PASS | G69: Sheet 5 reads the same engine.
B70: IC-06 | C70: Forecast 3-year total equals the sum of its years | D70: =IF(ROUND('4. Forecast'!$H$13-SUM('4. Forecast'!$E$13:$G$13),6)=0,"PASS","FAIL") -> PASS | E70: =IF(ROUND('4. Forecast'!$H$26-SUM('4. Forecast'!$E$26:$G$26),6)=0,"PASS","FAIL") -> PASS | F70: =IF(ROUND('4. Forecast'!$H$39-SUM('4. Forecast'!$E$39:$G$39),6)=0,"PASS","FAIL") -> PASS | G70: The forecast block adds up.
B71: IC-07 | C71: Combined ratio equals loss plus expense ratio | D71: =IF(ROUND('3. Workings'!D82-('3. Workings'!D80+'3. Workings'!D81),6)=0,"PASS","FAIL") -> PASS | E71: =IF(ROUND('3. Workings'!E82-('3. Workings'!E80+'3. Workings'!E81),6)=0,"PASS","FAIL") -> PASS | F71: =IF(ROUND('3. Workings'!F82-('3. Workings'!F80+'3. Workings'!F81),6)=0,"PASS","FAIL") -> PASS | G71: Both halves of the ratio are accounted for.
B72: IC-08 | C72: Claims-handling hours reconcile to touches avoided | D72: =IF(ROUND(('3. Workings'!D133-'3. Workings'!D134)-'3. Workings'!D112,4)=0,"PASS","FAIL") -> PASS | E72: =IF(ROUND(('3. Workings'!E133-'3. Workings'!E134)-'3. Workings'!E112,4)=0,"PASS","FAIL") -> PASS | F72: =IF(ROUND(('3. Workings'!F133-'3. Workings'!F134)-'3. Workings'!F112,4)=0,"PASS","FAIL") -> PASS | G72: The Panel 3 chart source ties to the touch model.
B74: IC-09 | C74: OVERALL | D74: =IF(COUNTIF(D65:F72,"PASS")=24,"ALL 24 CHECKS PASS","ATTENTION: "&COUNTIF(D65:F72,"FAIL")&" CHECK(S) FAILING") -> ALL 24 CHECKS PASS | G74: Eight checks across three plans. This cell feeds the Dashboard.

Sheet 3. Workings
B2: Detailed Workings
B3: Filed premium to net benefit, for all three implementation plans side by side. Every cell is a formula reading Sheet 1. Nothing here is typed.
B5: PART A — FROM FILED PREMIUM TO CLAIMS IN SCOPE
B6: Ref | C6: Step | D6: Conservative | E6: Base | F6: Aggressive | G6: Unit | H6: How it is derived
B7: W-01 | C7: Motor OD GDPI, FY2025-26 | D7: ='1. Assumptions and Sources'!$D$7 -> 3317.3 | E7: ='1. Assumptions and Sources'!$D$7 -> 3317.3 | F7: ='1. Assumptions and Sources'!$D$7 -> 3317.3 | G7: Rs Cr | H7: A-01. Bajaj's own filed Motor OD gross direct premium.
B8: W-02 | C8: Motor OD net earned premium | D8: =D7*'1. Assumptions and Sources'!$D$8 -> 1654.6692 | E8: =E7*'1. Assumptions and Sources'!$D$8 -> 1654.6692 | F8: =F7*'1. Assumptions and Sources'!$D$8 -> 1654.6692 | G8: Rs Cr | H8: W-01 x A-02 filed NEP/GDPI ratio.
B9: W-03 | C9: Annual incurred claims pool | D9: =D8*'1. Assumptions and Sources'!$D$9 -> 1234.3833 | E9: =E8*'1. Assumptions and Sources'!$D$9 -> 1234.3833 | F9: =F8*'1. Assumptions and Sources'!$D$9 -> 1234.3833 | G9: Rs Cr | H9: W-02 x A-03 net incurred claims ratio. This is the pool ClaimPulse acts on.
B10: W-04 | C10: Average claim size | D10: ='1. Assumptions and Sources'!$D$23 -> 45000 | E10: ='1. Assumptions and Sources'!$D$23 -> 45000 | F10: ='1. Assumptions and Sources'!$D$23 -> 45000 | G10: Rs | H10: B-01. Reconciled to an in-band claim frequency at Part K.
B11: W-05 | C11: Annual claim count, full book | D11: =D9*10000000/D10 -> 274307.39 | E11: =E9*10000000/E10 -> 274307.39 | F11: =F9*10000000/F10 -> 274307.39 | G11: claims | H11: Claims pool in rupees divided by average claim size.
B12: W-06 | C12: Rollout of the addressable book | D12: ='1. Assumptions and Sources'!D$54 -> 0.2 | E12: ='1. Assumptions and Sources'!E$54 -> 0.6 | F12: ='1. Assumptions and Sources'!F$54 -> 1 | G12: ratio | H12: C-01. THE defining lever between the three plans.
B13: W-07 | C13: Annual claims on the platform | D13: =D11*D12 -> 54861.478 | E13: =E11*E12 -> 164584.43 | F13: =F11*F12 -> 274307.39 | G13: claims | H13: Full-book count x rollout.
B14: W-08 | C14: Monthly claims on the platform | D14: =D13/12 -> 4571.7898 | E14: =E13/12 -> 13715.369 | F14: =F13/12 -> 22858.949 | G14: claims | H14: Annual claim count divided by twelve.
B15: W-09 | C15: Annual claims VALUE on the platform | D15: =D9*D12 -> 246.87665 | E15: =E9*E12 -> 740.62995 | F15: =F9*F12 -> 1234.3833 | G15: Rs Cr | H15: Claims pool x rollout. Drives both fraud lines.
B17: PART B — LANE MIX, MANUAL TOUCHES AND TAT · the Trust Score routing
B18: Ref | C18: Step | D18: Conservative | E18: Base | F18: Aggressive | G18: Unit | H18: How it is derived
B19: W-10 | C19: Blended manual touches after ClaimPulse | D19: ='1. Assumptions and Sources'!$D$25*'1. Assumptions and Sources'!$D$28+'1. Assumptions and Sources'!$D$26*'1. Assumptions and Sources'!$D$29+'1. Assumptions and Sources'!$D$27*'1. Assumptions and Sources'!$D$30 -> 1.23 | E19: ='1. Assumptions and Sources'!$D$25*'1. Assumptions and Sources'!$D$28+'1. Assumptions and Sources'!$D$26*'1. Assumptions and Sources'!$D$29+'1. Assumptions and Sources'!$D$27*'1. Assumptions and Sources'!$D$30 -> 1.23 | F19: ='1. Assumptions and Sources'!$D$25*'1. Assumptions and Sources'!$D$28+'1. Assumptions and Sources'!$D$26*'1. Assumptions and Sources'!$D$29+'1. Assumptions and Sources'!$D$27*'1. Assumptions and Sources'!$D$30 -> 1.23 | G19: touches | H19: Lane-weighted: 65% green x 0.2 + 25% amber x 2 + 10% red x 6.
B20: W-11 | C20: Manual touches removed per claim | D20: ='1. Assumptions and Sources'!$D$24-D19 -> 5.77 | E20: ='1. Assumptions and Sources'!$D$24-E19 -> 5.77 | F20: ='1. Assumptions and Sources'!$D$24-F19 -> 5.77 | G20: touches | H20: 7 today less the blended figure above.
B21: W-12 | C21: Claim TAT on ClaimPulse | D21: ='1. Assumptions and Sources'!$D$25*'1. Assumptions and Sources'!$D$32+'1. Assumptions and Sources'!$D$26*'1. Assumptions and Sources'!$D$33+'1. Assumptions and Sources'!$D$27*'1. Assumptions and Sources'!$D$34 -> 2.55 | E21: ='1. Assumptions and Sources'!$D$25*'1. Assumptions and Sources'!$D$32+'1. Assumptions and Sources'!$D$26*'1. Assumptions and Sources'!$D$33+'1. Assumptions and Sources'!$D$27*'1. Assumptions and Sources'!$D$34 -> 2.55 | F21: ='1. Assumptions and Sources'!$D$25*'1. Assumptions and Sources'!$D$32+'1. Assumptions and Sources'!$D$26*'1. Assumptions and Sources'!$D$33+'1. Assumptions and Sources'!$D$27*'1. Assumptions and Sources'!$D$34 -> 2.55 | G21: days | H21: Lane-weighted: 65% x 1.5d + 25% x 3.5d + 10% x 7d.
B22: W-13 | C22: Claim TAT today | D22: ='1. Assumptions and Sources'!$D$31 -> 9.8 | E22: ='1. Assumptions and Sources'!$D$31 -> 9.8 | F22: ='1. Assumptions and Sources'!$D$31 -> 9.8 | G22: days | H22: B-09. Industry-typical 7 to 10+ days.
B23: W-14 | C23: TAT on ClaimPulse, after live-capture friction | D23: =('1. Assumptions and Sources'!$D$25-'1. Assumptions and Sources'!$D$42)*'1. Assumptions and Sources'!$D$32+('1. Assumptions and Sources'!$D$26+'1. Assumptions and Sources'!$D$42)*'1. Assumptions and Sources'!$D$33+'1. Assumptions and Sources'!$D$27*'1. Assumptions and Sources'!$D$34 -> 2.71 | E23: =('1. Assumptions and Sources'!$D$25-'1. Assumptions and Sources'!$D$42)*'1. Assumptions and Sources'!$D$32+('1. Assumptions and Sources'!$D$26+'1. Assumptions and Sources'!$D$42)*'1. Assumptions and Sources'!$D$33+'1. Assumptions and Sources'!$D$27*'1. Assumptions and Sources'!$D$34 -> 2.71 | F23: =('1. Assumptions and Sources'!$D$25-'1. Assumptions and Sources'!$D$42)*'1. Assumptions and Sources'!$D$32+('1. Assumptions and Sources'!$D$26+'1. Assumptions and Sources'!$D$42)*'1. Assumptions and Sources'!$D$33+'1. Assumptions and Sources'!$D$27*'1. Assumptions and Sources'!$D$34 -> 2.71 | G23: days | H23: 8% of claims fall from green to amber because live capture was not possible. The honest figure.
B24: W-15 | C24: Blended TAT across the whole Motor OD book | D24: =D12*D23+(1-D12)*D22 -> 8.382 | E24: =E12*E23+(1-E12)*E22 -> 5.546 | F24: =F12*F23+(1-F12)*F22 -> 2.71 | G24: days | H24: Platform TAT on the rolled-out share, 9.8 days on the rest. This is the number that improves as rollout rises.
B25: W-16 | C25: TAT reduction vs today | D25: =D22-D24 -> 1.418 | E25: =E22-E24 -> 4.254 | F25: =F22-F24 -> 7.09 | G25: days | H25: W-13 less W-15.
B26: W-17 | C26: TAT reduction | D26: =D25/D22 -> 0.14469388 | E26: =E25/E22 -> 0.43408163 | F26: =F25/F22 -> 0.72346939 | G26: % | H26: As a percentage of today's TAT.
B28: PART C — ANNUAL BENEFIT LINES (Rs Cr)
B29: Ref | C29: Benefit line | D29: Conservative | E29: Base | F29: Aggressive | G29: Unit | H29: How it is derived
B30: W-18 | C30: Labour: manual touches removed | D30: =D13*('1. Assumptions and Sources'!$D$24*'1. Assumptions and Sources'!$D$51-D19*'1. Assumptions and Sources'!D$55)/10000000 -> 7.5763701 | E30: =E13*('1. Assumptions and Sources'!$D$24*'1. Assumptions and Sources'!$D$51-E19*'1. Assumptions and Sources'!E$55)/10000000 -> 23.741305 | F30: =F13*('1. Assumptions and Sources'!$D$24*'1. Assumptions and Sources'!$D$51-F19*'1. Assumptions and Sources'!F$55)/10000000 -> 41.255831 | G30: Rs Cr | H30: Claims x (baseline touches at B-28 less residual touches at the plan rate). Lands in the EXPENSE ratio. Tests at H-03 and H-04.
B31: W-19 | C31: Fraud avoided: fraud and duplicate graph | D31: =D15*'1. Assumptions and Sources'!$D$39*(1-(1-'1. Assumptions and Sources'!$D$36)/(1-'1. Assumptions and Sources'!$D$35))*('1. Assumptions and Sources'!$D$38/('1. Assumptions and Sources'!$D$37+'1. Assumptions and Sources'!$D$38)) -> 3.6836595 | E31: =E15*'1. Assumptions and Sources'!$D$39*(1-(1-'1. Assumptions and Sources'!$D$36)/(1-'1. Assumptions and Sources'!$D$35))*('1. Assumptions and Sources'!$D$38/('1. Assumptions and Sources'!$D$37+'1. Assumptions and Sources'!$D$38)) -> 11.050978 | F31: =F15*'1. Assumptions and Sources'!$D$39*(1-(1-'1. Assumptions and Sources'!$D$36)/(1-'1. Assumptions and Sources'!$D$35))*('1. Assumptions and Sources'!$D$38/('1. Assumptions and Sources'!$D$37+'1. Assumptions and Sources'!$D$38)) -> 18.418297 | G31: Rs Cr | H31: Claims value x leakage pool x reduction in the UNDETECTED share, then the graph's 18 of 28 pp share. Hits the LOSS ratio.
B32: W-20 | C32: Fraud avoided: CAPTURE INTEGRITY GATE | D32: =D15*'1. Assumptions and Sources'!$D$39*(1-(1-'1. Assumptions and Sources'!$D$36)/(1-'1. Assumptions and Sources'!$D$35))*('1. Assumptions and Sources'!$D$37/('1. Assumptions and Sources'!$D$37+'1. Assumptions and Sources'!$D$38)) -> 2.0464775 | E32: =E15*'1. Assumptions and Sources'!$D$39*(1-(1-'1. Assumptions and Sources'!$D$36)/(1-'1. Assumptions and Sources'!$D$35))*('1. Assumptions and Sources'!$D$37/('1. Assumptions and Sources'!$D$37+'1. Assumptions and Sources'!$D$38)) -> 6.1394325 | F32: =F15*'1. Assumptions and Sources'!$D$39*(1-(1-'1. Assumptions and Sources'!$D$36)/(1-'1. Assumptions and Sources'!$D$35))*('1. Assumptions and Sources'!$D$37/('1. Assumptions and Sources'!$D$37+'1. Assumptions and Sources'!$D$38)) -> 10.232387 | G32: Rs Cr | H32: Same chain, the gate's 10 of 28 pp share. EXIF and metadata contradiction caught at intake.
B33: W-21 | C33: Synthetic-media exposure avoided: THE GATE | D33: =D15*'1. Assumptions and Sources'!$D$40*'1. Assumptions and Sources'!$D$41 -> 2.0984515 | E33: =E15*'1. Assumptions and Sources'!$D$40*'1. Assumptions and Sources'!$D$41 -> 6.2953546 | F33: =F15*'1. Assumptions and Sources'!$D$40*'1. Assumptions and Sources'!$D$41 -> 10.492258 | G33: Rs Cr | H33: Claims value x synthetic-fraud incidence x gate detection rate. A NEW vector, additive to W-19 and W-20. Nobody else defends against it.
B34: W-22 | C34: Renewal retention on the claimant cohort | D34: =D13*'1. Assumptions and Sources'!$D$43*'1. Assumptions and Sources'!$D$44*'1. Assumptions and Sources'!$D$45/10000000 -> 0.19201517 | E34: =E13*'1. Assumptions and Sources'!$D$43*'1. Assumptions and Sources'!$D$44*'1. Assumptions and Sources'!$D$45/10000000 -> 0.57604552 | F34: =F13*'1. Assumptions and Sources'!$D$43*'1. Assumptions and Sources'!$D$44*'1. Assumptions and Sources'!$D$45/10000000 -> 0.96007586 | G34: Rs Cr | H34: Claims x average premium x renewal uplift x retained value. Distribution income, so it sits OUTSIDE the combined ratio.
B35: W-23 | C35: less: live-capture friction cost | D35: =-D13*'1. Assumptions and Sources'!$D$42*('1. Assumptions and Sources'!$D$29-'1. Assumptions and Sources'!$D$28)*'1. Assumptions and Sources'!D$55/10000000 -> -0.23700158 | E35: =-E13*'1. Assumptions and Sources'!$D$42*('1. Assumptions and Sources'!$D$29-'1. Assumptions and Sources'!$D$28)*'1. Assumptions and Sources'!E$55/10000000 -> -0.59250396 | F35: =-F13*'1. Assumptions and Sources'!$D$42*('1. Assumptions and Sources'!$D$29-'1. Assumptions and Sources'!$D$28)*'1. Assumptions and Sources'!F$55/10000000 -> -0.79000528 | G35: Rs Cr | H35: 8% of claims take amber-lane touches instead of green. The cost of the hard live-capture rule.
B36: W-24 | C36: GROSS ANNUAL BENEFIT | D36: =SUM(D30:D35) -> 15.359972 | E36: =SUM(E30:E35) -> 47.210612 | F36: =SUM(F30:F35) -> 80.568845 | G36: Rs Cr | H36: Sum of the six lines above.
B38: PART D — BUILD COST, ONE-OFF · identical in all three plans (you build the same system)
B39: Ref | C39: Component | D39: Rs Cr | E39: Phase | F39: Basis
B40: ='1. Assumptions and Sources'!$B$60 -> D-01 | C40: ='1. Assumptions and Sources'!$C$60 -> Document AI, OCR and field extraction | D40: ='1. Assumptions and Sources'!$D$60*'1. Assumptions and Sources'!$D$16*'1. Assumptions and Sources'!$D$14/10000000 -> 0.4382847 | E40: ='1. Assumptions and Sources'!$F$60 -> P1 | F40: ='1. Assumptions and Sources'!$G$60 -> Vendor NLP extraction band $20-45K
B41: ='1. Assumptions and Sources'!$B$61 -> D-02 | C41: ='1. Assumptions and Sources'!$C$61 -> Policy validation, RAG on actual wording | D41: ='1. Assumptions and Sources'!$D$61*'1. Assumptions and Sources'!$D$16*'1. Assumptions and Sources'!$D$14/10000000 -> 0.3130605 | E41: ='1. Assumptions and Sources'!$F$61 -> P1 | F41: ='1. Assumptions and Sources'!$G$61 -> Vendor RAG build band $20-60K
B42: ='1. Assumptions and Sources'!$B$62 -> D-03 | C42: ='1. Assumptions and Sources'!$C$62 -> EXIF and metadata forensics engine | D42: ='1. Assumptions and Sources'!$D$62*'1. Assumptions and Sources'!$D$16*'1. Assumptions and Sources'!$D$14/10000000 -> 0.3130605 | E42: ='1. Assumptions and Sources'!$F$62 -> P1 | F42: ='1. Assumptions and Sources'!$G$62 -> CAPTURE INTEGRITY GATE. Rules-based, zero model training.
B43: ='1. Assumptions and Sources'!$B$63 -> D-04 | C43: ='1. Assumptions and Sources'!$C$63 -> Synthetic and tampered image screening | D43: ='1. Assumptions and Sources'!$D$63*'1. Assumptions and Sources'!$D$16*'1. Assumptions and Sources'!$D$14/10000000 -> 0.626121 | E43: ='1. Assumptions and Sources'!$F$63 -> P2 | F43: ='1. Assumptions and Sources'!$G$63 -> CAPTURE INTEGRITY GATE. The moat. Diffusion and GAN artefact classifier tuned on own media.
B44: ='1. Assumptions and Sources'!$B$64 -> D-05 | C44: ='1. Assumptions and Sources'!$C$64 -> Guided live-capture SDK, gallery disabled | D44: ='1. Assumptions and Sources'!$D$64*'1. Assumptions and Sources'!$D$16*'1. Assumptions and Sources'!$D$14/10000000 -> 0.3756726 | E44: ='1. Assumptions and Sources'!$F$64 -> P1 | F44: ='1. Assumptions and Sources'!$G$64 -> CAPTURE INTEGRITY GATE. The hard rule that makes the other two checks reliable.
B45: ='1. Assumptions and Sources'!$B$65 -> D-06 | C45: ='1. Assumptions and Sources'!$C$65 -> CV damage assessment, 360 video and depth | D45: ='1. Assumptions and Sources'!$D$65*'1. Assumptions and Sources'!$D$16*'1. Assumptions and Sources'!$D$14/10000000 -> 1.0017936 | E45: ='1. Assumptions and Sources'!$F$65 -> P2 | F45: ='1. Assumptions and Sources'!$G$65 -> Two independent sources, $80-180K band
B46: ='1. Assumptions and Sources'!$B$66 -> D-07 | C46: ='1. Assumptions and Sources'!$C$66 -> Repair cost estimation engine | D46: ='1. Assumptions and Sources'!$D$66*'1. Assumptions and Sources'!$D$16*'1. Assumptions and Sources'!$D$14/10000000 -> 0.5008968 | E46: ='1. Assumptions and Sources'!$F$66 -> P2 | F46: ='1. Assumptions and Sources'!$G$66 -> Settled claims plus live parts feeds. Garage APIs.
B47: ='1. Assumptions and Sources'!$B$67 -> D-08 | C47: ='1. Assumptions and Sources'!$C$67 -> Fraud and duplicate graph engine | D47: ='1. Assumptions and Sources'!$D$67*'1. Assumptions and Sources'!$D$16*'1. Assumptions and Sources'!$D$14/10000000 -> 1.0017936 | E47: ='1. Assumptions and Sources'!$F$67 -> P3 | F47: ='1. Assumptions and Sources'!$G$67 -> Two sources, $80-100K real-time financial fraud
B48: ='1. Assumptions and Sources'!$B$68 -> D-09 | C48: ='1. Assumptions and Sources'!$C$68 -> Trust Score orchestration core | D48: ='1. Assumptions and Sources'!$D$68*'1. Assumptions and Sources'!$D$16*'1. Assumptions and Sources'!$D$14/10000000 -> 1.878363 | E48: ='1. Assumptions and Sources'!$F$68 -> P4 | F48: ='1. Assumptions and Sources'!$G$68 -> Multi-model parallel orchestration, $150-300K band
B49: ='1. Assumptions and Sources'!$B$69 -> D-10 | C49: ='1. Assumptions and Sources'!$C$69 -> Production hardening | D49: ='1. Assumptions and Sources'!$D$69*'1. Assumptions and Sources'!$D$16*'1. Assumptions and Sources'!$D$14/10000000 -> 0.7513452 | E49: ='1. Assumptions and Sources'!$F$69 -> P4 | F49: ='1. Assumptions and Sources'!$G$69 -> 40% of orchestration. Audit trail, human override, rollback, explainability.
B50: ='1. Assumptions and Sources'!$B$70 -> D-11 | C50: ='1. Assumptions and Sources'!$C$70 -> Claimant, surveyor and garage consoles | D50: ='1. Assumptions and Sources'!$D$70*'1. Assumptions and Sources'!$D$16*'1. Assumptions and Sources'!$D$14/10000000 -> 0.4382847 | E50: ='1. Assumptions and Sources'!$F$70 -> P4 | F50: ='1. Assumptions and Sources'!$G$70 -> Submission, tracking, proactive status push
B51: ='1. Assumptions and Sources'!$B$71 -> D-12 | C51: ='1. Assumptions and Sources'!$C$71 -> Systems integration | D51: ='1. Assumptions and Sources'!$D$71*'1. Assumptions and Sources'!$D$16*'1. Assumptions and Sources'!$D$14/10000000 -> 1.0017936 | E51: ='1. Assumptions and Sources'!$F$71 -> Cross | F51: ='1. Assumptions and Sources'!$G$71 -> VAHAN, garage, policy DB, payment, CRM, surveyor, WhatsApp, mobile. No published benchmark exists; an SI quote is a pre-build gate.
B52: ='1. Assumptions and Sources'!$B$72 -> D-13 | C52: ='1. Assumptions and Sources'!$C$72 -> Training data: labelled damage and synthetic set | D52: ='1. Assumptions and Sources'!$E$72/10000000 -> 0.6 | E52: ='1. Assumptions and Sources'!$F$72 -> P2 | F52: ='1. Assumptions and Sources'!$G$72 -> CAPTURE INTEGRITY GATE. Real Indian damage media plus generated fakes to train the classifier.
B53: ='1. Assumptions and Sources'!$B$73 -> D-14 | C53: ='1. Assumptions and Sources'!$C$73 -> Model QC and UAT window | D53: ='1. Assumptions and Sources'!$E$73/10000000 -> 0.4 | E53: ='1. Assumptions and Sources'!$F$73 -> Cross | F53: ='1. Assumptions and Sources'!$G$73 -> Shadow to canary to gradual, plus model-output quality assurance
B54: ='1. Assumptions and Sources'!$B$74 -> D-15 | C54: ='1. Assumptions and Sources'!$C$74 -> Security, DPDP and SOC2 setup | D54: ='1. Assumptions and Sources'!$E$74/10000000 -> 0.25 | E54: ='1. Assumptions and Sources'!$F$74 -> Cross | F54: ='1. Assumptions and Sources'!$G$74 -> India pentest, SOC2 tooling, compliance engineering. One-off, separate from ongoing monitoring.
B55: W-25 | C55: TOTAL BUILD COST | D55: =SUM(D40:D54) -> 9.8904698 | E55: All | F55: USD lines x A-10 India uplift x A-08 FX, plus the three rupee lines.
B57: PART E — ANNUAL RUN COST (Rs Cr)
B58: Ref | C58: Cost line | D58: Conservative | E58: Base | F58: Aggressive | G58: Unit | H58: How it is derived
B59: W-26 | C59: GPU compute, peak-sized | D59: =D13*'1. Assumptions and Sources'!$D$78*'1. Assumptions and Sources'!$D$79*'1. Assumptions and Sources'!$D$80*'1. Assumptions and Sources'!$D$81*'1. Assumptions and Sources'!$D$14/10000000 -> 0.62739429 | E59: =E13*'1. Assumptions and Sources'!$D$78*'1. Assumptions and Sources'!$D$79*'1. Assumptions and Sources'!$D$80*'1. Assumptions and Sources'!$D$81*'1. Assumptions and Sources'!$D$14/10000000 -> 1.8821829 | F59: =F13*'1. Assumptions and Sources'!$D$78*'1. Assumptions and Sources'!$D$79*'1. Assumptions and Sources'!$D$80*'1. Assumptions and Sources'!$D$81*'1. Assumptions and Sources'!$D$14/10000000 -> 3.1369715 | G59: Rs Cr | H59: Claims x GPU hours x peak multiplier x safety margin x rate x FX. Sized on provisioned peak capacity because claims cluster. Sheet 13 sets the right-sizing decision rule.
B60: W-27 | C60: Storage | D60: =D13*'1. Assumptions and Sources'!$D$82*'1. Assumptions and Sources'!$D$14*'1. Assumptions and Sources'!$D$83/10000000 -> 0.067967885 | E60: =E13*'1. Assumptions and Sources'!$D$82*'1. Assumptions and Sources'!$D$14*'1. Assumptions and Sources'!$D$83/10000000 -> 0.20390365 | F60: =F13*'1. Assumptions and Sources'!$D$82*'1. Assumptions and Sources'!$D$14*'1. Assumptions and Sources'!$D$83/10000000 -> 0.33983942 | G60: Rs Cr | H60: Claims x USD per claim x FX x replication multiplier.
B61: W-28 | C61: MLOps tooling | D61: ='1. Assumptions and Sources'!$D$84*'1. Assumptions and Sources'!$D$14*12/10000000 -> 0.80052 | E61: ='1. Assumptions and Sources'!$D$84*'1. Assumptions and Sources'!$D$14*12/10000000 -> 0.80052 | F61: ='1. Assumptions and Sources'!$D$84*'1. Assumptions and Sources'!$D$14*12/10000000 -> 0.80052 | G61: Rs Cr | H61: E-07 x FX x 12. Fixed.
B62: W-29 | C62: Operations team | D62: ='1. Assumptions and Sources'!$D$85*12/10000000 -> 0.6440004 | E62: ='1. Assumptions and Sources'!$D$85*12/10000000 -> 0.6440004 | F62: ='1. Assumptions and Sources'!$D$85*12/10000000 -> 0.6440004 | G62: Rs Cr | H62: E-08 x 12. Fixed.
B63: W-30 | C63: Security and compliance monitoring | D63: ='1. Assumptions and Sources'!$D$86*12/10000000 -> 0.2499996 | E63: ='1. Assumptions and Sources'!$D$86*12/10000000 -> 0.2499996 | F63: ='1. Assumptions and Sources'!$D$86*12/10000000 -> 0.2499996 | G63: Rs Cr | H63: E-09 x 12. Fixed. Separate from the one-off setup in D-15.
B64: W-31 | C64: Legal and regulatory counsel | D64: ='1. Assumptions and Sources'!$D$87*12/10000000 -> 0.12 | E64: ='1. Assumptions and Sources'!$D$87*12/10000000 -> 0.12 | F64: ='1. Assumptions and Sources'!$D$87*12/10000000 -> 0.12 | G64: Rs Cr | H64: E-10 x 12. Fixed.
B65: W-32 | C65: TOTAL ANNUAL RUN COST | D65: =SUM(D59:D64) -> 2.5098822 | E65: =SUM(E59:E64) -> 3.9006065 | F65: =SUM(F59:F64) -> 5.2913309 | G65: Rs Cr | H65: Two volume-scaled lines plus four fixed lines.
B67: PART F — NET RESULT
B68: Ref | C68: Metric | D68: Conservative | E68: Base | F68: Aggressive | G68: Unit | H68: How it is derived
B69: W-33 | C69: Gross annual benefit | D69: =D36 -> 15.359972 | E69: =E36 -> 47.210612 | F69: =F36 -> 80.568845 | G69: Rs Cr | H69: From Part C.
B70: W-34 | C70: Annual run cost | D70: =D65 -> 2.5098822 | E70: =E65 -> 3.9006065 | F70: =F65 -> 5.2913309 | G70: Rs Cr | H70: From Part E.
B71: W-35 | C71: NET ANNUAL BENEFIT | D71: =D69-D70 -> 12.85009 | E71: =E69-E70 -> 43.310005 | F71: =F69-F70 -> 75.277514 | G71: Rs Cr | H71: Steady state, at the plan's rollout.
B72: W-36 | C72: Net monthly benefit | D72: =D71/12 -> 1.0708408 | E72: =E71/12 -> 3.6091671 | F72: =F71/12 -> 6.2731261 | G72: Rs Cr | H72: Net annual benefit divided by twelve.
B73: W-37 | C73: Build cost, one-off | D73: =$D$55 -> 9.8904698 | E73: =$D$55 -> 9.8904698 | F73: =$D$55 -> 9.8904698 | G73: Rs Cr | H73: From Part D. Flat across plans.
B74: W-38 | C74: PAYBACK on steady-state economics | D74: =IF(D72>0,D73/D72,"n/a") -> 9.2361717 | E74: =IF(E72>0,E73/E72,"n/a") -> 2.7403746 | F74: =IF(F72>0,F73/F72,"n/a") -> 1.5766413 | G74: months | H74: Build cost divided by net monthly benefit. Payback from project kickoff, at Sheet 4 FS-05, is the number the deck quotes.
B76: PART G — INSURANCE P&L BRIDGE · combined ratio = loss ratio + expense ratio
B77: Ref | C77: Metric | D77: Conservative | E77: Base | F77: Aggressive | G77: Unit | H77: How it is derived
B78: W-39 | C78: Motor OD net earned premium | D78: =D8 -> 1654.6692 | E78: =E8 -> 1654.6692 | F78: =F8 -> 1654.6692 | G78: Rs Cr | H78: From W-02.
B79: W-40 | C79: Rs per 1 pp of Motor OD ratio | D79: =D78*0.01 -> 16.546692 | E79: =E78*0.01 -> 16.546692 | F79: =F78*0.01 -> 16.546692 | G79: Rs Cr | H79: 1% of Motor OD earned premium.
B80: W-41 | C80: LOSS ratio impact (all three fraud lines) | D80: =(D31+D32+D33)/D79 -> 0.47312105 | E80: =(E31+E32+E33)/E79 -> 1.4193632 | F80: =(F31+F32+F33)/F79 -> 2.3656053 | G80: pp | H80: Fraud reduces incurred claims, so it moves the loss ratio.
B81: W-42 | C81: EXPENSE ratio impact (labour, net of friction and all run cost) | D81: =(D30+D35-D70)/D79 -> 0.29187019 | E81: =(E30+E35-E70)/E79 -> 1.1632654 | F81: =(F30+F35-F70)/F79 -> 2.125772 | G81: pp | H81: Claims-handling OPEX sits in the expense ratio.
B82: W-43 | C82: COMBINED RATIO IMPACT — MOTOR OD basis | D82: =D80+D81 -> 0.76499125 | E82: =E80+E81 -> 2.5826285 | F82: =F80+F81 -> 4.4913773 | G82: pp | H82: Loss plus expense, measured against Motor OD earned premium. Always quoted with its denominator.
B83: W-44 | C83: Bajaj total net earned premium, estimated | D83: ='1. Assumptions and Sources'!$D$11*'1. Assumptions and Sources'!$D$8 -> 10205.947 | E83: ='1. Assumptions and Sources'!$D$11*'1. Assumptions and Sources'!$D$8 -> 10205.947 | F83: ='1. Assumptions and Sources'!$D$11*'1. Assumptions and Sources'!$D$8 -> 10205.947 | G83: Rs Cr | H83: A-05 total GDPI x A-02 NEP ratio. Used only for the group-basis view.
B84: W-45 | C84: Rs per 1 pp of group ratio | D84: =D83*0.01 -> 102.05947 | E84: =E83*0.01 -> 102.05947 | F84: =F83*0.01 -> 102.05947 | G84: Rs Cr | H84: 1% of group earned premium.
B85: W-46 | C85: COMBINED RATIO IMPACT — GROUP basis | D85: =(D31+D32+D33+D30+D35-D70)/D84 -> 0.12402646 | E85: =(E31+E32+E33+E30+E35-E70)/E84 -> 0.41871627 | F85: =(F31+F32+F33+F30+F35-F70)/F84 -> 0.72817779 | G85: pp | H85: The SAME rupees against the whole book. Never subtract the Motor OD figure from a group combined ratio.
B86: W-47 | C86: Distribution income (renewal), outside the combined ratio | D86: =D34 -> 0.19201517 | E86: =E34 -> 0.57604552 | F86: =F34 -> 0.96007586 | G86: Rs Cr | H86: Commission is not an underwriting item, so it is excluded from both ratios above.
B88: PART H — DOWNSIDE TESTS · what happens when our two weakest assumptions break
B89: Ref | C89: Test line | D89: Conservative | E89: Base | F89: Aggressive | G89: Unit | H89: How it is derived
B90: W-48 | C90: Labour benefit at the IN-HOUSE touch cost | D90: =D13*D20*'1. Assumptions and Sources'!$D$92/10000000 -> 2.627371 | E90: =E13*E20*'1. Assumptions and Sources'!$D$92/10000000 -> 7.8821131 | F90: =F13*F20*'1. Assumptions and Sources'!$D$92/10000000 -> 13.136855 | G90: Rs Cr | H90: Rs 83 per touch in place of Rs 250. Tests H-03.
B91: W-49 | C91: Fraud avoided if detection lands at 82% | D91: =D15*'1. Assumptions and Sources'!$D$39*(1-(1-'1. Assumptions and Sources'!$D$93)/(1-'1. Assumptions and Sources'!$D$35)) -> 4.092955 | E91: =E15*'1. Assumptions and Sources'!$D$39*(1-(1-'1. Assumptions and Sources'!$D$93)/(1-'1. Assumptions and Sources'!$D$35)) -> 12.278865 | F91: =F15*'1. Assumptions and Sources'!$D$39*(1-(1-'1. Assumptions and Sources'!$D$93)/(1-'1. Assumptions and Sources'!$D$35)) -> 20.464775 | G91: Rs Cr | H91: Both fraud lines combined, at the 82% detection landing (F-02).
B92: W-50 | C92: less: friction cost at the in-house rate | D92: =-D13*'1. Assumptions and Sources'!$D$42*('1. Assumptions and Sources'!$D$29-'1. Assumptions and Sources'!$D$28)*'1. Assumptions and Sources'!$D$92/10000000 -> -0.065570438 | E92: =-E13*'1. Assumptions and Sources'!$D$42*('1. Assumptions and Sources'!$D$29-'1. Assumptions and Sources'!$D$28)*'1. Assumptions and Sources'!$D$92/10000000 -> -0.19671132 | F92: =-F13*'1. Assumptions and Sources'!$D$42*('1. Assumptions and Sources'!$D$29-'1. Assumptions and Sources'!$D$28)*'1. Assumptions and Sources'!$D$92/10000000 -> -0.32785219 | G92: Rs Cr | H92: Consistent with W-48.
B93: W-51 | C93: Downside net annual benefit | D93: =D90+D91+D92-D70 -> 4.1448734 | E93: =E90+E91+E92-E70 -> 16.06366 | F93: =F90+F91+F92-F70 -> 27.982447 | G93: Rs Cr | H93: In-house labour cost AND fraud at 82% AND zero synthetic-media benefit AND zero renewal benefit.
B94: W-52 | C94: Floor net annual benefit | D94: =D90+D92-D70 -> 0.051918422 | E94: =E90+E92-E70 -> 3.7847953 | F94: =F90+F92-F70 -> 7.5176721 | G94: Rs Cr | H94: Labour only, at in-house rates, with NO fraud benefit whatsoever. The absolute worst case.
B95: W-53 | C95: Payback — as modelled | D95: =D74 -> 9.2361717 | E95: =E74 -> 2.7403746 | F95: =F74 -> 1.5766413 | G95: months | H95: From Part F. Steady-state basis; the kickoff-basis figure is at Sheet 4 FS-05.
B96: W-54 | C96: Payback — realistic downside | D96: =IF(D93>0,D73/(D93/12),"does not pay back") -> 28.634321 | E96: =IF(E93>0,E73/(E93/12),"does not pay back") -> 7.3884554 | F96: =IF(F93>0,F73/(F93/12),"does not pay back") -> 4.2414317 | G96: months | H96: Net benefit with in-house labour cost, fraud at 82 per cent, and no synthetic-media or renewal benefit.
B97: W-55 | C97: Payback — absolute floor | D97: =IF(D94>0,D73/(D94/12),"does not pay back") -> 2286.0024 | E97: =IF(E94>0,E73/(E94/12),"does not pay back") -> 31.358536 | F97: =IF(F94>0,F73/(F94/12),"does not pay back") -> 15.787552 | G97: months | H97: Labour only at in-house rates, zero fraud.
B99: PART I — STAKEHOLDER VALUE SPLIT · who books each rupee, and who is affected without booking one
B100: Ref | C100: Metric | D100: Conservative | E100: Base | F100: Aggressive | G100: Unit | H100: How it is derived
B101: W-56 | C101: Bajaj General claims operations — EXPENSE-ratio value | D101: =D30+D35 -> 7.3393685 | E101: =E30+E35 -> 23.148801 | F101: =F30+F35 -> 40.465826 | G101: Rs Cr | H101: Labour saving less the live-capture friction cost. Booked in the expense ratio.
B102: W-57 | C102: Bajaj General underwriting — LOSS-ratio value | D102: =D31+D32+D33 -> 7.8285885 | E102: =E31+E32+E33 -> 23.485766 | F102: =F31+F32+F33 -> 39.142943 | G102: Rs Cr | H102: All three fraud lines: graph, capture gate and synthetic media. Booked in the loss ratio.
B103: W-58 | C103: BFDL distribution — renewal value | D103: =D34 -> 0.19201517 | E103: =E34 -> 0.57604552 | F103: =F34 -> 0.96007586 | G103: Rs Cr | H103: Retained commission and margin. Sits outside the combined ratio.
B104: W-59 | C104: less: platform run cost | D104: =-D65 -> -2.5098822 | E104: =-E65 -> -3.9006065 | F104: =-F65 -> -5.2913309 | G104: Rs Cr | H104: Borne by whichever entity operates the platform. Shown separately so the split is honest.
B105: W-60 | C105: CHECK — split less W-35, must be zero | D105: =D101+D102+D103+D104-D71 -> 0 | E105: =E101+E102+E103+E104-E71 -> 0 | F105: =F101+F102+F103+F104-F71 -> 0 | G105: Rs Cr | H105: Integrity check. If this is not zero the stakeholder split has drifted from the P&L.
B106: W-61 | C106: Claim TAT saved per on-platform claim | D106: =D22-D23 -> 7.09 | E106: =E22-E23 -> 7.09 | F106: =F22-F23 -> 7.09 | G106: days | H106: Today’s 9.8 days less the post-friction platform TAT of 2.71 days.
B107: W-62 | C107: CLAIMANT-DAYS RETURNED PER YEAR | D107: =D13*D106 -> 388967.88 | E107: =E13*E106 -> 1166903.6 | F107: =F13*F106 -> 1944839.4 | G107: days | H107: On-platform claims x TAT saved. The claimant-facing headline, and it scales with rollout.
B108: W-63 | C108: Claims auto-settled with zero human touch | D108: =D13*'1. Assumptions and Sources'!$D$25 -> 35659.961 | E108: =E13*'1. Assumptions and Sources'!$D$25 -> 106979.88 | F108: =F13*'1. Assumptions and Sources'!$D$25 -> 178299.8 | G108: claims | H108: Green-lane share (B-03) of on-platform claims.
B109: W-64 | C109: Claims still reviewed by a human | D109: =D13-D108 -> 19201.517 | E109: =E13-E108 -> 57604.552 | F109: =F13-F108 -> 96007.586 | G109: claims | H109: Amber and red lanes. Judgement is redeployed, not removed.
B110: W-65 | C110: Share of the book still on the 9.8-day journey | D110: =1-D12 -> 0.8 | E110: =1-E12 -> 0.4 | F110: =1-F12 -> 0 | G110: ratio | H110: The counterweight: rollout defines who is NOT reached. Conservative leaves 80% untouched.
...

Sheet 4. Forecast
B2: Three-Year Forecast
B3: One block per implementation plan. Year 0 is the 10-month build with no benefit. Benefit ramps through Year 1 and reaches steady state in Year 3. Run cost is charged in full from Year 1, which is deliberately conservative.
B5: CONSERVATIVE · 20% rollout
B6: Ref | C6: Line | D6: Year 0 | E6: Year 1 | F6: Year 2 | G6: Year 3 | H6: 3-yr total | I6: Unit
B7: F-01 | C7: Benefit realisation factor | E7: ='1. Assumptions and Sources'!$D$46 -> 0.45 | F7: ='1. Assumptions and Sources'!$D$47 -> 0.92 | G7: ='1. Assumptions and Sources'!$D$48 -> 1 | I7: ratio
B8: F-02 | C8: Market growth factor | E8: 1 | F8: =1+'1. Assumptions and Sources'!$D$12 -> 1.087 | G8: =(1+'1. Assumptions and Sources'!$D$12)^2 -> 1.181569 | I8: x
B9: F-03 | C9: Claims processed | E9: ='3. Workings'!$D$13*E7*E8 -> 24687.665 | F9: ='3. Workings'!$D$13*F7*F8 -> 54863.672 | G9: ='3. Workings'!$D$13*G7*G8 -> 64822.622 | H9: =SUM(E9:G9) -> 144373.96 | I9: claims
B10: F-04 | C10: Gross benefit | E10: ='3. Workings'!$D$36*E7*E8 -> 6.9119875 | F10: ='3. Workings'!$D$36*F7*F8 -> 15.360587 | G10: ='3. Workings'!$D$36*G7*G8 -> 18.148867 | H10: =SUM(E10:G10) -> 40.421441 | I10: Rs Cr
B11: F-05 | C11: Run cost | E11: ='3. Workings'!$D$65*E8 -> 2.5098822 | F11: ='3. Workings'!$D$65*F8 -> 2.7282419 | G11: ='3. Workings'!$D$65*G8 -> 2.965599 | H11: =SUM(E11:G11) -> 8.2037231 | I11: Rs Cr
B12: F-06 | C12: Build cost | D12: ='3. Workings'!$D$55 -> 9.8904698 | E12: 0 | F12: 0 | G12: 0 | H12: =D12 -> 9.8904698 | I12: Rs Cr
B13: F-07 | C13: NET BENEFIT | D13: =-D12 -> -9.8904698 | E13: =E10-E11-E12 -> 4.4021053 | F13: =F10-F11-F12 -> 12.632345 | G13: =G10-G11-G12 -> 15.183268 | H13: =SUM(E13:G13) -> 32.217718 | I13: Rs Cr
B14: F-08 | C14: Risk-adjusted net benefit | D14: =D13 -> -9.8904698 | E14: =IF(E13>0,E13*(1-'1. Assumptions and Sources'!$D$50),E13) -> 3.3566053 | F14: =IF(F13>0,F13*(1-'1. Assumptions and Sources'!$D$50),F13) -> 9.6321628 | G14: =IF(G13>0,G13*(1-'1. Assumptions and Sources'!$D$50),G13) -> 11.577242 | H14: =SUM(E14:G14) -> 24.56601 | I14: Rs Cr
B15: F-09 | C15: Cumulative net position | D15: =D13 -> -9.8904698 | E15: =D15+E13 -> -5.4883645 | F15: =E15+F13 -> 7.1439802 | G15: =F15+G13 -> 22.327248 | I15: Rs Cr
B18: BASE · 60% rollout
B19: Ref | C19: Line | D19: Year 0 | E19: Year 1 | F19: Year 2 | G19: Year 3 | H19: 3-yr total | I19: Unit
B20: F-01 | C20: Benefit realisation factor | E20: ='1. Assumptions and Sources'!$D$46 -> 0.45 | F20: ='1. Assumptions and Sources'!$D$47 -> 0.92 | G20: ='1. Assumptions and Sources'!$D$48 -> 1 | I20: ratio
B21: F-02 | C21: Market growth factor | E21: 1 | F21: =1+'1. Assumptions and Sources'!$D$12 -> 1.087 | G21: =(1+'1. Assumptions and Sources'!$D$12)^2 -> 1.181569 | I21: x
B22: F-03 | C22: Claims processed | E22: ='3. Workings'!$E$13*E20*E21 -> 74062.995 | F22: ='3. Workings'!$E$13*F20*F21 -> 164591.02 | G22: ='3. Workings'!$E$13*G20*G21 -> 194467.86 | H22: =SUM(E22:G22) -> 433121.88 | I22: claims
B23: F-04 | C23: Gross benefit | E23: ='3. Workings'!$E$36*E20*E21 -> 21.244775 | F23: ='3. Workings'!$E$36*F20*F21 -> 47.2125 | G23: ='3. Workings'!$E$36*G20*G21 -> 55.782595 | H23: =SUM(E23:G23) -> 124.23987 | I23: Rs Cr
B24: F-05 | C24: Run cost | E24: ='3. Workings'!$E$65*E21 -> 3.9006065 | F24: ='3. Workings'!$E$65*F21 -> 4.2399593 | G24: ='3. Workings'!$E$65*G21 -> 4.6088358 | H24: =SUM(E24:G24) -> 12.749402 | I24: Rs Cr
B25: F-06 | C25: Build cost | D25: ='3. Workings'!$D$55 -> 9.8904698 | E25: 0 | F25: 0 | G25: 0 | H25: =D25 -> 9.8904698 | I25: Rs Cr
B26: F-07 | C26: NET BENEFIT | D26: =-D25 -> -9.8904698 | E26: =E23-E24-E25 -> 17.344169 | F26: =F23-F24-F25 -> 42.972541 | G26: =G23-G24-G25 -> 51.173759 | H26: =SUM(E26:G26) -> 111.49047 | I26: Rs Cr
B27: F-08 | C27: Risk-adjusted net benefit | D27: =D26 -> -9.8904698 | E27: =IF(E26>0,E26*(1-'1. Assumptions and Sources'!$D$50),E26) -> 13.224929 | F27: =IF(F26>0,F26*(1-'1. Assumptions and Sources'!$D$50),F26) -> 32.766562 | G27: =IF(G26>0,G26*(1-'1. Assumptions and Sources'!$D$50),G26) -> 39.019992 | H27: =SUM(E27:G27) -> 85.011483 | I27: Rs Cr
B28: F-09 | C28: Cumulative net position | D28: =D26 -> -9.8904698 | E28: =D28+E26 -> 7.4536989 | F28: =E28+F26 -> 50.42624 | G28: =F28+G26 -> 101.6 | I28: Rs Cr
B31: AGGRESSIVE · 100% rollout
B32: Ref | C32: Line | D32: Year 0 | E32: Year 1 | F32: Year 2 | G32: Year 3 | H32: 3-yr total | I32: Unit
B33: F-01 | C33: Benefit realisation factor | E33: ='1. Assumptions and Sources'!$D$46 -> 0.45 | F33: ='1. Assumptions and Sources'!$D$47 -> 0.92 | G33: ='1. Assumptions and Sources'!$D$48 -> 1 | I33: ratio
B34: F-02 | C34: Market growth factor | E34: 1 | F34: =1+'1. Assumptions and Sources'!$D$12 -> 1.087 | G34: =(1+'1. Assumptions and Sources'!$D$12)^2 -> 1.181569 | I34: x
B35: F-03 | C35: Claims processed | E35: ='3. Workings'!$F$13*E33*E34 -> 123438.33 | F35: ='3. Workings'!$F$13*F33*F34 -> 274318.36 | G35: ='3. Workings'!$F$13*G33*G34 -> 324113.11 | H35: =SUM(E35:G35) -> 721869.8 | I35: claims
B36: F-04 | C36: Gross benefit | E36: ='3. Workings'!$F$36*E33*E34 -> 36.25598 | F36: ='3. Workings'!$F$36*F33*F34 -> 80.572067 | G36: ='3. Workings'!$F$36*G33*G34 -> 95.197649 | H36: =SUM(E36:G36) -> 212.0257 | I36: Rs Cr
B37: F-05 | C37: Run cost | E37: ='3. Workings'!$F$65*E34 -> 5.2913309 | F37: ='3. Workings'!$F$65*F34 -> 5.7516767 | G37: ='3. Workings'!$F$65*G34 -> 6.2520725 | H37: =SUM(E37:G37) -> 17.29508 | I37: Rs Cr
B38: F-06 | C38: Build cost | D38: ='3. Workings'!$D$55 -> 9.8904698 | E38: 0 | F38: 0 | G38: 0 | H38: =D38 -> 9.8904698 | I38: Rs Cr
B39: F-07 | C39: NET BENEFIT | D39: =-D38 -> -9.8904698 | E39: =E36-E37-E38 -> 30.964649 | F39: =F36-F37-F38 -> 74.820391 | G39: =G36-G37-G38 -> 88.945577 | H39: =SUM(E39:G39) -> 194.73062 | I39: Rs Cr
B40: F-08 | C40: Risk-adjusted net benefit | D40: =D39 -> -9.8904698 | E40: =IF(E39>0,E39*(1-'1. Assumptions and Sources'!$D$50),E39) -> 23.610545 | F40: =IF(F39>0,F39*(1-'1. Assumptions and Sources'!$D$50),F39) -> 57.050548 | G40: =IF(G39>0,G39*(1-'1. Assumptions and Sources'!$D$50),G39) -> 67.821002 | H40: =SUM(E40:G40) -> 148.4821 | I40: Rs Cr
B41: F-09 | C41: Cumulative net position | D41: =D39 -> -9.8904698 | E41: =D41+E39 -> 21.074179 | F41: =E41+F39 -> 95.89457 | G41: =F41+G39 -> 184.84015 | I41: Rs Cr
B44: FORECAST SUMMARY — ALL THREE PLANS
B45: Ref | C45: Metric | D45: Conservative | E45: Base | F45: Aggressive | G45: Unit
B46: FS-01 | C46: Build cost (Year 0) | D46: ='3. Workings'!$D$55 -> 9.8904698 | E46: ='3. Workings'!$D$55 -> 9.8904698 | F46: ='3. Workings'!$D$55 -> 9.8904698 | G46: Rs Cr
B47: FS-02 | C47: 3-year net benefit | D47: =$H$13 -> 32.217718 | E47: =$H$26 -> 111.49047 | F47: =$H$39 -> 194.73062 | G47: Rs Cr
B48: FS-03 | C48: 3-year net benefit, risk-adjusted | D48: =$H$14 -> 24.56601 | E48: =$H$27 -> 85.011483 | F48: =$H$40 -> 148.4821 | G48: Rs Cr
B49: FS-04 | C49: 3-year NPV at 12% | D49: =-'3. Workings'!$D$55+E13/(1+'1. Assumptions and Sources'!$D$15)+F13/(1+'1. Assumptions and Sources'!$D$15)^2+G13/(1+'1. Assumptions and Sources'!$D$15)^3 -> 14.91756 | E49: =-'3. Workings'!$D$55+E26/(1+'1. Assumptions and Sources'!$D$15)+F26/(1+'1. Assumptions and Sources'!$D$15)^2+G26/(1+'1. Assumptions and Sources'!$D$15)^3 -> 76.277313 | F49: =-'3. Workings'!$D$55+E39/(1+'1. Assumptions and Sources'!$D$15)+F39/(1+'1. Assumptions and Sources'!$D$15)^2+G39/(1+'1. Assumptions and Sources'!$D$15)^3 -> 140.7126 | G49: Rs Cr
B50: FS-05 | C50: Payback from project kickoff | D50: ='1. Assumptions and Sources'!$D$49+IF(E13>='3. Workings'!$D$55,'3. Workings'!$D$55/(E13/12),IF(E13+F13>='3. Workings'!$D$55,12+('3. Workings'!$D$55-E13)/(F13/12),IF(E13+F13+G13>='3. Workings'!$D$55,24+('3. Workings'!$D$55-E13-F13)/(G13/12),"beyond 3 years"))) -> 27.21363 | E50: ='1. Assumptions and Sources'!$D$49+IF(E26>='3. Workings'!$D$55,'3. Workings'!$D$55/(E26/12),IF(E26+F26>='3. Workings'!$D$55,12+('3. Workings'!$D$55-E26)/(F26/12),IF(E26+F26+G26>='3. Workings'!$D$55,24+('3. Workings'!$D$55-E26-F26)/(G26/12),"beyond 3 years"))) -> 16.842971 | F50: ='1. Assumptions and Sources'!$D$49+IF(E39>='3. Workings'!$D$55,'3. Workings'!$D$55/(E39/12),IF(E39+F39>='3. Workings'!$D$55,12+('3. Workings'!$D$55-E39)/(F39/12),IF(E39+F39+G39>='3. Workings'!$D$55,24+('3. Workings'!$D$55-E39-F39)/(G39/12),"beyond 3 years"))) -> 13.83294 | G50: months
C52: Payback from kickoff includes the ten-month build window before any benefit accrues. This is the project-basis figure and the one the deck quotes; the steady-state figure on Sheet 3 Part F is shorter because it excludes the build window.

Sheet 5. Investor Metrics
B2: Investor Metrics
B3: Unit economics, project DCF, ROIC and capital allocation. Every figure reads Sheets 2 to 4, so all three plans move together when an input changes.
B5: PART A — UNIT ECONOMICS · per claim
B6: Ref | C6: Metric | D6: Conservative | E6: Base | F6: Aggressive | G6: Unit | H6: How it is derived
B7: UE-01 | C7: Cost to serve per claim — TODAY | D7: ='1. Assumptions and Sources'!$D$24*'1. Assumptions and Sources'!$D$51 -> 1750 | E7: ='1. Assumptions and Sources'!$D$24*'1. Assumptions and Sources'!$D$51 -> 1750 | F7: ='1. Assumptions and Sources'!$D$24*'1. Assumptions and Sources'!$D$51 -> 1750 | G7: Rs | H7: Baseline touches (B-02) x baseline cost per touch (B-28). Identical in all three plans.
B8: UE-02 | C8: Blended manual touches after ClaimPulse | D8: ='3. Workings'!D19 -> 1.23 | E8: ='3. Workings'!E19 -> 1.23 | F8: ='3. Workings'!F19 -> 1.23 | G8: touches | H8: Lane-weighted from the Trust Score routing.
B9: UE-03 | C9: Cost to serve per claim — AFTER | D9: ='3. Workings'!D19*'1. Assumptions and Sources'!D$55 -> 369 | E9: ='3. Workings'!E19*'1. Assumptions and Sources'!E$55 -> 307.5 | F9: ='3. Workings'!F19*'1. Assumptions and Sources'!F$55 -> 246 | G9: Rs | H9: Blended touches x cost per touch.
B10: UE-04 | C10: Labour saving per claim | D10: =D7-D9 -> 1381 | E10: =E7-E9 -> 1442.5 | F10: =F7-F9 -> 1504 | G10: Rs | H10: UE-01 less UE-03. The per-unit prize.
B11: UE-05 | C11: Run cost per claim | D11: ='3. Workings'!D65*10000000/'3. Workings'!D13 -> 457.49445 | E11: ='3. Workings'!E65*10000000/'3. Workings'!E13 -> 236.99729 | F11: ='3. Workings'!F65*10000000/'3. Workings'!F13 -> 192.89786 | G11: Rs | H11: Total annual run cost / annual claims processed.
B12: UE-06 | C12: Fraud and synthetic exposure avoided per claim | D12: =('3. Workings'!D31+'3. Workings'!D32+'3. Workings'!D33)*10000000/'3. Workings'!D13 -> 1426.9737 | E12: =('3. Workings'!E31+'3. Workings'!E32+'3. Workings'!E33)*10000000/'3. Workings'!E13 -> 1426.9737 | F12: =('3. Workings'!F31+'3. Workings'!F32+'3. Workings'!F33)*10000000/'3. Workings'!F13 -> 1426.9737 | G12: Rs | H12: All three fraud lines spread across claims processed.
B13: UE-07 | C13: NET BENEFIT PER CLAIM | D13: ='3. Workings'!D71*10000000/'3. Workings'!D13 -> 2342.2792 | E13: ='3. Workings'!E71*10000000/'3. Workings'!E13 -> 2631.4764 | F13: ='3. Workings'!F71*10000000/'3. Workings'!F13 -> 2744.2758 | G13: Rs | H13: Net annual benefit / annual claims. The true per-unit economics.
B14: UE-08 | C14: Cost to serve as % of claim value — today | D14: =D7/'3. Workings'!D10 -> 0.038888889 | E14: =E7/'3. Workings'!E10 -> 0.038888889 | F14: =F7/'3. Workings'!F10 -> 0.038888889 | G14: ratio | H14: Sanity check against the Rs 45,000 average claim.
B15: UE-09 | C15: Cost to serve as % of claim value — after | D15: =(D9+D11)/'3. Workings'!D10 -> 0.018366543 | E15: =(E9+E11)/'3. Workings'!E10 -> 0.01209994 | F15: =(F9+F11)/'3. Workings'!F10 -> 0.0097532858 | G15: ratio | H15: Including platform run cost per claim.
B16: UE-10 | C16: Claim TAT per claim | D16: ='3. Workings'!D23 -> 2.71 | E16: ='3. Workings'!E23 -> 2.71 | F16: ='3. Workings'!F23 -> 2.71 | G16: days | H16: On-platform, after live-capture friction. 9.8 days today.
B17: UE-11 | C17: Break-even rollout, labour only | D17: =('3. Workings'!$D$55+'3. Workings'!D61+'3. Workings'!D62+'3. Workings'!D63+'3. Workings'!D64)/((D10-('3. Workings'!D59+'3. Workings'!D60)*10000000/'3. Workings'!D13)*'3. Workings'!D11/10000000) -> 0.34021149 | E17: =('3. Workings'!$D$55+'3. Workings'!E61+'3. Workings'!E62+'3. Workings'!E63+'3. Workings'!E64)/((E10-('3. Workings'!E59+'3. Workings'!E60)*10000000/'3. Workings'!E13)*'3. Workings'!E11/10000000) -> 0.32430954 | F17: =('3. Workings'!$D$55+'3. Workings'!F61+'3. Workings'!F62+'3. Workings'!F63+'3. Workings'!F64)/((F10-('3. Workings'!F59+'3. Workings'!F60)*10000000/'3. Workings'!F13)*'3. Workings'!F11/10000000) -> 0.30982777 | G17: ratio | H17: Rollout at which labour savings alone cover build plus a full year of run cost. Includes run cost, unlike a naive calculation.
B19: PART B — PROJECT DCF AND NPV · 5 years, same ramp convention as Sheet 4
B20: Ref | C20: Year | D20: Conservative | E20: Base | F20: Aggressive | G20: Discount factor | H20: Note
B21: DC-00 | C21: Year 0 — 10-month build | D21: =-'3. Workings'!$D$55 -> -9.8904698 | E21: =-'3. Workings'!$D$55 -> -9.8904698 | F21: =-'3. Workings'!$D$55 -> -9.8904698 | G21: =1 -> 1 | H21: Build cost only. No benefit accrues before go-live.
B22: DC-01 | C22: Year 1 — benefit ramping | D22: ='3. Workings'!D36*'1. Assumptions and Sources'!$D$46-'3. Workings'!D65 -> 4.4021053 | E22: ='3. Workings'!E36*'1. Assumptions and Sources'!$D$46-'3. Workings'!E65 -> 17.344169 | F22: ='3. Workings'!F36*'1. Assumptions and Sources'!$D$46-'3. Workings'!F65 -> 30.964649 | G22: =1/(1+'1. Assumptions and Sources'!$D$15)^1 -> 0.89285714 | H22: Gross benefit x realisation x growth, less run cost.
B23: DC-02 | C23: Year 2 | D23: ='3. Workings'!D36*'1. Assumptions and Sources'!$D$47*(1+'1. Assumptions and Sources'!$D$12)-'3. Workings'!D65*(1+'1. Assumptions and Sources'!$D$12) -> 12.632345 | E23: ='3. Workings'!E36*'1. Assumptions and Sources'!$D$47*(1+'1. Assumptions and Sources'!$D$12)-'3. Workings'!E65*(1+'1. Assumptions and Sources'!$D$12) -> 42.972541 | F23: ='3. Workings'!F36*'1. Assumptions and Sources'!$D$47*(1+'1. Assumptions and Sources'!$D$12)-'3. Workings'!F65*(1+'1. Assumptions and Sources'!$D$12) -> 74.820391 | G23: =1/(1+'1. Assumptions and Sources'!$D$15)^2 -> 0.79719388 | H23: Gross benefit x realisation x growth, less run cost.
B24: DC-03 | C24: Year 3 | D24: ='3. Workings'!D36*'1. Assumptions and Sources'!$D$48*(1+'1. Assumptions and Sources'!$D$12)^2-'3. Workings'!D65*(1+'1. Assumptions and Sources'!$D$12)^2 -> 15.183268 | E24: ='3. Workings'!E36*'1. Assumptions and Sources'!$D$48*(1+'1. Assumptions and Sources'!$D$12)^2-'3. Workings'!E65*(1+'1. Assumptions and Sources'!$D$12)^2 -> 51.173759 | F24: ='3. Workings'!F36*'1. Assumptions and Sources'!$D$48*(1+'1. Assumptions and Sources'!$D$12)^2-'3. Workings'!F65*(1+'1. Assumptions and Sources'!$D$12)^2 -> 88.945577 | G24: =1/(1+'1. Assumptions and Sources'!$D$15)^3 -> 0.71178025 | H24: Gross benefit x realisation x growth, less run cost.
B25: DC-04 | C25: Year 4 — steady state | D25: ='3. Workings'!D36*'1. Assumptions and Sources'!$D$48*(1+'1. Assumptions and Sources'!$D$12)^3-'3. Workings'!D65*(1+'1. Assumptions and Sources'!$D$12)^3 -> 16.504212 | E25: ='3. Workings'!E36*'1. Assumptions and Sources'!$D$48*(1+'1. Assumptions and Sources'!$D$12)^3-'3. Workings'!E65*(1+'1. Assumptions and Sources'!$D$12)^3 -> 55.625877 | F25: ='3. Workings'!F36*'1. Assumptions and Sources'!$D$48*(1+'1. Assumptions and Sources'!$D$12)^3-'3. Workings'!F65*(1+'1. Assumptions and Sources'!$D$12)^3 -> 96.683842 | G25: =1/(1+'1. Assumptions and Sources'!$D$15)^4 -> 0.63551808 | H25: Gross benefit x realisation x growth, less run cost.
B26: DC-05 | C26: Year 5 — steady state | D26: ='3. Workings'!D36*'1. Assumptions and Sources'!$D$48*(1+'1. Assumptions and Sources'!$D$12)^4-'3. Workings'!D65*(1+'1. Assumptions and Sources'!$D$12)^4 -> 17.940079 | E26: ='3. Workings'!E36*'1. Assumptions and Sources'!$D$48*(1+'1. Assumptions and Sources'!$D$12)^4-'3. Workings'!E65*(1+'1. Assumptions and Sources'!$D$12)^4 -> 60.465328 | F26: ='3. Workings'!F36*'1. Assumptions and Sources'!$D$48*(1+'1. Assumptions and Sources'!$D$12)^4-'3. Workings'!F65*(1+'1. Assumptions and Sources'!$D$12)^4 -> 105.09534 | G26: =1/(1+'1. Assumptions and Sources'!$D$15)^5 -> 0.56742686 | H26: Gross benefit x realisation x growth, less run cost.
B27: DC-06 | C27: 5-year cumulative, undiscounted | D27: =SUM(D21:D26) -> 56.771539 | E27: =SUM(E21:E26) -> 217.6912 | F27: =SUM(F21:F26) -> 386.61932 | H27: Sum of the six rows above.
B28: DC-07 | C28: 5-YEAR NPV at 12% | D28: =SUMPRODUCT(D21:D26,$G$21:$G$26) -> 35.585967 | E28: =SUMPRODUCT(E21:E26,$G$21:$G$26) -> 145.93821 | F28: =SUMPRODUCT(F21:F26,$G$21:$G$26) -> 261.79085 | H28: Net cash flow x discount factor.
B29: DC-08 | C29: 5-year IRR | D29: =IRR(D21:D26) -> 0.91015199 | E29: =IRR(E21:E26) -> 2.5513244 | F29: =IRR(F21:F26) -> 4.0658352 | H29: A small fixed build against a very large claims pool produces a high IRR. Carried in the annexure; payback and combined ratio lead.
B31: PART C — ROIC AND EVA
B32: Ref | C32: Metric | D32: Conservative | E32: Base | F32: Aggressive | G32: Unit | H32: Note
B33: RE-01 | C33: Net annual benefit, steady state | D33: ='3. Workings'!D71 -> 12.85009 | E33: ='3. Workings'!E71 -> 43.310005 | F33: ='3. Workings'!F71 -> 75.277514 | G33: Rs Cr | H33: From Sheet 3 Part F.
B34: RE-02 | C34: Net annual benefit, realistic downside | D34: ='3. Workings'!D93 -> 4.1448734 | E34: ='3. Workings'!E93 -> 16.06366 | F34: ='3. Workings'!F93 -> 27.982447 | G34: Rs Cr | H34: In-house touch cost, fraud at 82%, no synthetic or renewal benefit.
B35: RE-03 | C35: Capital deployed — build only | D35: ='3. Workings'!$D$55 -> 9.8904698 | E35: ='3. Workings'!$D$55 -> 9.8904698 | F35: ='3. Workings'!$D$55 -> 9.8904698 | G35: Rs Cr | H35: From Sheet 3 Part D.
B36: RE-04 | C36: Capital deployed — fully loaded | D36: ='3. Workings'!$D$55*(1+'1. Assumptions and Sources'!$D$119) -> 11.37404 | E36: ='3. Workings'!$D$55*(1+'1. Assumptions and Sources'!$D$119) -> 11.37404 | F36: ='3. Workings'!$D$55*(1+'1. Assumptions and Sources'!$D$119) -> 11.37404 | G36: Rs Cr | H36: Build plus 15% contingency.
B37: RE-05 | C37: Hurdle rate (WACC) | D37: ='1. Assumptions and Sources'!$D$15 -> 0.12 | E37: ='1. Assumptions and Sources'!$D$15 -> 0.12 | F37: ='1. Assumptions and Sources'!$D$15 -> 0.12 | G37: ratio | H37: A-09.
B38: RE-06 | C38: ROIC — headline, on fully loaded capital | D38: =D33/D36 -> 1.1297736 | E38: =E33/E36 -> 3.8077943 | F38: =F33/F36 -> 6.6183618 | G38: ratio | H38: Steady-state net benefit / fully loaded capital.
B39: RE-07 | C39: ROIC — realistic downside | D39: =D34/D36 -> 0.36441522 | E39: =E34/E36 -> 1.4123091 | F39: =F34/F36 -> 2.4602029 | G39: ratio | H39: The downside-basis return, and the one quoted whenever ROIC comes up.
B40: RE-08 | C40: EVA at the 12% hurdle — headline | D40: =D33-D37*D36 -> 11.485205 | E40: =E33-E37*E36 -> 41.94512 | F40: =F33-F37*F36 -> 73.912629 | G40: Rs Cr | H40: Net benefit less the cost of the capital employed.
B41: RE-09 | C41: EVA at the 12% hurdle — downside | D41: =D34-D37*D36 -> 2.7799886 | E41: =E34-E37*E36 -> 14.698775 | F41: =F34-F37*F36 -> 26.617562 | G41: Rs Cr | H41: Still comfortably positive, which is the point.
B42: RE-10 | C42: Investor gate: does downside ROIC clear WACC? | D42: =IF(D39>D37,"PASS","FAIL") -> PASS | E42: =IF(E39>E37,"PASS","FAIL") -> PASS | F42: =IF(F39>F37,"PASS","FAIL") -> PASS | H42: Tested on the downside case, not the headline.
C43: ROIC on this project is high because a small software build sits against a Rs 1,106 Cr claims pool. The deck leads with payback from kickoff and combined-ratio impact, which are the measures that scale to the size of the book.
B45: PART D — CAPITAL ALLOCATION: BUILD vs BUY vs WAIT
B46: Alternative | C46: 3-yr TCO (Rs Cr) | D46: Time to value | E46: Strategic control | F46: Data moat | G46: Status of the estimate
B47: Status quo: OTS plus manual handling | C47: 0 | D47: Immediate | E47: High | F47: None | G47: Zero capex, but carries the cost of waiting quantified below.
B48: Buy point solutions (OCR, or fraud rules, or photo estimate) | C48: Excluded on capability | D48: 6-12 months | E48: Low | F48: None | G48: Point solutions address one signal each. None fuses document, damage, policy, graph and capture evidence into a single routing decision, so none removes the manual reconciliation step that drives the labour line. Excluded on capability before price.
B49: Buy a fused vendor platform | C49: Excluded on capability | D49: Live elsewhere | E49: None | F49: None | G49: A fused platform covers three of the five engines and screens no synthetic damage media, which is the evidence layer every other engine depends on. Excluded on capability before price.
B50: BUILD ClaimPulse — Conservative | C50: ='3. Workings'!$D$55+'4. Forecast'!$H$11 -> 18.094193 | D50: 10-11 months | E50: Full | F50: High | G50: Build cost plus three years of run cost, from this model.
B51: BUILD ClaimPulse — Base | C51: ='3. Workings'!$D$55+'4. Forecast'!$H$24 -> 22.639871 | D51: 10-11 months | E51: Full | F51: High | G51: Build cost plus three years of run cost, from this model.
B52: BUILD ClaimPulse — Aggressive | C52: ='3. Workings'!$D$55+'4. Forecast'!$H$37 -> 27.18555 | D52: 10-11 months | E52: Full | F52: High | G52: Build cost plus three years of run cost, from this model.
B53: Wait for motor pricing to correct | C53: 0 | D53: 3-6 months | E53: N/A | F53: N/A | G53: Management has said the tactical motor pull-back continues until pricing improves. Waiting is a decision with a cost.
B54: BUY the commodity AI layer inside the build — quantified | C54: ='13. GenAI Build vs Buy'!$D$38 -> 0.23956891 | D54: Immediate | E54: Full | F54: High | G54: Sheet 13 prices the GenAI-substitutable share of inference on published vendor rates. Buying that layer is the cheaper route and is adopted inside the build; the moat and baseline layers stay in house.
B55: PART E — THE COST OF WAITING · the alternative is not free
B56: Ref | C56: Metric | D56: Value | E56: Unit | F56: Source / how it is derived
B57: CW-01 | C57: Motor OD loss ratio deterioration, Q1 FY27 vs Q1 FY26 | D57: ='1. Assumptions and Sources'!$D$118 -> 0.032 | E57: pp | F57: I-01. Filed: 74.9% to 76.6%.
B58: CW-02 | C58: Annual rupee cost of that deterioration | D58: ='3. Workings'!$E$78*'1. Assumptions and Sources'!$D$118 -> 52.949416 | E58: Rs Cr | F58: Motor OD net earned premium x the pp movement. Directional.
B59: CW-03 | C59: Monthly opportunity cost of delay, Base plan | D59: ='3. Workings'!$E$72 -> 3.6091671 | E59: Rs Cr | F59: Every month of delay forgoes one month of net benefit.
B60: CW-04 | C60: Cost of a six-month delay, Base plan | D60: ='3. Workings'!$E$72*6 -> 21.655003 | E60: Rs Cr | F60: Six months of forgone net benefit.

Sheet 6. Stakeholder Analysis
B2: Stakeholder Analysis
B3: Who is affected, what changes for them, and how each stakeholder's outcome is measured in this model. Every success metric maps to a line on Sheets 1 to 5.
B5: PART A — STAKEHOLDER MAP
B6: Ref | C6: Stakeholder | D6: What they need today | E6: What ClaimPulse changes | F6: Success metric | G6: Where it sits in this model
B7: SH-01 | C7: Policyholder / claimant | D7: Certainty and speed. Our research found status apps are abandoned after 2 to 3 silent visits. | E7: Green-lane auto-settlement in about 1.5 days instead of 9.8. Proactive status push instead of pull. | F7: Blended claim TAT; app abandonment; claimant renewal rate | G7: Sheet 2 H-03, H-04, H-05. Sheet 3 Part B.
B8: SH-02 | C8: Bajaj General claims operations | D8: Fewer low-value manual touches, and capacity for genuinely complex claims. | E8: 7 manual touches to 1.23 blended. Adjusters move from data entry to exception handling. | F8: Touches per claim; cost to serve; adjuster throughput | G8: Sheet 2 H-06. Sheet 5 UE-01 to UE-04.
B9: SH-03 | C9: Underwriting and the CFO | D9: Loss-ratio and expense-ratio relief without cutting distribution. | E9: Fraud leakage down and claims OPEX down. Both sides of the combined ratio move. | F9: Combined ratio pp; loss ratio pp; expense ratio pp | G9: Sheet 3 Part G. Sheet 2 H-15, H-16.
B10: SH-04 | C10: BFDL / Bajaj Markets | D10: A differentiated distribution proposition and a platform asset the group owns. | E10: Owns the Trust Score engine and the Capture Integrity Gate as a group capability, extensible to health and home in P5. | F10: Platform reuse; partner adoption; NPS at claim | G10: Sheet 5 Part D. Sheet 3 W-22 renewal line.
B11: SH-05 | C11: Bajaj Finserv group leadership | D11: Capital allocated to something that compounds, not a one-off saving. | E11: A proprietary fraud graph and synthetic-media defence that improve with every claim processed. | F11: ROIC vs hurdle; payback; NPV; strategic control | G11: Sheet 5 Parts B, C and D.
B12: SH-06 | C12: Surveyors | D12: Deployment against claims that actually need judgement. | E12: AI triage handles sub-Rs 50,000 claims inside the IRDAI exemption. Surveyors focus above it. | F12: Surveyor cost per claim; share of claims requiring survey | G12: Sheet 1 A-11. Sheet 3 Part B lane mix.
B13: SH-07 | C13: Garages and the repair network | D13: Faster approvals and predictable estimates. | E13: The repair cost engine gives an indicative band at first notification, from settled claims plus live parts feeds. | F13: Estimate-to-approval time; estimate vs final variance | G13: Sheet 1 D-07. Sheet 3 Part D.
B14: SH-08 | C14: IRDAI and the regulator | D14: Explainable, auditable, fair automated decisions. | E14: Human override, full audit trail and per-decision explanation, built into production hardening. RAG grounds decisions in the actual policy wording. | F14: Audit completeness; override rate; complaint volume | G14: Sheet 1 D-10. Sheet 3 Part D.
B15: SH-09 | C15: Honest claimants who cannot use live capture | D15: Not to be penalised for an older phone, indoor parking or GPS off. | E15: Amber lane absorbs them with an innocent explanation rather than a rejection. We cost this friction explicitly. | F15: Share downgraded green to amber; amber false-positive rate | G15: Sheet 1 B-20. Sheet 3 W-23.
B17: PART B — WHAT EACH STAKEHOLDER WILL CHALLENGE, AND THE ANSWER
B18: Ref | C18: Who asks | D18: The challenge | E18: Our answer | F18: Where the evidence is
B19: CQ-01 | C19: Claims operations | D19: Seven manual touches is not our number. | E19: Agreed, it is ours, and it is the largest single driver of the labour line. We have flagged it as Tier 4 and the model recalculates the moment you give us the real figure. | F19: Sheet 1 B-02 and H-04.
B20: CQ-02 | C20: CFO / finance | D20: A three-month payback is not credible. | E20: On steady-state economics it is three months. From project kickoff, including the ten-month build, it is around eighteen. And if both our weakest assumptions break it is still under nine months. | F20: Sheet 2 H-12, H-13, H-19.
B21: CQ-03 | C21: CFO / finance | D21: Rs 250 per touch is outsourced pricing. Our staff are in-house. | E21: Correct, and that is why the downside case reprices every touch at Rs 83. The case still clears. | F21: Sheet 1 F-01. Sheet 3 Part H.
B22: CQ-04 | C22: Underwriting | D22: You cannot subtract a Motor OD saving from our group combined ratio. | E22: We do not. The model shows both bases separately, and states the denominator on every line. | F22: Sheet 3 W-43 and W-46.
B23: CQ-05 | C23: Actuarial | D23: Your fraud leakage number comes from health insurance. | E23: No motor-specific Indian leakage figure is published. The proxy is stated with its basis, and closing it is the second data request. | F23: Sheet 1 B-17 and H-01.
B24: CQ-06 | C24: Data science | D24: Ninety percent fraud precision is above the published range for graph models. | E24: It is a target, not a capability, and we label it that way. The downside case lands it at 82%. | F24: Sheet 1 B-14 and F-02.
B25: CQ-07 | C25: Group finance | D25: Rs 38 Cr a year is under half a percent of group PAT. | E25: On Motor OD alone, yes. Motor is the proof, not the prize. The gate and the graph extend to health and home in P5 without re-architecture. | F25: Sheet 5 Part D. Implementation roadmap P5.
B26: CQ-08 | C26: Legal and compliance | D26: Live-capture-only will exclude some honest claimants. | E26: It will, and we cost it. Eight percent of claims fall to amber, which is a Rs 0.53 Cr annual cost at Base. They are still handled, just not auto-settled. | F26: Sheet 1 B-20. Sheet 3 W-23.
B27: CQ-09 | C27: Strategy | D27: What stops a competitor copying this in eighteen months? | E27: The orchestration is copyable. The fraud graph and the synthetic-media classifier are trained on our own claim media and compound with every claim processed. That is the moat, and it is why the gate is costed as a first-class layer rather than a footnote. | F27: Sheet 1 D-03 to D-05 and D-13.
B28: CQ-10 | C28: Anyone | D28: Why is BFDL funding a benefit that lands in Bajaj General's P&L? | E28: At group level Bajaj Finserv consolidates both. It is a capital allocation question, not a transfer question. We would still recommend an explicit internal service arrangement. | F28: Sheet 1 H-07.
B30: PART C — QUANTIFIED STAKEHOLDER SCORECARD · every row is a formula reading Sheet 3 Part I, and every row moves with the plan
B31: Ref | C31: Stakeholder | D31: Quantified outcome | E31: Conservative | F31: Base | G31: Aggressive | H31: Unit
B32: SC-01 | C32: SH-01 Policyholder / claimant | D32: Claimant-days returned per year | E32: ='3. Workings'!D107 -> 388967.88 | F32: ='3. Workings'!E107 -> 1166903.6 | G32: ='3. Workings'!F107 -> 1944839.4 | H32: days
B33: SC-02 | C33: SH-01 Policyholder / claimant | D33: Claims auto-settled with zero human touch | E33: ='3. Workings'!D108 -> 35659.961 | F33: ='3. Workings'!E108 -> 106979.88 | G33: ='3. Workings'!F108 -> 178299.8 | H33: claims
B34: SC-03 | C34: SH-01 Policyholder / claimant | D34: Blended claim TAT across the whole book | E34: ='3. Workings'!D24 -> 8.382 | F34: ='3. Workings'!E24 -> 5.546 | G34: ='3. Workings'!F24 -> 2.71 | H34: days
B35: SC-04 | C35: SH-01 Policyholder / claimant | D35: Share of the book still on the 9.8-day journey | E35: ='3. Workings'!D110 -> 0.8 | F35: ='3. Workings'!E110 -> 0.4 | G35: ='3. Workings'!F110 -> 0 | H35: ratio
B36: SC-05 | C36: SH-02 Bajaj General claims operations | D36: Manual touches avoided per year | E36: ='3. Workings'!D111 -> 316550.73 | F36: ='3. Workings'!E111 -> 949652.18 | G36: ='3. Workings'!F111 -> 1582753.6 | H36: touches
B37: SC-06 | C37: SH-02 Bajaj General claims operations | D37: FTE capacity released to complex claims | E37: ='3. Workings'!D113 -> 58.620505 | F37: ='3. Workings'!E113 -> 175.86152 | G37: ='3. Workings'!F113 -> 293.10253 | H37: FTE
B38: SC-07 | C38: SH-02 Bajaj General claims operations | D38: Expense-ratio value booked | E38: ='3. Workings'!D101 -> 7.3393685 | F38: ='3. Workings'!E101 -> 23.148801 | G38: ='3. Workings'!F101 -> 40.465826 | H38: Rs Cr
B39: SC-08 | C39: SH-03 Underwriting and the CFO | D39: Loss-ratio value booked | E39: ='3. Workings'!D102 -> 7.8285885 | F39: ='3. Workings'!E102 -> 23.485766 | G39: ='3. Workings'!F102 -> 39.142943 | H39: Rs Cr
B40: SC-09 | C40: SH-03 Underwriting and the CFO | D40: Combined ratio improvement, Motor OD basis | E40: ='3. Workings'!D82 -> 0.76499125 | F40: ='3. Workings'!E82 -> 2.5826285 | G40: ='3. Workings'!F82 -> 4.4913773 | H40: pp
B41: SC-10 | C41: SH-04 BFDL / Bajaj Markets | D41: Distribution income retained per year | E41: ='3. Workings'!D103 -> 0.19201517 | F41: ='3. Workings'!E103 -> 0.57604552 | G41: ='3. Workings'!F103 -> 0.96007586 | H41: Rs Cr
B42: SC-11 | C42: SH-05 Bajaj Finserv group leadership | D42: Group consolidated net annual benefit | E42: ='3. Workings'!D129 -> 12.85009 | F42: ='3. Workings'!E129 -> 43.310005 | G42: ='3. Workings'!F129 -> 75.277514 | H42: Rs Cr
B43: SC-12 | C43: SH-05 Bajaj Finserv group leadership | D43: Share of the annualised underwriting loss offset | E43: ='3. Workings'!D132 -> 0.024711712 | F43: ='3. Workings'!E132 -> 0.083288471 | G43: ='3. Workings'!F132 -> 0.14476445 | H43: ratio
B44: SC-13 | C44: SH-06 Surveyors | D44: Physical survey visits avoided per year | E44: ='3. Workings'!D117 -> 24687.665 | F44: ='3. Workings'!E117 -> 74062.995 | G44: ='3. Workings'!F117 -> 123438.33 | H44: visits
B45: SC-14 | C45: SH-07 Garages and the repair network | D45: Estimate-to-approval days saved per claim | E45: ='3. Workings'!D118 -> 3 | F45: ='3. Workings'!E118 -> 3 | G45: ='3. Workings'!F118 -> 3 | H45: days
B46: SC-15 | C46: SH-08 IRDAI and the regulator | D46: Build spend on governance and explainability | E46: ='3. Workings'!D119 -> 1.0013452 | F46: ='3. Workings'!E119 -> 1.0013452 | G46: ='3. Workings'!F119 -> 1.0013452 | H46: Rs Cr
B47: SC-16 | C47: SH-08 IRDAI and the regulator | D47: Annual run spend on compliance and legal | E47: ='3. Workings'!D121 -> 0.3699996 | F47: ='3. Workings'!E121 -> 0.3699996 | G47: ='3. Workings'!F121 -> 0.3699996 | H47: Rs Cr
B48: SC-17 | C48: SH-09 Honest claimants who cannot use live capture | D48: Claimants downgraded green to amber per year | E48: ='3. Workings'!D123 -> 4388.9182 | F48: ='3. Workings'!E123 -> 13166.755 | G48: ='3. Workings'!F123 -> 21944.591 | H48: claims
B49: SC-18 | C49: SH-09 Honest claimants who cannot use live capture | D49: Cost we carry for them, stated openly | E49: ='3. Workings'!D124 -> 0.23700158 | F49: ='3. Workings'!E124 -> 0.59250396 | G49: ='3. Workings'!F124 -> 0.79000528 | H49: Rs Cr
C51: Rows SC-01 to SC-16 are the case for the investment. Rows SC-17 and SC-18 are the cost the design imposes on people who did nothing wrong, and they are quoted unprompted.

Sheet 7. Trend Analysis
B2: Trend Analysis · the exogenous forces this case is planned against
B3: A TREND is a force we do not control. A SCENARIO is a coherent combination of trends that changes the claim environment, and therefore the numbers. No trend becomes a figure unless it survives the evidence class test below.
B4: SOURCING STANDARD: every external figure below carries a named publisher, a publication date and an evidence class. Figures verified against a live source on 12 August 2026 are marked VERIFIED. Figures carried at a lower tier say so, and none of them is load-bearing on a rupee line.
B5: SCOPE: this sheet consolidates the trend field across four research domains — Customer, Technology, Social and Industrial. Part 2 carries the full 20-trend vector map.
B7: PART 1 — THE TREND FIELD · named, dated and independently verified
B8: Ref | C8: Domain | D8: Trend | E8: Evidence class | F8: Named source | G8: Date | H8: Verified | I8: Feeds
B9: T-01 | C9: Consumer | D9: Digital-first settlement is the default expectation, carried over from UPI and digital KYC rather than from insurance | E9: EXT BENCHMARK | F9: Mordor Intelligence, Online Insurance in India: mobile app 56.1% and P&C 41.8% of the ONLINE insurance market | G9: 2025 base | H9: VERIFIED — shares are within India’s online insurance market | I9: S1
B10: T-02 | C10: Consumer | D10: Only a minority of consumers are comfortable with AI deciding a claim unaided | E10: EXT BENCHMARK | F10: Insurity Consumer Survey: support for AI 20% to 39%; only 22% comfortable with AI filing a claim; 46% would let AI generate a quote | G10: Feb 2026 fieldwork, published 21 Apr 2026 | H10: VERIFIED — US consumers, n over 1,000 | I10: S3
B11: T-03 | C11: Social | D11: Claims experience ranks second only to price as a retention driver | E11: EXT BENCHMARK | F11: Retently 2025 (insurance NPS 23) and CustomerGauge (35); QuestionPro: every 5-point NPS gain is about 1pp of retention | G11: 2025-26 | H11: VERIFIED — note all three reach us through one compilation, so treat as a single secondary source | I11: S1, S3
B12: T-04 | C12: Technology | D12: Generative image tools have made photographic evidence cheap to fabricate; deepfake-assisted fraud attempts reported sharply up | E12: EXT BENCHMARK | F12: NVIDIA customer story on ControlExpert: 95% accuracy detecting manipulated images within three seconds, motor claims, on NVIDIA AI Enterprise | G12: Current | H12: VERIFIED — vendor and customer-story tier, correctly labelled Tier 3 | I12: S2
B13: T-05 | C13: Technology | D13: Graph and network methods lift fraud detection by roughly 10 to 20 pp over rule engines | E13: EXT BENCHMARK | F13: Systematic review of graph and GNN fraud detection | G13: 2025 | H13: TIER 2 — carried at stated tier; bounds a target that is separately stress-tested | I13: S2
B14: T-06 | C14: Technology | D14: Vendor straight-through processing ceilings for simple motor claims sit at 75 to 85 per cent | E14: EXT BENCHMARK | F14: Vendor published STP ceilings; industry all-complexity range 7 to 35% | G14: 2025-26 | H14: TIER 2 — carried at stated tier | I14: S1
B15: T-07 | C15: Industry | D15: Repair networks consolidating toward API-connected claims-to-repair chains; telematics-linked flows report up to 50 per cent cycle-time reduction | E15: EXT BENCHMARK | F15: Telematics cycle-time research, global, not India or Motor OD specific. Autorox (India) separately claims up to 25% reduction in overpaid repair approvals | G15: 2025-26 | H15: PARTIAL — Autorox 25% VERIFIED on the vendor’s own site; the 50% telematics figure is carried at TIER 2 | I15: S4
B16: T-08 | C16: Industry | D16: General insurance is in a soft pricing cycle; underwriting results stressed across the market | E16: FACT | F16: Bajaj Finserv Q1 FY27 investor presentation and earnings call, 31 Jul 2026. Bajaj General combined ratio 104.7%, GWP Rs 5,789 Cr up 11.3%, solvency 254% | G16: Q1 FY27 | H16: VERIFIED against the BSE filing | I16: All
B17: T-09 | C17: Industry | D17: Motor deliberately slowed by the client because pricing is inadequate; return-on-risk-capital gates re-entry | E17: FACT | F17: Bajaj Finserv Q1 FY27 earnings call, management commentary | G17: Jul 2026 | H17: VERIFIED — combined ratio trajectory 103.6% to 104.7% confirmed | I17: All
B18: T-10 | C18: Industry | D18: Supreme Court motor third-party judgment forced peer reserve strengthening of 2.8 pp of combined ratio in one quarter | E18: FACT | F18: ICICI Lombard Q1 FY27 results. Provision Rs 165 Cr; combined ratio 107.2% against 102.9%; adjusted 102.3%. Judgment recognises loss of domestic care for homemakers at a notional Rs 30,000 per month | G18: Q1 FY27 | H18: VERIFIED — 2.8pp exact. Industry motor TP loss ratio expected to rise 12 to 15% | I18: Context
B19: T-11 | C19: Regulatory | D19: IRDAI moved insurers to proactive, board-governed fraud monitoring with a fraud monitoring committee and unit | E19: FACT | F19: IRDAI (Insurance Fraud Monitoring Framework) Guidelines, 2025. Ref IRDAI/IID/GDL/MISC/112/10/2025 dated 09.10.2025. Repeals the 2013 circular and extends to all distribution channels | G19: Eff. 1 Apr 2026 | H19: VERIFIED — reference number, date and effective date all exact | I19: S2, S5
B20: T-12 | C20: Regulatory | D20: Motor losses below Rs 50,000 need not be surveyed by a registered surveyor; app-based and AI assessment contemplated | E20: FACT | F20: IRDAI Master Circular on Protection of Policyholders' Interests, 11 Jun 2024. IRDAI: insurers are leveraging app based methodology with AI driven assessment | G20: 2024, current | H20: VERIFIED — threshold and the AI-assessment wording both confirmed | I20: S1
B21: T-13 | C21: Regulatory | D21: IRDAI constituted an AI working group in June 2026. Norms not yet published | E21: FACT | F21: IRDAI AI Working Group announced 19 Jun 2026. Seven members, chaired by Sandeep Shukla, Director IRDAI Hyderabad. Three-month mandate covering governance frameworks, safeguards and an AI audit framework | G21: Jun 2026 | H21: VERIFIED — and now nameable. Follows IRDAI's revised information and cyber security guidelines of Apr 2026 | I21: S5
B22: T-14 | C22: Regulatory | D22: No published incidence of synthetic claim media in Indian motor, because the vector is unmeasured | E22: NOT SOURCEABLE | F22: None exists. Independently rediscovered as a total gap by all four research engines (Customer E31, Technology TE05 and TE08, Social Scenario 2, Industrial IE03) | G22: n/a | H22: CONFIRMED ABSENT after independent search | I22: S2
B23: T-15 | C23: Regulatory | D23: National data-protection obligations land inside the investment horizon | E23: FACT | F23: DPDP Rules 2025, notified 13 Nov 2025, full compliance 13 May 2027. Penalties to Rs 250 Cr apply from day one; no grace period | G23: Current | H23: VERIFIED — both dates exact | I23: S5
B24: T-16 | C24: Consumer | D24: Claims are the dominant source of general-insurance grievance, and the pool is growing | E24: FACT | F24: IRDAI Annual Report 2024-25: 257,790 grievances on Bima Bharosa, up 20% YoY, 69% claims-related. Rajya Sabha reply 16 Dec 2025: motor fell from 26.18% of complaints in FY24 to 24.8% in FY25 | G24: FY2024-25 | H24: VERIFIED — both sources confirmed | I24: S1, S3
B25: T-17 | C25: Industry | D25: Industry fraud and waste leakage runs at 8 to 10 per cent of payouts, concentrated in the mid-ticket band | E25: EXT BENCHMARK | F25: BCG and Medi Assist, Nov 2025: Rs 8,000 to 10,000 Cr annual leakage, concentrated between Rs 50,000 and Rs 2.5 lakh claim value | G25: Nov 2025 | H25: VERIFIED — BCG and Medi Assist, November 2025. Health-skewed and applied to motor as a proxy; the mid-ticket band corroborates the Rs 45,000 average claim | I25: S2
... B30: T-21 | C30: Technology | D30: Region-pinned inference now carries an explicit price premium, making data residency a costed choice rather than an architectural preference | E30: FACT | F30: OpenAI and Anthropic both publish a 1.1x multiplier for region-pinned inference. Sheet 1 M-24 | G30: Aug 2026 | H30: VERIFIED. Converts the DPDP question in T-15 into a line item rather than a principle | I30: S5
B31: PART 2 — FOUR-ENGINE TREND VECTOR MAP · 20 trends scored on six dimensions
B32: Carried over in full from the Customer engine, which is the architectural parent of the other three. Scores are 1 to 5. Scoring rule, applied throughout: a strongly-evidenced weak trend is worth more than a weakly-evidenced strong one. Any trend whose evidence reads NO SOURCE scores 1 on evidence confidence and must NOT be presented as a driver of quantified impact.
B33: Ref | C33: Field | D33: Trend | E33: Magnitude | F33: Velocity | G33: Persistence | H33: Evid. conf. | I33: Motor rel. | J33: Exposure | K33: Evidence anchor
B34: C1 | C34: Customer | D34: Digital servicing penetration | E34: 4 | F34: 4 | G34: 4 | H34: 4 | I34: 3 | J34: 4 | K34: T-01. Purchase-side only; claim-side conversion has no source
B35: C2 | C35: Customer | D35: Claim-speed expectation | E35: 4 | F35: 3 | G35: 4 | H35: 3 | I35: 5 | J35: 5 | K35: T-16 complaint proxy. Direct TAT expectation has no source
B36: C3 | C36: Customer | D36: AI assistance acceptance | E36: 3 | F36: 4 | G36: 3 | H36: 3 | I36: 3 | J36: 3 | K36: T-02. US data, direction only for India
B37: C4 | C37: Customer | D37: AI autonomy acceptance | E37: 2 | F37: 2 | G37: 4 | H37: 3 | I37: 4 | J37: 4 | K37: T-02 plus T-13 regulator posture. India consumer data has no source
B38: C5 | C38: Customer | D38: Explainability expectation | E38: 3 | F38: 2 | G38: 5 | H38: 5 | I38: 5 | J38: 4 | K38: IRDAI Policyholders' Interests Regs 2024. A legal mandate, not a preference
B39: C6 | C39: Customer | D39: Data-sharing willingness | E39: 2 | F39: 2 | G39: 4 | H39: 4 | I39: 3 | J39: 2 | K39: T-15 DPDP constraint. Willingness itself unmeasured
B40: C7 | C40: Customer | D40: Digital evidence behaviour | E40: 3 | F40: 3 | G40: 3 | H40: 3 | I40: 5 | J40: 5 | K40: Peer video-survey adoption. Gallery vs live-capture split is pilot data only
B41: C8 | C41: Customer | D41: Human escalation preference | E41: 3 | F41: 2 | G41: 3 | H41: 2 | I41: 4 | J41: 4 | K41: Evidence confidence set at 2: the available trust data measures claims professionals rather than customers
B42: C9 | C42: Customer | D42: Omnichannel behaviour | E42: 2 | F42: 2 | G42: 2 | H42: 2 | I42: 2 | J42: 2 | K42: Channels evidenced; switching behaviour unmeasured
B43: T1 | C43: Technology | D43: AI capability | E43: 4 | F43: 4 | G43: 3 | H43: 1 | I43: 2 | J43: 2 | K43: No benchmark held. Directional consensus only
B44: T2 | C44: Technology | D44: Inference cost deflation | E44: 3 | F44: 3 | G44: 3 | H44: 2 | I44: 2 | J44: 3 | K44: Direction only; no rate suitable for multi-year extrapolation
B45: T3 | C45: Technology | D45: Multimodal capability | E45: 3 | F45: 3 | G45: 3 | H45: 1 | I45: 3 | J45: 4 | K45: No benchmark held
... B62: I6 | C62: Industry | D62: Underwriting selectivity | E62: 3 | F62: 2 | G62: 4 | H62: 5 | I62: 3 | J62: 2 | K62: T-08, T-09. FACT
B64: PART 3 — EVIDENCE GAPS CARRIED OPENLY · figures no source supports, and how each is handled
B65: Ref | C65: Figure sought | D65: How it is handled in the model
B66: U-01 | C66: Motor-specific fraud leakage for India | D66: The 8 to 10 per cent benchmark in circulation is health, from BCG and Medi Assist November 2025. Carried as a stated proxy at H-01 and stress-tested to zero on Sheet 8.
B67: U-02 | C67: Published incidence of synthetic claim media | D67: No published incidence. Modelled forward-looking at 1.0 per cent with a 0.5 to 2.0 per cent sensitivity.
B68: U-03 | C68: Repair-cost overpayment base for India | D68: Not published. Autorox’s 25 per cent reduction rate is sourced; the rupee base it would multiply is not, so no repair-overpayment benefit is claimed anywhere in the model.
B69: U-04 | C69: Ongoing AI compliance and audit operating cost | D69: No published figure. Priced as a build overlay in scenario S5 at plus 15 and plus 20 per cent of build.
B70: U-05 | C70: Bajaj-specific renewal elasticity | D70: Would require a renewal cohort study. Excluded from the NPV entirely
B71: U-06 | C71: Human exception-handling capacity ceiling | D71: Bajaj claims-operations data only. Flagged by two of the four engines as the breakpoint most likely to bind first, and modelled by none of them. The single most actionable data request
B72: U-07 | C72: India consumer acceptance of AI claim DECISIONS | D72: No India-specific survey exists. All acceptance data is US-led. This is why T-02 is scoped, not extrapolated
B73: U-08 | C73: P90 and P95 TAT distribution | D73: The model produces a mean only. Distribution needs pilot or Bajaj data
B75: PART 4 — WHAT THE TREND WORK SETTLED
B76: 1. | C76: The evidence-integrity layer moved from a slide claim to a costed build line, because T-04 makes every downstream model unsafe without it.
B77: 2. | C77: The fraud target was capped and stress-tested, because T-05 puts our +28 pp above the published range.
B78: 3. | C78: Repair-network gains were kept OUT of the investment case, because T-07 delivers customer benefit that does not accrue to us.
B79: 4. | C79: Rollout was made the primary lever rather than a fixed plan, because T-09 means deployment must track the pricing decision, not lead it.
B80: 5. | C80: Regulatory tightening is priced as a build overlay rather than ignored, because T-13 is a known unknown.
B81: 6. | C81: Fraud governance moved from optional to mandatory, because T-11 makes a board-level fraud monitoring committee a compliance obligation from 1 April 2026, not a differentiator.
B82: 7. | C82: The mid-ticket concentration in T-17 was adopted as corroboration of the Rs 45,000 average claim size, because it places industry leakage in exactly the band the green lane is scoped to.
B84: PART 5 — EVIDENCE CLASS SUMMARY
B85: Every external figure carried by this case is classified. Eighteen are verified clean against a live source and quotable without qualification. Nine are carried at a stated lower tier; none of those is load-bearing on a rupee figure except the graph-AI range, which only bounds a target the model already stress-tests to zero.
B86: Ref | C86: Figure | D86: Evidence class | E86: How it is used
B87: V-01 | C87: Claims cycle time, 32.4 days | D87: TIER 2, scope-bounded. J.D. Power 2025 US Property Claims Satisfaction Study, US homeowners’ property claims. J.D. Power also reports over 44 days from first notice of loss to final payment. | E87: Not used as an India motor benchmark. B-09 uses the India-typical 7 to 10 day band instead.
B88: V-02 | C88: Trust uplift from human oversight | D88: TIER 2, scope-bounded. Wisedocs 2025, 65 claims professionals in US workers’ compensation: trust in AI alone 16 per cent, rising to 60 per cent with human experts. | E88: Used as evidence on claims-handler acceptance, not customer acceptance. Trend C8 scored accordingly.
B89: V-03 | C89: Fraud and waste at 8 to 10 per cent of payouts | D89: TIER 2 PROXY. BCG and Medi Assist, November 2025. Health, not motor. | E89: Carried as a stated proxy at H-01. The mid-ticket concentration corroborates the Rs 45,000 average claim.
B90: V-04 | C90: Bajaj digital servicing 90.9%, AI bots 64.5%, Motor NPS 78 | D90: TIER 1 FILED. FY26 figures, Bajaj General investor deck, 30 April 2026. | E90: Used as FY26 context. The 104.7 per cent combined ratio is cited separately from Q1 FY27.
B91: V-05 | C91: Mordor digital channel shares 56.1% and 41.8% | D91: EXT BENCHMARK. Shares within India’s online insurance market. | E91: Used with that scope stated. Trend C1 is capped for the missing claim-side conversion.
B92: V-06 | C92: Insurity AI acceptance | D92: EXT BENCHMARK. US only, n over 1,000, February 2026 fieldwork. | E92: Used as directional for India, which is why U-07 records the India gap explicitly.
B93: V-07 | C93: EU AI Act uplift of 15 to 20 per cent of development budget | D93: TIER 3. Refers to AI projects generally rather than insurance claims platforms. Better-grounded absolute figures exist at roughly EUR 200k to 500k initial and EUR 80k to 150k annually. | E93: Used only to bound scenario S5, which tests plus 15 and plus 20 per cent of build.
B94: V-08 | C94: Verified clean and quotable without qualification | D94: TIER 1, quotable without qualification | E94: Quote freely. All carry named publisher and date in Part 1
B95: V-09 | C95: Carried at a stated lower tier | D95: Motor OD market-share series; surveyor fee schedule; dark-pattern prevalence; India motor claims NPS; peer video-survey counts; detractor conversion; the 50 per cent telematics figure; the graph-AI uplift range; AI-fake pass-through rates. | E95: None is load-bearing on a rupee figure except the graph-AI range, which only bounds a target the model already stress-tests to zero.
B97: FX check: the model converts USD build benchmarks at Rs 95.3 (assumption A-08). Spot USD/INR traded between 94.89 and 95.45 in the week to 11 August 2026, so 95.3 is accurate and marginally conservative.

Sheet 8. Scenario Simulation
B2: Scenario Simulation · five researched scenarios, three intensity levels each, run on the live model engine
B3: Every scenario in Part B moves ONE lever and holds everything else at Base, so the effect is attributable to that lever. Level 2 of S1 IS the Base case by construction, which is how the engine is checked. Sheet 3 Part L runs the correlated case, where several levers miss at once.
B5: PART A — ENGINE CHECK · this sheet must tie to the model before anything below it means anything
B6: Part B recomputes from the live engine, so it cannot go stale. These anchors confirm the link is intact before anything below is quoted.
B7: Ref | C7: Anchor | D7: Part B basis | E7: Live model | F7: Check
B8: EC-01 | C8: Blended manual touches per claim | D8: ='3. Workings'!$E$19 -> 1.23 | E8: ='3. Workings'!E19 -> 1.23 | F8: =IF(ABS(D8-E8)<=0.02,"TIE","CHECK") -> TIE
B9: EC-02 | C9: Blended TAT on platform, days | D9: ='3. Workings'!$E$21 -> 2.55 | E9: ='3. Workings'!E21 -> 2.55 | F9: =IF(ABS(D9-E9)<=0.02,"TIE","CHECK") -> TIE
B10: EC-03 | C10: Gross annual benefit, Rs Cr | D10: ='3. Workings'!$E$36 -> 47.210612 | E10: ='3. Workings'!E36 -> 47.210612 | F10: =IF(ABS(D10-E10)<=0.02,"TIE","CHECK") -> TIE
B11: EC-04 | C11: Net annual benefit, Rs Cr | D11: ='3. Workings'!$E$71 -> 43.310005 | E11: ='3. Workings'!E71 -> 43.310005 | F11: =IF(ABS(D11-E11)<=0.02,"TIE","CHECK") -> TIE
B12: EC-05 | C12: Build cost, Rs Cr | D12: ='3. Workings'!$E$73 -> 9.8904698 | E12: ='3. Workings'!E73 -> 9.8904698 | F12: =IF(ABS(D12-E12)<=0.02,"TIE","CHECK") -> TIE
B13: EC-06 | C13: Payback, steady state, months | D13: ='3. Workings'!$E$74 -> 2.7403746 | E13: ='3. Workings'!E74 -> 2.7403746 | F13: =IF(ABS(D13-E13)<=0.02,"TIE","CHECK") -> TIE
B14: EC-07 | C14: OVERALL | D14: =IF(COUNTIF(F8:F13,"TIE")=6,"ALL SIX ANCHORS TIE - Part B is live against the current engine","LINK BROKEN - do not quote Part B") -> ALL SIX ANCHORS TIE - Part B is live against the current engine
B16: PART B — SCENARIO RESULTS · Base plan, computed live from the engine
B17: Each scenario moves one lever and holds everything else at Base. S1 Level 2 is the Base case by construction. S4 changes claimant-facing TAT through the garage chain and carries no P&L effect, which is why it is shown and not claimed. Sheet 3 Part L runs the correlated case.
B18: Scenario | C18: Intensity level | D18: Lever value | E18: Touches | F18: TAT, days | G18: Net annual, Rs Cr | H18: Build, Rs Cr | I18: Payback, months | J18: Comb. ratio, pp | K18: Delta vs Base, Rs Cr
B19: S1 Digital-first settlement expectation | C19: L1 Emerging | D19: =0.55*100&"% green" -> 55% green | E19: =(0.55*'1. Assumptions and Sources'!$D$28+((1-0.55)*'1. Assumptions and Sources'!$D$26/('1. Assumptions and Sources'!$D$26+'1. Assumptions and Sources'!$D$27))*'1. Assumptions and Sources'!$D$29+((1-0.55)*'1. Assumptions and Sources'!$D$27/('1. Assumptions and Sources'!$D$26+'1. Assumptions and Sources'!$D$27))*'1. Assumptions and Sources'!$D$30) -> 1.5242857 | F19: =0.55*'1. Assumptions and Sources'!$D$32+((1-0.55)*'1. Assumptions and Sources'!$D$26/('1. Assumptions and Sources'!$D$26+'1. Assumptions and Sources'!$D$27))*'1. Assumptions and Sources'!$D$33+((1-0.55)*'1. Assumptions and Sources'!$D$27/('1. Assumptions and Sources'!$D$26+'1. Assumptions and Sources'!$D$27))*'1. Assumptions and Sources'!$D$34 -> 2.85 | G19: =(('3. Workings'!$E$13*('1. Assumptions and Sources'!$D$24*'1. Assumptions and Sources'!$D$51-(0.55*'1. Assumptions and Sources'!$D$28+((1-0.55)*'1. Assumptions and Sources'!$D$26/('1. Assumptions and Sources'!$D$26+'1. Assumptions and Sources'!$D$27))*'1. Assumptions and Sources'!$D$29+((1-0.55)*'1. Assumptions and Sources'!$D$27/('1. Assumptions and Sources'!$D$26+'1. Assumptions and Sources'!$D$27))*'1. Assumptions and Sources'!$D$30)*'1. Assumptions and Sources'!$E$55)/10000000)+('3. Workings'!$E$31+'3. Workings'!$E$32+'3. Workings'!$E$33)+'3. Workings'!$E$34+'3. Workings'!$E$35)-'3. Workings'!$E$65 -> 42.099134 | H19: ='3. Workings'!$D$55 -> 9.8904698 | I19: 17.064925 | J19: =(('3. Workings'!$E$31+'3. Workings'!$E$32+'3. Workings'!$E$33)+('3. Workings'!$E$13*('1. Assumptions and Sources'!$D$24*'1. Assumptions and Sources'!$D$51-(0.55*'1. Assumptions and Sources'!$D$28+((1-0.55)*'1. Assumptions and Sources'!$D$26/('1. Assumptions and Sources'!$D$26+'1. Assumptions and Sources'!$D$27))*'1. Assumptions and Sources'!$D$29+((1-0.55)*'1. Assumptions and Sources'!$D$27/('1. Assumptions and Sources'!$D$26+'1. Assumptions and Sources'!$D$27))*'1. Assumptions and Sources'!$D$30)*'1. Assumptions and Sources'!$E$55)/10000000)+'3. Workings'!$E$35-'3. Workings'!$E$65)/'3. Workings'!$E$79 -> 2.5094495 | K19: =G19-$G$20 -> -1.2108712
C20: L2 Established (= Base case) | D20: =TEXT('1. Assumptions and Sources'!$D$25,"0%")&" green" -> 65% green | E20: =(0.65*'1. Assumptions and Sources'!$D$28+((1-0.65)*'1. Assumptions and Sources'!$D$26/('1. Assumptions and Sources'!$D$26+'1. Assumptions and Sources'!$D$27))*'1. Assumptions and Sources'!$D$29+((1-0.65)*'1. Assumptions and Sources'!$D$27/('1. Assumptions and Sources'!$D$26+'1. Assumptions and Sources'!$D$27))*'1. Assumptions and Sources'!$D$30) -> 1.23 | F20: =0.65*'1. Assumptions and Sources'!$D$32+((1-0.65)*'1. Assumptions and Sources'!$D$26/('1. Assumptions and Sources'!$D$26+'1. Assumptions and Sources'!$D$27))*'1. Assumptions and Sources'!$D$33+((1-0.65)*'1. Assumptions and Sources'!$D$27/('1. Assumptions and Sources'!$D$26+'1. Assumptions and Sources'!$D$27))*'1. Assumptions and Sources'!$D$34 -> 2.55 | G20: =(('3. Workings'!$E$13*('1. Assumptions and Sources'!$D$24*'1. Assumptions and Sources'!$D$51-(0.65*'1. Assumptions and Sources'!$D$28+((1-0.65)*'1. Assumptions and Sources'!$D$26/('1. Assumptions and Sources'!$D$26+'1. Assumptions and Sources'!$D$27))*'1. Assumptions and Sources'!$D$29+((1-0.65)*'1. Assumptions and Sources'!$D$27/('1. Assumptions and Sources'!$D$26+'1. Assumptions and Sources'!$D$27))*'1. Assumptions and Sources'!$D$30)*'1. Assumptions and Sources'!$E$55)/10000000)+('3. Workings'!$E$31+'3. Workings'!$E$32+'3. Workings'!$E$33)+'3. Workings'!$E$34+'3. Workings'!$E$35)-'3. Workings'!$E$65 -> 43.310005 | H20: ='3. Workings'!$D$55 -> 9.8904698 | I20: 16.842971 | J20: =(('3. Workings'!$E$31+'3. Workings'!$E$32+'3. Workings'!$E$33)+('3. Workings'!$E$13*('1. Assumptions and Sources'!$D$24*'1. Assumptions and Sources'!$D$51-(0.65*'1. Assumptions and Sources'!$D$28+((1-0.65)*'1. Assumptions and Sources'!$D$26/('1. Assumptions and Sources'!$D$26+'1. Assumptions and Sources'!$D$27))*'1. Assumptions and Sources'!$D$29+((1-0.65)*'1. Assumptions and Sources'!$D$27/('1. Assumptions and Sources'!$D$26+'1. Assumptions and Sources'!$D$27))*'1. Assumptions and Sources'!$D$30)*'1. Assumptions and Sources'!$E$55)/10000000)+'3. Workings'!$E$35-'3. Workings'!$E$65)/'3. Workings'!$E$79 -> 2.5826285 | K20: =G20-$G$20 -> 0
C21: L3 Accelerated | D21: =0.78*100&"% green" -> 78% green | E21: =(0.78*'1. Assumptions and Sources'!$D$28+((1-0.78)*'1. Assumptions and Sources'!$D$26/('1. Assumptions and Sources'!$D$26+'1. Assumptions and Sources'!$D$27))*'1. Assumptions and Sources'!$D$29+((1-0.78)*'1. Assumptions and Sources'!$D$27/('1. Assumptions and Sources'!$D$26+'1. Assumptions and Sources'!$D$27))*'1. Assumptions and Sources'!$D$30) -> 0.84742857 | F21: =0.78*'1. Assumptions and Sources'!$D$32+((1-0.78)*'1. Assumptions and Sources'!$D$26/('1. Assumptions and Sources'!$D$26+'1. Assumptions and Sources'!$D$27))*'1. Assumptions and Sources'!$D$33+((1-0.78)*'1. Assumptions and Sources'!$D$27/('1. Assumptions and Sources'!$D$26+'1. Assumptions and Sources'!$D$27))*'1. Assumptions and Sources'!$D$34 -> 2.16 | G21: =(('3. Workings'!$E$13*('1. Assumptions and Sources'!$D$24*'1. Assumptions and Sources'!$D$51-(0.78*'1. Assumptions and Sources'!$D$28+((1-0.78)*'1. Assumptions and Sources'!$D$26/('1. Assumptions and Sources'!$D$26+'1. Assumptions and Sources'!$D$27))*'1. Assumptions and Sources'!$D$29+((1-0.78)*'1. Assumptions and Sources'!$D$27/('1. Assumptions and Sources'!$D$26+'1. Assumptions and Sources'!$D$27))*'1. Assumptions and Sources'!$D$30)*'1. Assumptions and Sources'!$E$55)/10000000)+('3. Workings'!$E$31+'3. Workings'!$E$32+'3. Workings'!$E$33)+'3. Workings'!$E$34+'3. Workings'!$E$35)-'3. Workings'!$E$65 -> 44.884138 | H21: ='3. Workings'!$D$55 -> 9.8904698 | I21: 16.574461 | J21: =(('3. Workings'!$E$31+'3. Workings'!$E$32+'3. Workings'!$E$33)+('3. Workings'!$E$13*('1. Assumptions and Sources'!$D$24*'1. Assumptions and Sources'!$D$51-(0.78*'1. Assumptions and Sources'!$D$28+((1-0.78)*'1. Assumptions and Sources'!$D$26/('1. Assumptions and Sources'!$D$26+'1. Assumptions and Sources'!$D$27))*'1. Assumptions and Sources'!$D$29+((1-0.78)*'1. Assumptions and Sources'!$D$27/('1. Assumptions and Sources'!$D$26+'1. Assumptions and Sources'!$D$27))*'1. Assumptions and Sources'!$D$30)*'1. Assumptions and Sources'!$E$55)/10000000)+'3. Workings'!$E$35-'3. Workings'!$E$65)/'3. Workings'!$E$79 -> 2.6777613 | K21: =G21-$G$20 -> 1.5741325
B22: S2 Synthetic evidence | C22: L1 Evidence gate holds | D22: =0.9*100&"% detection" -> 90% detection | E22: ='3. Workings'!$E$19 -> 1.23 | F22: ='3. Workings'!$E$21 -> 2.55 | G22: =('3. Workings'!$E$30+('3. Workings'!$E$31+'3. Workings'!$E$32+'3. Workings'!$E$33)*((1-(1-0.9)/(1-'1. Assumptions and Sources'!$D$35))/(1-(1-'1. Assumptions and Sources'!$D$36)/(1-'1. Assumptions and Sources'!$D$35)))+'3. Workings'!$E$34+'3. Workings'!$E$35)-'3. Workings'!$E$65 -> 43.310005 | H22: ='3. Workings'!$D$55 -> 9.8904698 | I22: ='1. Assumptions and Sources'!$D$49+IF((('3. Workings'!$E$30+('3. Workings'!$E$31+'3. Workings'!$E$32+'3. Workings'!$E$33)*((1-(1-0.9)/(1-'1. Assumptions and Sources'!$D$35))/(1-(1-'1. Assumptions and Sources'!$D$36)/(1-'1. Assumptions and Sources'!$D$35)))+'3. Workings'!$E$34+'3. Workings'!$E$35)*'1. Assumptions and Sources'!$D$46-'3. Workings'!$E$65)>='3. Workings'!$D$55,'3. Workings'!$D$55/((('3. Workings'!$E$30+('3. Workings'!$E$31+'3. Workings'!$E$32+'3. Workings'!$E$33)*((1-(1-0.9)/(1-'1. Assumptions and Sources'!$D$35))/(1-(1-'1. Assumptions and Sources'!$D$36)/(1-'1. Assumptions and Sources'!$D$35)))+'3. Workings'!$E$34+'3. Workings'!$E$35)*'1. Assumptions and Sources'!$D$46-'3. Workings'!$E$65)/12),IF((('3. Workings'!$E$30+('3. Workings'!$E$31+'3. Workings'!$E$32+'3. Workings'!$E$33)*((1-(1-0.9)/(1-'1. Assumptions and Sources'!$D$35))/(1-(1-'1. Assumptions and Sources'!$D$36)/(1-'1. Assumptions and Sources'!$D$35)))+'3. Workings'!$E$34+'3. Workings'!$E$35)*'1. Assumptions and Sources'!$D$46-'3. Workings'!$E$65)+((('3. Workings'!$E$30+('3. Workings'!$E$31+'3. Workings'!$E$32+'3. Workings'!$E$33)*((1-(1-0.9)/(1-'1. Assumptions and Sources'!$D$35))/(1-(1-'1. Assumptions and Sources'!$D$36)/(1-'1. Assumptions and Sources'!$D$35)))+'3. Workings'!$E$34+'3. Workings'!$E$35)*'1. Assumptions and Sources'!$D$47-'3. Workings'!$E$65)*(1+'1. Assumptions and Sources'!$D$12))>='3. Workings'!$D$55,12+('3. Workings'!$D$55-(('3. Workings'!$E$30+('3. Workings'!$E$31+'3. Workings'!$E$32+'3. Workings'!$E$33)*((1-(1-0.9)/(1-'1. Assumptions and Sources'!$D$35))/(1-(1-'1. Assumptions and Sources'!$D$36)/(1-'1. Assumptions and Sources'!$D$35)))+'3. Workings'!$E$34+'3. Workings'!$E$35)*'1. Assumptions and Sources'!$D$46-'3. Workings'!$E$65))/(((('3. Workings'!$E$30+('3. Workings'!$E$31+'3. Workings'!$E$32+'3. Workings'!$E$33)*((1-(1-0.9)/(1-'1. Assumptions and Sources'!$D$35))/(1-(1-'1. Assumptions and Sources'!$D$36)/(1-'1. Assumptions and Sources'!$D$35)))+'3. Workings'!$E$34+'3. Workings'!$E$35)*'1. Assumptions and Sources'!$D$47-'3. Workings'!$E$65)*(1+'1. Assumptions and Sources'!$D$12))/12),IF((('3. Workings'!$E$30+('3. Workings'!$E$31+'3. Workings'!$E$32+'3. Workings'!$E$33)*((1-(1-0.9)/(1-'1. Assumptions and Sources'!$D$35))/(1-(1-'1. Assumptions and Sources'!$D$36)/(1-'1. Assumptions and Sources'!$D$35)))+'3. Workings'!$E$34+'3. Workings'!$E$35)*'1. Assumptions and Sources'!$D$46-'3. Workings'!$E$65)+((('3. Workings'!$E$30+('3. Workings'!$E$31+'3. Workings'!$E$32+'3. Workings'!$E$33)*((1-(1-0.9)/(1-'1. Assumptions and Sources'!$D$35))/(1-(1-'1. Assumptions and Sources'!$D$36)/(1-'1. Assumptions and Sources'!$D$35)))+'3. Workings'!$E$34+'3. Workings'!$E$35)*'1. Assumptions and Sources'!$D$47-'3. Workings'!$E$65)*(1+'1. Assumptions and Sources'!$D$12))+((('3. Workings'!$E$30+('3. Workings'!$E$31+'3. Workings'!$E$32+'3. Workings'!$E$33)*((1-(1-0.9)/(1-'1. Assumptions and Sources'!$D$35))/(1-(1-'1. Assumptions and Sources'!$D$36)/(1-'1. Assumptions and Sources'!$D$35)))+'3. Workings'!$E$34+'3. Workings'!$E$35)*'1. Assumptions and Sources'!$D$48-'3. Workings'!$E$65)*(1+'1. Assumptions and Sources'!$D$12)^2)>='3. Workings'!$D$55,24+('3. Workings'!$D$55-(('3. Workings'!$E$30+('3. Workings'!$E$31+'3. Workings'!$E$32+'3. Workings'!$E$33)*((1-(1-0.9)/(1-'1. Assumptions and Sources'!$D$35))/(1-(1-'1. Assumptions and Sources'!$D$36)/(1-'1. Assumptions and Sources'!$D$35)))+'3. Workings'!$E$34+'3. Workings'!$E$35)*'1. Assumptions and Sources'!$D$46-'3. Workings'!$E$65)-((('3. Workings'!$E$30+('3. Workings'!$E$31+'3. Workings'!$E$32+'3. Workings'!$E$33)*((1-(1-0.9)/(1-'1. Assumptions and Sources'!$D$35))/(1-(1-'1. Assumptions and Sources'!$D$36)/(1-'1. Assumptions and Sources'!$D$35)))+'3. Workings'!$E$34+'3. Workings'!$E$35)*'1. Assumptions and Sources'!$D$47-'3. Workings'!$E$65)*(1+'1. Assumptions and Sources'!$D$12)))/(((('3. Workings'!$E$30+('3. Workings'!$E$31+'3. Workings'!$E$32+'3. Workings'!$E$33)*((1-(1-0.9)/(1-'1. Assumptions and Sources'!$D$35))/(1-(1-'1. Assumptions and Sources'!$D$36)/(1-'1. Assumptions and Sources'!$D$35)))+'3. Workings'!$E$34+'3. Workings'!$E$35)*'1. Assumptions and Sources'!$D$48-'3. Workings'!$E$65)*(1+'1. Assumptions and Sources'!$D$12)^2)/12),"beyond 3 years"))) -> 16.842971 | J22: =(('3. Workings'!$E$31+'3. Workings'!$E$32+'3. Workings'!$E$33)*((1-(1-0.9)/(1-'1. Assumptions and Sources'!$D$35))/(1-(1-'1. Assumptions and Sources'!$D$36)/(1-'1. Assumptions and Sources'!$D$35)))+'3. Workings'!$E$30+'3. Workings'!$E$35-'3. Workings'!$E$65)/'3. Workings'!$E$79 -> 2.5826285 | K22: =G22-$G$20 -> 0
C23: L2 Partial erosion | D23: =0.77*100&"% detection" -> 77% detection | E23: ='3. Workings'!$E$19 -> 1.23 | F23: ='3. Workings'!$E$21 -> 2.55 | G23: =('3. Workings'!$E$30+('3. Workings'!$E$31+'3. Workings'!$E$32+'3. Workings'!$E$33)*((1-(1-0.77)/(1-'1. Assumptions and Sources'!$D$35))/(1-(1-'1. Assumptions and Sources'!$D$36)/(1-'1. Assumptions and Sources'!$D$35)))+'3. Workings'!$E$34+'3. Workings'!$E$35)-'3. Workings'!$E$65 -> 32.4059 | H23: ='3. Workings'!$D$55 -> 9.8904698 | I23: ='1. Assumptions and Sources'!$D$49+IF((('3. Workings'!$E$30+('3. Workings'!$E$31+'3. Workings'!$E$32+'3. Workings'!$E$33)*((1-(1-0.77)/(1-'1. Assumptions and Sources'!$D$35))/(1-(1-'1. Assumptions and Sources'!$D$36)/(1-'1. Assumptions and Sources'!$D$35)))+'3. Workings'!$E$34+'3. Workings'!$E$35)*'1. Assumptions and Sources'!$D$46-'3. Workings'!$E$65)>='3. Workings'!$D$55,'3. Workings'!$D$55/((('3. Workings'!$E$30+('3. Workings'!$E$31+'3. Workings'!$E$32+'3. Workings'!$E$33)*((1-(1-0.77)/(1-'1. Assumptions and Sources'!$D$35))/(1-(1-'1. Assumptions and Sources'!$D$36)/(1-'1. Assumptions and Sources'!$D$35)))+'3. Workings'!$E$34+'3. Workings'!$E$35)*'1. Assumptions and Sources'!$D$46-'3. Workings'!$E$65)/12),IF((('3. Workings'!$E$30+('3. Workings'!$E$31+'3. Workings'!$E$32+'3. Workings'!$E$33)*((1-(1-0.77)/(1-'1. Assumptions and Sources'!$D$35))/(1-(1-'1. Assumptions and Sources'!$D$36)/(1-'1. Assumptions and Sources'!$D$35)))+'3. Workings'!$E$34+'3. Workings'!$E$35)*'1. Assumptions and Sources'!$D$46-'3. Workings'!$E$65)+((('3. Workings'!$E$30+('3. Workings'!$E$31+'3. Workings'!$E$32+'3. Workings'!$E$33)*((1-(1-0.77)/(1-'1. Assumptions and Sources'!$D$35))/(1-(1-'1. Assumptions and Sources'!$D$36)/(1-'1. Assumptions and Sources'!$D$35)))+'3. Workings'!$E$34+'3. Workings'!$E$35)*'1. Assumptions and Sources'!$D$47-'3. Workings'!$E$65)*(1+'1. Assumptions and Sources'!$D$12))>='3. Workings'!$D$55,12+('3. Workings'!$D$55-(('3. Workings'!$E$30+('3. Workings'!$E$31+'3. Workings'!$E$32+'3. Workings'!$E$33)*((1-(1-0.77)/(1-'1. Assumptions and Sources'!$D$35))/(1-(1-'1. Assumptions and Sources'!$D$36)/(1-'1. Assumptions and Sources'!$D$35)))+'3. Workings'!$E$34+'3. Workings'!$E$35)*'1. Assumptions and Sources'!$D$46-'3. Workings'!$E$65))/(((('3. Workings'!$E$30+('3. Workings'!$E$31+'3. Workings'!$E$32+'3. Workings'!$E$33)*((1-(1-0.77)/(1-'1. Assumptions and Sources'!$D$35))/(1-(1-'1. Assumptions and Sources'!$D$36)/(1-'1. Assumptions and Sources'!$D$35)))+'3. Workings'!$E$34+'3. Workings'!$E$35)*'1. Assumptions and Sources'!$D$47-'3. Workings'!$E$65)*(1+'1. Assumptions and Sources'!$D$12))/12),IF((('3. Workings'!$E$30+('3. Workings'!$E$31+'3. Workings'!$E$32+'3. Workings'!$E$33)*((1-(1-0.77)/(1-'1. Assumptions and Sources'!$D$35))/(1-(1-'1. Assumptions and Sources'!$D$36)/(1-'1. Assumptions and Sources'!$D$35)))+'3. Workings'!$E$34+'3. Workings'!$E$35)*'1. Assumptions and Sources'!$D$46-'3. Workings'!$E$65)+((('3. Workings'!$E$30+('3. Workings'!$E$31+'3. Workings'!$E$32+'3. Workings'!$E$33)*((1-(1-0.77)/(1-'1. Assumptions and Sources'!$D$35))/(1-(1-'1. Assumptions and Sources'!$D$36)/(1-'1. Assumptions and Sources'!$D$35)))+'3. Workings'!$E$34+'3. Workings'!$E$35)*'1. Assumptions and Sources'!$D$47-'3. Workings'!$E$65)*(1+'1. Assumptions and Sources'!$D$12))+((('3. Workings'!$E$30+('3. Workings'!$E$31+'3. Workings'!$E$32+'3. Workings'!$E$33)*((1-(1-0.77)/(1-'1. Assumptions and Sources'!$D$35))/(1-(1-'1. Assumptions and Sources'!$D$36)/(1-'1. Assumptions and Sources'!$D$35)))+'3. Workings'!$E$34+'3. Workings'!$E$35)*'1. Assumptions and Sources'!$D$48-'3. Workings'!$E$65)*(1+'1. Assumptions and Sources'!$D$12)^2)>='3. Workings'!$D$55,24+('3. Workings'!$D$55-(('3. Workings'!$E$30+('3. Workings'!$E$31+'3. Workings'!$E$32+'3. Workings'!$E$33)*((1-(1-0.77)/(1-'1. Assumptions and Sources'!$D$35))/(1-(1-'1. Assumptions and Sources'!$D$36)/(1-'1. Assumptions and Sources'!$D$35)))+'3. Workings'!$E$34+'3. Workings'!$E$35)*'1. Assumptions and Sources'!$D$46-'3. Workings'!$E$65)-((('3. Workings'!$E$30+('3. Workings'!$E$31+'3. Workings'!$E$32+'3. Workings'!$E$33)*((1-(1-0.77)/(1-'1. Assumptions and Sources'!$D$35))/(1-(1-'1. Assumptions and Sources'!$D$36)/(1-'1. Assumptions and Sources'!$D$35)))+'3. Workings'!$E$34+'3. Workings'!$E$35)*'1. Assumptions and Sources'!$D$47-'3. Workings'!$E$65)*(1+'1. Assumptions and Sources'!$D$12)))/(((('3. Workings'!$E$30+('3. Workings'!$E$31+'3. Workings'!$E$32+'3. Workings'!$E$33)*((1-(1-0.77)/(1-'1. Assumptions and Sources'!$D$35))/(1-(1-'1. Assumptions and Sources'!$D$36)/(1-'1. Assumptions and Sources'!$D$35)))+'3. Workings'!$E$34+'3. Workings'!$E$35)*'1. Assumptions and Sources'!$D$48-'3. Workings'!$E$65)*(1+'1. Assumptions and Sources'!$D$12)^2)/12),"beyond 3 years"))) -> 19.542701 | J23: =(('3. Workings'!$E$31+'3. Workings'!$E$32+'3. Workings'!$E$33)*((1-(1-0.77)/(1-'1. Assumptions and Sources'!$D$35))/(1-(1-'1. Assumptions and Sources'!$D$36)/(1-'1. Assumptions and Sources'!$D$35)))+'3. Workings'!$E$30+'3. Workings'!$E$35-'3. Workings'!$E$65)/'3. Workings'!$E$79 -> 1.9236385 | K23: =G23-$G$20 -> -10.904105
C24: L3 Detection neutralised | D24: =0.62*100&"% detection" -> 62% detection | E24: ='3. Workings'!$E$19 -> 1.23 | F24: ='3. Workings'!$E$21 -> 2.55 | G24: =('3. Workings'!$E$30+('3. Workings'!$E$31+'3. Workings'!$E$32+'3. Workings'!$E$33)*((1-(1-0.62)/(1-'1. Assumptions and Sources'!$D$35))/(1-(1-'1. Assumptions and Sources'!$D$36)/(1-'1. Assumptions and Sources'!$D$35)))+'3. Workings'!$E$34+'3. Workings'!$E$35)-'3. Workings'!$E$65 -> 19.82424 | H24: ='3. Workings'!$D$55 -> 9.8904698 | I24: ='1. Assumptions and Sources'!$D$49+IF((('3. Workings'!$E$30+('3. Workings'!$E$31+'3. Workings'!$E$32+'3. Workings'!$E$33)*((1-(1-0.62)/(1-'1. Assumptions and Sources'!$D$35))/(1-(1-'1. Assumptions and Sources'!$D$36)/(1-'1. Assumptions and Sources'!$D$35)))+'3. Workings'!$E$34+'3. Workings'!$E$35)*'1. Assumptions and Sources'!$D$46-'3. Workings'!$E$65)>='3. Workings'!$D$55,'3. Workings'!$D$55/((('3. Workings'!$E$30+('3. Workings'!$E$31+'3. Workings'!$E$32+'3. Workings'!$E$33)*((1-(1-0.62)/(1-'1. Assumptions and Sources'!$D$35))/(1-(1-'1. Assumptions and Sources'!$D$36)/(1-'1. Assumptions and Sources'!$D$35)))+'3. Workings'!$E$34+'3. Workings'!$E$35)*'1. Assumptions and Sources'!$D$46-'3. Workings'!$E$65)/12),IF((('3. Workings'!$E$30+('3. Workings'!$E$31+'3. Workings'!$E$32+'3. Workings'!$E$33)*((1-(1-0.62)/(1-'1. Assumptions and Sources'!$D$35))/(1-(1-'1. Assumptions and Sources'!$D$36)/(1-'1. Assumptions and Sources'!$D$35)))+'3. Workings'!$E$34+'3. Workings'!$E$35)*'1. Assumptions and Sources'!$D$46-'3. Workings'!$E$65)+((('3. Workings'!$E$30+('3. Workings'!$E$31+'3. Workings'!$E$32+'3. Workings'!$E$33)*((1-(1-0.62)/(1-'1. Assumptions and Sources'!$D$35))/(1-(1-'1. Assumptions and Sources'!$D$36)/(1-'1. Assumptions and Sources'!$D$35)))+'3. Workings'!$E$34+'3. Workings'!$E$35)*'1. Assumptions and Sources'!$D$47-'3. Workings'!$E$65)*(1+'1. Assumptions and Sources'!$D$12))>='3. Workings'!$D$55,12+('3. Workings'!$D$55-(('3. Workings'!$E$30+('3. Workings'!$E$31+'3. Workings'!$E$32+'3. Workings'!$E$33)*((1-(1-0.62)/(1-'1. Assumptions and Sources'!$D$35))/(1-(1-'1. Assumptions and Sources'!$D$36)/(1-'1. Assumptions and Sources'!$D$35)))+'3. Workings'!$E$34+'3. Workings'!$E$35)*'1. Assumptions and Sources'!$D$46-'3. Workings'!$E$65))/(((('3. Workings'!$E$30+('3. Workings'!$E$31+'3. Workings'!$E$32+'3. Workings'!$E$33)*((1-(1-0.62)/(1-'1. Assumptions and Sources'!$D$35))/(1-(1-'1. Assumptions and Sources'!$D$36)/(1-'1. Assumptions and Sources'!$D$35)))+'3. Workings'!$E$34+'3. Workings'!$E$35)*'1. Assumptions and Sources'!$D$47-'3. Workings'!$E$65)*(1+'1. Assumptions and Sources'!$D$12))/12),IF((('3. Workings'!$E$30+('3. Workings'!$E$31+'3. Workings'!$E$32+'3. Workings'!$E$33)*((1-(1-0.62)/(1-'1. Assumptions and Sources'!$D$35))/(1-(1-'1. Assumptions and Sources'!$D$36)/(1-'1. Assumptions and Sources'!$D$35)))+'3. Workings'!$E$34+'3. Workings'!$E$35)*'1. Assumptions and Sources'!$D$46-'3. Workings'!$E$65)+((('3. Workings'!$E$30+('3. Workings'!$E$31+'3. Workings'!$E$32+'3. Workings'!$E$33)*((1-(1-0.62)/(1-'1. Assumptions and Sources'!$D$35))/(1-(1-'1. Assumptions and Sources'!$D$36)/(1-'1. Assumptions and Sources'!$D$35)))+'3. Workings'!$E$34+'3. Workings'!$E$35)*'1. Assumptions and Sources'!$D$47-'3. Workings'!$E$65)*(1+'1. Assumptions and Sources'!$D$12))+((('3. Workings'!$E$30+('3. Workings'!$E$31+'3. Workings'!$E$32+'3. Workings'!$E$33)*((1-(1-0.62)/(1-'1. Assumptions and Sources'!$D$35))/(1-(1-'1. Assumptions and Sources'!$D$36)/(1-'1. Assumptions and Sources'!$D$35)))+'3. Workings'!$E$34+'3. Workings'!$E$35)*'1. Assumptions and Sources'!$D$48-'3. Workings'!$E$65)*(1+'1. Assumptions and Sources'!$D$12)^2)>='3. Workings'!$D$55,24+('3. Workings'!$D$55-(('3. Workings'!$E$30+('3. Workings'!$E$31+'3. Workings'!$E$32+'3. Workings'!$E$33)*((1-(1-0.62)/(1-'1. Assumptions and Sources'!$D$35))/(1-(1-'1. Assumptions and Sources'!$D$36)/(1-'1. Assumptions and Sources'!$D$35)))+'3. Workings'!$E$34+'3. Workings'!$E$35)*'1. Assumptions and Sources'!$D$46-'3. Workings'!$E$65)-((('3. Workings'!$E$30+('3. Workings'!$E$31+'3. Workings'!$E$32+'3. Workings'!$E$33)*((1-(1-0.62)/(1-'1. Assumptions and Sources'!$D$35))/(1-(1-'1. Assumptions and Sources'!$D$36)/(1-'1. Assumptions and Sources'!$D$35)))+'3. Workings'!$E$34+'3. Workings'!$E$35)*'1. Assumptions and Sources'!$D$47-'3. Workings'!$E$65)*(1+'1. Assumptions and Sources'!$D$12)))/(((('3. Workings'!$E$30+('3. Workings'!$E$31+'3. Workings'!$E$32+'3. Workings'!$E$33)*((1-(1-0.62)/(1-'1. Assumptions and Sources'!$D$35))/(1-(1-'1. Assumptions and Sources'!$D$36)/(1-'1. Assumptions and Sources'!$D$35)))+'3. Workings'!$E$34+'3. Workings'!$E$35)*'1. Assumptions and Sources'!$D$48-'3. Workings'!$E$65)*(1+'1. Assumptions and Sources'!$D$12)^2)/12),"beyond 3 years"))) -> 23.918252 | J24: =(('3. Workings'!$E$31+'3. Workings'!$E$32+'3. Workings'!$E$33)*((1-(1-0.62)/(1-'1. Assumptions and Sources'!$D$35))/(1-(1-'1. Assumptions and Sources'!$D$36)/(1-'1. Assumptions and Sources'!$D$35)))+'3. Workings'!$E$30+'3. Workings'!$E$35-'3. Workings'!$E$65)/'3. Workings'!$E$79 -> 1.1632654 | K24: =G24-$G$20 -> -23.485766
B25: S3 Explainability requirement | C25: Not monetised | D25: n/a
B26: S4 Repair ecosystem digitisation | C26: L1 Unconnected | D26: 0% faster | E26: ='3. Workings'!$E$19 -> 1.23 | F26: ='3. Workings'!$E$21 -> 2.55 | G26: ='3. Workings'!$E$71 -> 43.310005 | H26: ='3. Workings'!$D$55 -> 9.8904698 | I26: ='1. Assumptions and Sources'!$D$49+IF(('3. Workings'!$E$36*'1. Assumptions and Sources'!$D$46-'3. Workings'!$E$65)>='3. Workings'!$D$55,'3. Workings'!$D$55/(('3. Workings'!$E$36*'1. Assumptions and Sources'!$D$46-'3. Workings'!$E$65)/12),IF(('3. Workings'!$E$36*'1. Assumptions and Sources'!$D$46-'3. Workings'!$E$65)+(('3. Workings'!$E$36*'1. Assumptions and Sources'!$D$47-'3. Workings'!$E$65)*(1+'1. Assumptions and Sources'!$D$12))>='3. Workings'!$D$55,12+('3. Workings'!$D$55-('3. Workings'!$E$36*'1. Assumptions and Sources'!$D$46-'3. Workings'!$E$65))/((('3. Workings'!$E$36*'1. Assumptions and Sources'!$D$47-'3. Workings'!$E$65)*(1+'1. Assumptions and Sources'!$D$12))/12),IF(('3. Workings'!$E$36*'1. Assumptions and Sources'!$D$46-'3. Workings'!$E$65)+(('3. Workings'!$E$36*'1. Assumptions and Sources'!$D$47-'3. Workings'!$E$65)*(1+'1. Assumptions and Sources'!$D$12))+(('3. Workings'!$E$36*'1. Assumptions and Sources'!$D$48-'3. Workings'!$E$65)*(1+'1. Assumptions and Sources'!$D$12)^2)>='3. Workings'!$D$55,24+('3. Workings'!$D$55-('3. Workings'!$E$36*'1. Assumptions and Sources'!$D$46-'3. Workings'!$E$65)-(('3. Workings'!$E$36*'1. Assumptions and Sources'!$D$47-'3. Workings'!$E$65)*(1+'1. Assumptions and Sources'!$D$12)))/((('3. Workings'!$E$36*'1. Assumptions and Sources'!$D$48-'3. Workings'!$E$65)*(1+'1. Assumptions and Sources'!$D$12)^2)/12),"beyond 3 years"))) -> 16.842971 | J26: ='3. Workings'!$E$82 -> 2.5826285 | K26: =G26-$G$20 -> 0
C27: L2 Partial API connectivity | D27: 25% faster | E27: ='3. Workings'!$E$19 -> 1.23 | F27: 2.16 | G27: ='3. Workings'!$E$71 -> 43.310005 | H27: ='3. Workings'!$D$55 -> 9.8904698 | I27: ='1. Assumptions and Sources'!$D$49+IF(('3. Workings'!$E$36*'1. Assumptions and Sources'!$D$46-'3. Workings'!$E$65)>='3. Workings'!$D$55,'3. Workings'!$D$55/(('3. Workings'!$E$36*'1. Assumptions and Sources'!$D$46-'3. Workings'!$E$65)/12),IF(('3. Workings'!$E$36*'1. Assumptions and Sources'!$D$46-'3. Workings'!$E$65)+(('3. Workings'!$E$36*'1. Assumptions and Sources'!$D$47-'3. Workings'!$E$65)*(1+'1. Assumptions and Sources'!$D$12))>='3. Workings'!$D$55,12+('3. Workings'!$D$55-('3. Workings'!$E$36*'1. Assumptions and Sources'!$D$46-'3. Workings'!$E$65))/((('3. Workings'!$E$36*'1. Assumptions and Sources'!$D$47-'3. Workings'!$E$65)*(1+'1. Assumptions and Sources'!$D$12))/12),IF(('3. Workings'!$E$36*'1. Assumptions and Sources'!$D$46-'3. Workings'!$E$65)+(('3. Workings'!$E$36*'1. Assumptions and Sources'!$D$47-'3. Workings'!$E$65)*(1+'1. Assumptions and Sources'!$D$12))+(('3. Workings'!$E$36*'1. Assumptions and Sources'!$D$48-'3. Workings'!$E$65)*(1+'1. Assumptions and Sources'!$D$12)^2)>='3. Workings'!$D$55,24+('3. Workings'!$D$55-('3. Workings'!$E$36*'1. Assumptions and Sources'!$D$46-'3. Workings'!$E$65)-(('3. Workings'!$E$36*'1. Assumptions and Sources'!$D$47-'3. Workings'!$E$65)*(1+'1. Assumptions and Sources'!$D$12)))/((('3. Workings'!$E$36*'1. Assumptions and Sources'!$D$48-'3. Workings'!$E$65)*(1+'1. Assumptions and Sources'!$D$12)^2)/12),"beyond 3 years"))) -> 16.842971 | J27: ='3. Workings'!$E$82 -> 2.5826285 | K27: =G27-$G$20 -> 0
C28: L3 Fully connected | D28: 50% faster | E28: ='3. Workings'!$E$19 -> 1.23 | F28: 1.76 | G28: ='3. Workings'!$E$71 -> 43.310005 | H28: ='3. Workings'!$D$55 -> 9.8904698 | I28: ='1. Assumptions and Sources'!$D$49+IF(('3. Workings'!$E$36*'1. Assumptions and Sources'!$D$46-'3. Workings'!$E$65)>='3. Workings'!$D$55,'3. Workings'!$D$55/(('3. Workings'!$E$36*'1. Assumptions and Sources'!$D$46-'3. Workings'!$E$65)/12),IF(('3. Workings'!$E$36*'1. Assumptions and Sources'!$D$46-'3. Workings'!$E$65)+(('3. Workings'!$E$36*'1. Assumptions and Sources'!$D$47-'3. Workings'!$E$65)*(1+'1. Assumptions and Sources'!$D$12))>='3. Workings'!$D$55,12+('3. Workings'!$D$55-('3. Workings'!$E$36*'1. Assumptions and Sources'!$D$46-'3. Workings'!$E$65))/((('3. Workings'!$E$36*'1. Assumptions and Sources'!$D$47-'3. Workings'!$E$65)*(1+'1. Assumptions and Sources'!$D$12))/12),IF(('3. Workings'!$E$36*'1. Assumptions and Sources'!$D$46-'3. Workings'!$E$65)+(('3. Workings'!$E$36*'1. Assumptions and Sources'!$D$47-'3. Workings'!$E$65)*(1+'1. Assumptions and Sources'!$D$12))+(('3. Workings'!$E$36*'1. Assumptions and Sources'!$D$48-'3. Workings'!$E$65)*(1+'1. Assumptions and Sources'!$D$12)^2)>='3. Workings'!$D$55,24+('3. Workings'!$D$55-('3. Workings'!$E$36*'1. Assumptions and Sources'!$D$46-'3. Workings'!$E$65)-(('3. Workings'!$E$36*'1. Assumptions and Sources'!$D$47-'3. Workings'!$E$65)*(1+'1. Assumptions and Sources'!$D$12)))/((('3. Workings'!$E$36*'1. Assumptions and Sources'!$D$48-'3. Workings'!$E$65)*(1+'1. Assumptions and Sources'!$D$12)^2)/12),"beyond 3 years"))) -> 16.842971 | J28: ='3. Workings'!$E$82 -> 2.5826285 | K28: =G28-$G$20 -> 0
B29: S5 Regulatory AI governance | C29: L1 No new rule | D29: +0% build | E29: ='3. Workings'!$E$19 -> 1.23 | F29: ='3. Workings'!$E$21 -> 2.55 | G29: ='3. Workings'!$E$71 -> 43.310005 | H29: =('3. Workings'!$D$55*(1+0)) -> 9.8904698 | I29: ='1. Assumptions and Sources'!$D$49+IF(('3. Workings'!$E$36*'1. Assumptions and Sources'!$D$46-'3. Workings'!$E$65)>=('3. Workings'!$D$55*(1+0)),('3. Workings'!$D$55*(1+0))/(('3. Workings'!$E$36*'1. Assumptions and Sources'!$D$46-'3. Workings'!$E$65)/12),IF(('3. Workings'!$E$36*'1. Assumptions and Sources'!$D$46-'3. Workings'!$E$65)+(('3. Workings'!$E$36*'1. Assumptions and Sources'!$D$47-'3. Workings'!$E$65)*(1+'1. Assumptions and Sources'!$D$12))>=('3. Workings'!$D$55*(1+0)),12+(('3. Workings'!$D$55*(1+0))-('3. Workings'!$E$36*'1. Assumptions and Sources'!$D$46-'3. Workings'!$E$65))/((('3. Workings'!$E$36*'1. Assumptions and Sources'!$D$47-'3. Workings'!$E$65)*(1+'1. Assumptions and Sources'!$D$12))/12),IF(('3. Workings'!$E$36*'1. Assumptions and Sources'!$D$46-'3. Workings'!$E$65)+(('3. Workings'!$E$36*'1. Assumptions and Sources'!$D$47-'3. Workings'!$E$65)*(1+'1. Assumptions and Sources'!$D$12))+(('3. Workings'!$E$36*'1. Assumptions and Sources'!$D$48-'3. Workings'!$E$65)*(1+'1. Assumptions and Sources'!$D$12)^2)>=('3. Workings'!$D$55*(1+0)),24+(('3. Workings'!$D$55*(1+0))-('3. Workings'!$E$36*'1. Assumptions and Sources'!$D$46-'3. Workings'!$E$65)-(('3. Workings'!$E$36*'1. Assumptions and Sources'!$D$47-'3. Workings'!$E$65)*(1+'1. Assumptions and Sources'!$D$12)))/((('3. Workings'!$E$36*'1. Assumptions and Sources'!$D$48-'3. Workings'!$E$65)*(1+'1. Assumptions and Sources'!$D$12)^2)/12),"beyond 3 years"))) -> 16.842971 | J29: ='3. Workings'!$E$82 -> 2.5826285 | K29: =G29-$G$20 -> 0
C30: L2 EU AI Act lower bound | D30: +15% build | E30: ='3. Workings'!$E$19 -> 1.23 | F30: ='3. Workings'!$E$21 -> 2.55 | G30: ='3. Workings'!$E$71 -> 43.310005 | H30: =('3. Workings'!$D$55*(1+0.15)) -> 11.37404 | I30: ='1. Assumptions and Sources'!$D$49+IF(('3. Workings'!$E$36*'1. Assumptions and Sources'!$D$46-'3. Workings'!$E$65)>=('3. Workings'!$D$55*(1+0.15)),('3. Workings'!$D$55*(1+0.15))/(('3. Workings'!$E$36*'1. Assumptions and Sources'!$D$46-'3. Workings'!$E$65)/12),IF(('3. Workings'!$E$36*'1. Assumptions and Sources'!$D$46-'3. Workings'!$E$65)+(('3. Workings'!$E$36*'1. Assumptions and Sources'!$D$47-'3. Workings'!$E$65)*(1+'1. Assumptions and Sources'!$D$12))>=('3. Workings'!$D$55*(1+0.15)),12+(('3. Workings'!$D$55*(1+0.15))-('3. Workings'!$E$36*'1. Assumptions and Sources'!$D$46-'3. Workings'!$E$65))/((('3. Workings'!$E$36*'1. Assumptions and Sources'!$D$47-'3. Workings'!$E$65)*(1+'1. Assumptions and Sources'!$D$12))/12),IF(('3. Workings'!$E$36*'1. Assumptions and Sources'!$D$46-'3. Workings'!$E$65)+(('3. Workings'!$E$36*'1. Assumptions and Sources'!$D$47-'3. Workings'!$E$65)*(1+'1. Assumptions and Sources'!$D$12))+(('3. Workings'!$E$36*'1. Assumptions and Sources'!$D$48-'3. Workings'!$E$65)*(1+'1. Assumptions and Sources'!$D$12)^2)>=('3. Workings'!$D$55*(1+0.15)),24+(('3. Workings'!$D$55*(1+0.15))-('3. Workings'!$E$36*'1. Assumptions and Sources'!$D$46-'3. Workings'!$E$65)-(('3. Workings'!$E$36*'1. Assumptions and Sources'!$D$47-'3. Workings'!$E$65)*(1+'1. Assumptions and Sources'!$D$12)))/((('3. Workings'!$E$36*'1. Assumptions and Sources'!$D$48-'3. Workings'!$E$65)*(1+'1. Assumptions and Sources'!$D$12)^2)/12),"beyond 3 years"))) -> 17.869416 | J30: ='3. Workings'!$E$82 -> 2.5826285 | K30: =G30-$G$20 -> 0
C31: L3 EU AI Act upper bound | D31: +20% build | E31: ='3. Workings'!$E$19 -> 1.23 | F31: ='3. Workings'!$E$21 -> 2.55 | G31: ='3. Workings'!$E$71 -> 43.310005 | H31: =('3. Workings'!$D$55*(1+0.2)) -> 11.868564 | I31: ='1. Assumptions and Sources'!$D$49+IF(('3. Workings'!$E$36*'1. Assumptions and Sources'!$D$46-'3. Workings'!$E$65)>=('3. Workings'!$D$55*(1+0.2)),('3. Workings'!$D$55*(1+0.2))/(('3. Workings'!$E$36*'1. Assumptions and Sources'!$D$46-'3. Workings'!$E$65)/12),IF(('3. Workings'!$E$36*'1. Assumptions and Sources'!$D$46-'3. Workings'!$E$65)+(('3. Workings'!$E$36*'1. Assumptions and Sources'!$D$47-'3. Workings'!$E$65)*(1+'1. Assumptions and Sources'!$D$12))>=('3. Workings'!$D$55*(1+0.2)),12+(('3. Workings'!$D$55*(1+0.2))-('3. Workings'!$E$36*'1. Assumptions and Sources'!$D$46-'3. Workings'!$E$65))/((('3. Workings'!$E$36*'1. Assumptions and Sources'!$D$47-'3. Workings'!$E$65)*(1+'1. Assumptions and Sources'!$D$12))/12),IF(('3. Workings'!$E$36*'1. Assumptions and Sources'!$D$46-'3. Workings'!$E$65)+(('3. Workings'!$E$36*'1. Assumptions and Sources'!$D$47-'3. Workings'!$E$65)*(1+'1. Assumptions and Sources'!$D$12))+(('3. Workings'!$E$36*'1. Assumptions and Sources'!$D$48-'3. Workings'!$E$65)*(1+'1. Assumptions and Sources'!$D$12)^2)>=('3. Workings'!$D$55*(1+0.2)),24+(('3. Workings'!$D$55*(1+0.2))-('3. Workings'!$E$36*'1. Assumptions and Sources'!$D$46-'3. Workings'!$E$65)-(('3. Workings'!$E$36*'1. Assumptions and Sources'!$D$47-'3. Workings'!$E$65)*(1+'1. Assumptions and Sources'!$D$12)))/((('3. Workings'!$E$36*'1. Assumptions and Sources'!$D$48-'3. Workings'!$E$65)*(1+'1. Assumptions and Sources'!$D$12)^2)/12),"beyond 3 years"))) -> 18.211565 | J31: ='3. Workings'!$E$82 -> 2.5826285 | K31: =G31-$G$20 -> 0
B33: PART C — COMPOUND STRESS TEST · all three quantified threats at once
B35: Lever | C35: Base | D35: Compound severe
B36: Auto-settlement share | C36: 65% | D36: 50%
B37: Fraud detection achieved | C37: 90% | D37: 62% (full revert to rule-based)
B38: Build cost, Rs Cr | C38: 9.89 | D38: 11.87
B40: NET ANNUAL BENEFIT, Rs Cr | C40: 38.62 | D40: 15.95
B41: PAYBACK, steady state, months | C41: 3.07 | D41: 8.9
B42: COMBINED RATIO, Motor OD, pp | C42: 2.57 | D42: 1.04
B44: There is no combination of the researched scenarios in which ClaimPulse fails to return its capital inside a year of steady-state operation.
B46: PART D — WHAT THE SCENARIOS ACTUALLY TELL US
B48: 1. Only ONE scenario genuinely threatens the case, and it is the one the platform was built around. If synthetic evidence defeats detection entirely, net benefit falls 54% to Rs 17.58 Cr and still pays back in under seven months.
B49: 2. Faster repair partners improve the CUSTOMER outcome and change our economics by nothing. TAT 2.55 to 1.76 days, net benefit unchanged. We keep it out of the investment case.
B50: 3. Regulatory tightening is affordable. The EU AI Act upper-bound overlay moves payback from 3.1 to 3.7 months.
B51: 4. Digital-first acceleration is a tailwind, not a rescue. 65% to 78% auto-settlement adds Rs 1.41 Cr a year.
B52: 5. Scenario 3 carries no rupee figure because no credible source prices an explainability obligation for Indian motor. Grievance-cost exposure of Rs 2.81 Cr a year is shown in the report as an order of magnitude only.
B54: SCOPE NOTE. Every row in Part B is computed on the current Rs 9.89 Cr build and ties to the live model on all six anchors in Part A. Part E is the underlying scenario library; read its mechanisms and its direction of travel, and take every rupee figure from Parts A to D.
B58: PART E — FOUR-ENGINE SCENARIO LIBRARY · every scenario tested across the four research engines
B59: Parts A to D are the LIVE model. Part E is the scenario library behind them, consolidated across the four research domains. Take every rupee figure from Parts A to D.
B60: Engine | C60: Scenario | D60: Grading | E60: Mechanism tested | F60: Worst case tested | G60: Result at worst case | H60: Breached?
B61: Customer (origin architecture) | C61: R1 Experience-Parity and Digital Evidence Abundance | D61: G1-G4 | E61: Speed expectation accelerates while capture and CV capability rise. Can more digital evidence be converted into TRUSTED straight-through processing? | F61: G4 Transformational | G61: Positive throughout | H61: No
B62: Customer | C62: R2 Conditional-Autonomy Equilibrium | D62: G1-G4 | E62: Automation frontier set by permission rather than capability. What AI is ALLOWED to decide, not what it can do | F62: G4 Transformational | G62: Positive; governance cost absorbed | H62: No
B63: Customer | C63: R3 Adversarial AI Equilibrium | D63: G1-G4 | E63: The adversarial gap: detection capability minus generation capability. Full reversion to the 62% rule-based baseline | F63: G4 Extreme | G63: Rs 1.49 Cr per month, Rs 17.92 Cr per year, still positive | H63: No
B64: Customer | C64: R4 Commoditisation-Moat Transition | D64: G1-G4 | E64: AI capability commoditises; the moat has to move from model to data and workflow | F64: G4 Transformational | G64: Positive; cost deflation is a tailwind | H64: No
B65: Technology | C65: S1 Autonomous Claims Market | D65: Base to Extreme | E65: Agentic orchestration matures and automation depth rises across the market | F65: Extreme | G65: Positive | H65: No
B66: Technology | C66: S2 Adversarial Digital Claim | D66: Base to Extreme | E66: Synthetic evidence defeats detection, with capacity realisation and incremental cost also applied | F66: Extreme | G66: Rs 0.132 Cr per month, near zero | H66: Thin cushion, 2.45pp of 14.06pp
B67: Technology | C67: S3 Data-Rich, Trust-Constrained Market | D67: Base to Extreme | E67: Evidence volume rises but consent and governance restrict what is usable | F67: Extreme | G67: Positive | H67: No
B68: Technology | C68: W8 COMBINED STRESS TEST | D68: Base to Extreme | E68: All three technology regimes move together. Automation depth, capacity and fraud detection collapse simultaneously | F68: Extreme | G68: MINUS Rs 0.531 Cr per month, NEGATIVE | H68: YES - both STP and fraud-detection breakpoints breached
B69: Technology | C69: T1 AI Commoditisation | D69: Base, G1-G4 | E69: Inference and model cost deflation, cost side only | F69: G4 | G69: Positive, upside only | H69: No
B70: Technology | C70: T2 Live-Capture Evidence Heterogeneity | D70: Base, G1-G4 | E70: Evidence arrives in more formats and qualities than the gate was built for | F70: G4 | G70: Positive | H70: No
B71: Technology | C71: T3 Adversarial Evidence, live-video attack surface | D71: Base, G1-G4 | E71: Attack moves from still images to live capture | F71: G4 | G71: Positive but thinning | H71: No
... B84: Industrial | C84: S4 Claims-Ecosystem and Data Transformation | D84: G1-G4 qualitative | E84: Evidence architecture shifts under DPDP consent rules and live-capture mandates | F84: G4 Fundamental evidence architecture shift | G84: Not quantified, bounded | H84: No
B86: PART F — CROSS-ENGINE SYNTHESIS · what survives being attacked from four directions
B87: F1. THE STRONGEST CLAIM. The labour and processing engine carries the case on its own, with zero fraud-detection lift. On the current Rs 9.89 Cr engine the zero-fraud floor is a net Rs 3.20 Cr a year and the build still repays.
B88: Engine | C88: Where it appears | D88: Figure cited by that engine
B89: Customer | C89: R3 Adversarial AI Equilibrium, G4 | D89: Rs 17.92 Cr per year even at full reversion to the 62% baseline
B90: Technology | C90: S2 Adversarial Digital Claim, Severe | D90: Rs 1.251 Cr per month, a harder test because it also applies capacity realisation and incremental cost
B91: Social | C91: Sc2 Synthetic Fraud Arms Race, Level 3 | D91: Labour-only engine still shows a 3.24-month payback at zero fraud benefit
B92: Industrial | C92: S3 Adversarial Claims, G4 | D92: Payback approaches the labour-only floor of 3.24 months
B94: F2. THE ONLY FAILURE MODE. Across all four engines and every grade and level tested, exactly one case turns net benefit negative: the Technology engine's W8 Combined Stress Test at Extreme, at minus Rs 0.531 Cr per month. The model does not fail under any single-mechanism shock, however severe. It fails only when automation depth, human capacity and fraud detection collapse at the same time. That is the honest boundary of the case, and it should be stated rather than hidden.
B96: F3. THE PROJECT-WIDE EVIDENCE GAP. Synthetic-media incidence in Indian motor claims has no source anywhere. All four engines rediscovered this independently (Customer E31, Technology TE05 and TE08, Social Scenario 2, Industrial IE03) and it sits underneath the highest-consequence downside scenario in every one of them. This is the single data point that would most strengthen the submission if it could be obtained.
B98: F4. THE BREAKPOINT NOBODY MODELLED. The human exception-handling capacity ceiling is flagged by two engines as the constraint most likely to bind first, and is modelled by none of them. It needs Bajaj claims-operations data. This is the most actionable near-term request in the entire project.
B100: PART G — PROVENANCE AND REBASING · why Parts A to D supersede the research engines
B101: Parts A to D of this sheet are computed on the current Rs 9.89 Cr engine and tie to the live model on all six anchors in Part A. Part E carries the scenario mechanisms.
B102: Figure | C102: Carried in | D102: Stale value | E102: Current canonical value
B103: Build cost, one-off | C103: Technology, Customer engines | D103: Rs 5.2874 Cr | E103: Rs 9.8905 Cr
B104: Build cost, one-off | C104: Social engine | D104: Rs 2.5 Cr | E104: Rs 9.8905 Cr - was doubly stale, the engine had already flagged itself
B105: Net monthly benefit, Base | C105: Technology, Customer engines | D105: Rs 3.140 Cr | E105: Rs 3.2187 Cr
B106: Net annual benefit, Base | C106: Social engine | D106: Rs 26.16 Cr | E106: Rs 38.62 Cr
B107: Steady-state payback, Base | C107: Technology, Customer engines | D107: 1.68 months | E107: 3.073 months
B108: Steady-state payback, Base | C108: Social engine | D108: 1.147 months | E108: 3.073 months
B109: Fraud leakage rate | C109: Social engine base case | D109: 1.2% | E109: 3.42% - carried consistently across the scenario library
B110: Platform run cost | C110: Social engine | D110: Rs 8.00 L per month | E110: About Rs 28.96 L per month
B111: NEP / GWP basis | C111: All engines | D111: 49.88% | E111: The live model runs the filed FY2026 basis at A-02. Sheet 1 Table P and Sheet 3 Part M carry all three bases.
B113: Two contradictions inside the source engines were found and are recorded here so they are not quoted by accident. First, the Bajaj on-the-spot settlement band appears as both sub-Rs 20,000 and sub-Rs 30,000 in adjacent cells of the same file. Second, steady-state payback appears as both 1.7 months and 3.24 months in two engines that cite the same workbook. Neither figure should be quoted from the engines. Use Part A of this sheet.
B115: PART H — COMPETITIVE CONVERGENCE · bounded rather than point-estimated
B116: Competitive AI convergence, meaning a rival matching the full ClaimPulse pipeline, is the single largest expected-loss line in our own risk model at 50% probability and 15% benefit erosion from year 2, a 7.5% expected loss. It is graded qualitatively by the Industrial engine and is NOT quantified as a financial scenario anywhere, including in Parts B and C above, which move technology, regulatory and behavioural levers but not a competitive one.
B117: Why it is bounded rather than point-estimated: erosion depends on a rival’s rollout pace and pricing response, neither of which is observable. A point estimate here would be an assumption presented as a scenario.
B118: What bounds it instead: the fraud-detection scenarios in Part B already test benefit erosion of 25% and 54% from a different cause. A 15% competitive erosion sits inside the range the model is shown to survive, at S2 Level 2 or milder. The case does not depend on the gap being closed, but the gap is real and we would rather name it than be asked about it.

Sheet 9. Landscape Impact
B2: Landscape Impact · what each scenario does to the wider industrial and business landscape
B3: HEADLINE. Across 17 scenarios and four research engines, the landscape analysis converges on one conclusion: speed is not the moat. TAT-based differentiation compresses industry-wide as every insurer chases the same benchmark, and every engine independently relocates the durable advantage to the same four places - proprietary claims data, garage and ecosystem relationships, governance built ahead of the mandate, and the ability to retrain faster than an adversary. The scenario that looks financially benign, commoditisation, is the one that threatens the moat most.
B4: SECOND HEADLINE. Regulatory tightening is not a competitive threat. Three separate engines reach the same finding: because an IRDAI constraint applies to every insurer simultaneously, ClaimPulse's RELATIVE position is preserved even as its absolute automation ceiling falls. Regulation compresses payback, not the value proposition.
B5: STRUCTURE. The four engines produced 17 scenarios, several of which are the same structural event seen through a different lens. They are grouped below by theme so each theme is read once, with each engine's distinct contribution kept underneath it. Every cell is carried over in full; nothing is summarised away. Escalation rows state how each scenario intensifies from its mildest to its most severe grade.
B6: SCOPE ON FIGURES. This sheet carries the landscape mechanisms and their direction of travel. Every rupee, NPV and payback figure quoted in the deck comes from Sheets 3, 4 and 5, which run the current Rs 9.89 Cr engine.
B8: THEME 1 — EXPERIENCE PARITY AND DIGITAL VISIBILITY
B9: Speed expectation is set outside insurance, by UPI and e-commerce. Insurers do not control the benchmark.
B11: R1 — Experience-Parity Claims Market (+ Evidence Abundance) | C11: Customer engine
B12: Escalation | C12: G1: digital volume +15%, Green -3pp. G4: digital volume +50%, Green -10pp. The landscape shift intensifies with digital-channel maturity, not with any single regulatory or technology trigger.
